Workbook

Sheet READ ME
B1: This template is designed to get you started in your import to coinledger
B2: As we do not know your circumstances or the tax advice that you have received please modify it to suit your circumstances
B3: all income is classified as Income (could be miner or staker dividends)
B4: The Taostats_CSV transaction Type of Fee will be imported as Merchant Payment - once Imported it will need
B5: fee | C5: Merchant Payment
B7: Any extrinsic that has more than one credit, one debit and a "fee" must be manually changed (e.g. batch or portfolio rebalance)
B8: You will also have to work with Coinledger to work out how to get the cost basis for income received in each subnet (as at 2026-03-08)
A10: Instructions:
A11: 1 | B11: Copy paste the contents of every csv into the Taostats_CSV tab
A12: 2 | B12: Make sure that the additional columns after blank in the Taostats_CSV column are copied down to match the number of rows imported
C13: The Sort Order is optional - It reorders to increasing block order
C14: The Lookup Helper is not optional - it is necessary for the tab website_csv(pro) to work
A15: 3 | B15: Optional Sort Taostats_CSV using the Sort Order
A16: 4 | B16: On the website_csv(pro) - Copy the 2nd row down on the sheet for as many rows are you have in the Taostats_CSV
A17: 5 | B17: Filter the rows using Check Row (column T) for any TRUE and correct the error in the Taostats_CSV tab
A18: 6 | B18: Filter Rows using Import Row = TRUE for the rows to be imported
A19: 7 | B19: on website_csv(pro) Check the Column AG and AH for error highlight - must be zero or the maths is wrong somewhere
A20: 8 | B20: on website_csv(pro) copy the values from column titles Date through to Tag to a csv file (the other columns can be copies - they will be ignored as the column title does not match)
A22: Method to import Batches
A23: 1 | B23: Filter the Taostats_CSV sheet using Count of extrinsic >3 (most batches)
A24: 2 | B24: Search for the extrinsic on Taostats
C25: Using the StakeRemoved Event will point you towards the correct match - but be aware you might have to sum some of them
A26: 3 | B26: Manually join the two sides of the transaction together by appending to the Extrinsic-ID a letter or number e.g. 5013009-0009 -> 5013009-0009-A
A27: 4 | B27: The website_csv(pro) tab will merge the transactions together for you - see example below
A29: Notes:
A30: 1 | B30: Each Taostats_CSV includes the opening balance - this is for verification purposes with accounting software balance - this row is usually not imported
A31: 2 | B31: Again a warning - batch transactions you have to work it out yourself
A32: 3 | B32: Again a warning - After a CoinLedger import you must review the transactions and ensure that the cost basis is correct
A34: valid tags for CoinLedger
A35: source for types | B35: https://help.coinledger.io/en/articles/8546372-what-transaction-types-does-coinledger-support
A36: import instructions | B36: https://help.coinledger.io/en/articles/6028758-universal-manual-import-template-guide
B39: Batch
B49: is converted to website_csv(pro)

Sheet Taostats_CSV
A2: Coldkey | B2: Block number | C2: Timestamp | D2: Network | E2: Token | F2: Transaction type | G2: Debit amount | H2: Credit amount | I2: Extrinsic ID | J2: Additional data | K2: Total balance | L2: Free balance | M2: Staked balance | N2: Locked balance | O2: Reserved balance | P2: Token price in USD | Q2: Token price in TAO | R2: Daily income | S2: Daily income USD | T2: Date | U2: blank | V2: Sort Order | W2: Count of extrinsic | X2: Lookup Helper | Y2: Net Amount (for a pivot table)
A3: 5Eq8C1NoLah4DaahQLMQ6wPLTSiAoiP35kVs9VMjaEqcSmdF | B3: 4605427 | C3: 2024-12-31T23:59:48+00:00 | D3: finney | E3: TAO | K3: 256.53009 | L3: 2.6901865 | M3: 253.8399 | N3: 0 | O3: 0 | P3: 439.7119272666333 | Q3: 1 | R3: 256.53009 | V3: ="S-"&IF(LEN(I3)=0,B3,I3&IF(F3="fee","-00",IF(LEN(G3)>0,"-01","-02"))) -> S-4605427 | W3: =COUNTIF(I:I,I3) -> 0 | X3: =IF(LEN(I3)>0,I3&IF(F3="fee","fee",IF(VALUE(G3)>0,"debit",IF(VALUE(H3)>0,"credit","error"))),"") | Y3: =ROUND(IF(ROW(U3) = 2,K3,0)+IF(H3<>"",H3,0) + IF(R3<>"",R3,0) - IF(G3<>"",G3,0),9) -> 256.53009
A4: 5Eq8C1NoLah4DaahQLMQ6wPLTSiAoiP35kVs9VMjaEqcSmdF | B4: 4612627 | C4: 2025-01-01T23:59:48+00:00 | D4: finney | E4: TAO | K4: 256.66097 | L4: 2.6901865 | M4: 253.97079 | N4: 0 | O4: 0 | P4: 487.3709307352656 | Q4: 1 | R4: 0.13088539 | S4: 63.78 | T4: 45658 | V4: ="S-"&IF(LEN(I4)=0,B4,I4&IF(F4="fee","-00",IF(LEN(G4)>0,"-01","-02"))) -> S-4612627 | W4: =COUNTIF(I:I,I4) -> 0 | X4: =IF(LEN(I4)>0,I4&IF(F4="fee","fee",IF(VALUE(G4)>0,"debit",IF(VALUE(H4)>0,"credit","error"))),"") | Y4: =ROUND(IF(ROW(U4) = 2,K4,0)+IF(H4<>"",H4,0) + IF(R4<>"",R4,0) - IF(G4<>"",G4,0),9) -> 0.13088539
A5: 5Eq8C1NoLah4DaahQLMQ6wPLTSiAoiP35kVs9VMjaEqcSmdF | B5: 4619827 | C5: 2025-01-02T23:59:48+00:00 | D5: finney | E5: TAO | K5: 256.77263 | L5: 2.6901865 | M5: 254.08245 | N5: 0 | O5: 0 | P5: 522.0907380013595 | Q5: 1 | R5: 0.11166127 | S5: 58.29 | T5: 45659 | V5: ="S-"&IF(LEN(I5)=0,B5,I5&IF(F5="fee","-00",IF(LEN(G5)>0,"-01","-02"))) -> S-4619827 | W5: =COUNTIF(I:I,I5) -> 0 | X5: =IF(LEN(I5)>0,I5&IF(F5="fee","fee",IF(VALUE(G5)>0,"debit",IF(VALUE(H5)>0,"credit","error"))),"") | Y5: =ROUND(IF(ROW(U5) = 2,K5,0)+IF(H5<>"",H5,0) + IF(R5<>"",R5,0) - IF(G5<>"",G5,0),9) -> 0.11166127
A6: 5Eq8C1NoLah4DaahQLMQ6wPLTSiAoiP35kVs9VMjaEqcSmdF | B6: 4627027 | C6: 2025-01-03T23:59:48+00:00 | D6: finney | E6: TAO | K6: 256.88524 | L6: 2.6901865 | M6: 254.19506 | N6: 0 | O6: 0 | P6: 551.3484249315601 | Q6: 1 | R6: 0.1126101 | S6: 62.08 | T6: 45660 | V6: ="S-"&IF(LEN(I6)=0,B6,I6&IF(F6="fee","-00",IF(LEN(G6)>0,"-01","-02"))) -> S-4627027 | W6: =COUNTIF(I:I,I6) -> 0 | X6: =IF(LEN(I6)>0,I6&IF(F6="fee","fee",IF(VALUE(G6)>0,"debit",IF(VALUE(H6)>0,"credit","error"))),"") | Y6: =ROUND(IF(ROW(U6) = 2,K6,0)+IF(H6<>"",H6,0) + IF(R6<>"",R6,0) - IF(G6<>"",G6,0),9) -> 0.1126101
A7: 5Eq8C1NoLah4DaahQLMQ6wPLTSiAoiP35kVs9VMjaEqcSmdF | B7: 4634227 | C7: 2025-01-04T23:59:48+00:00 | D7: finney | E7: TAO | K7: 256.99636 | L7: 2.6901865 | M7: 254.30617 | N7: 0 | O7: 0 | P7: 561.8861556228987 | Q7: 1 | R7: 0.11111491 | S7: 62.43 | T7: 45661 | V7: ="S-"&IF(LEN(I7)=0,B7,I7&IF(F7="fee","-00",IF(LEN(G7)>0,"-01","-02"))) -> S-4634227 | W7: =COUNTIF(I:I,I7) -> 0 | X7: =IF(LEN(I7)>0,I7&IF(F7="fee","fee",IF(VALUE(G7)>0,"debit",IF(VALUE(H7)>0,"credit","error"))),"") | Y7: =ROUND(IF(ROW(U7) = 2,K7,0)+IF(H7<>"",H7,0) + IF(R7<>"",R7,0) - IF(G7<>"",G7,0),9) -> 0.11111491
A8: 5Eq8C1NoLah4DaahQLMQ6wPLTSiAoiP35kVs9VMjaEqcSmdF | B8: 4641427 | C8: 2025-01-05T23:59:48+00:00 | D8: finney | E8: TAO | K8: 257.109 | L8: 2.6901865 | M8: 254.41881 | N8: 0 | O8: 0 | P8: 566.19555 | Q8: 1 | R8: 0.11264267 | S8: 63.77 | T8: 45662 | V8: ="S-"&IF(LEN(I8)=0,B8,I8&IF(F8="fee","-00",IF(LEN(G8)>0,"-01","-02"))) -> S-4641427 | W8: =COUNTIF(I:I,I8) -> 0 | X8: =IF(LEN(I8)>0,I8&IF(F8="fee","fee",IF(VALUE(G8)>0,"debit",IF(VALUE(H8)>0,"credit","error"))),"") | Y8: =ROUND(IF(ROW(U8) = 2,K8,0)+IF(H8<>"",H8,0) + IF(R8<>"",R8,0) - IF(G8<>"",G8,0),9) -> 0.11264267
A9: 5Eq8C1NoLah4DaahQLMQ6wPLTSiAoiP35kVs9VMjaEqcSmdF | B9: 4648627 | C9: 2025-01-06T23:59:48+00:00 | D9: finney | E9: TAO | K9: 257.22522 | L9: 2.6901865 | M9: 254.53503 | N9: 0 | O9: 0 | P9: 555.4454806317118 | Q9: 1 | R9: 0.11621987 | S9: 64.55 | T9: 45663 | V9: ="S-"&IF(LEN(I9)=0,B9,I9&IF(F9="fee","-00",IF(LEN(G9)>0,"-01","-02"))) -> S-4648627 | W9: =COUNTIF(I:I,I9) -> 0 | X9: =IF(LEN(I9)>0,I9&IF(F9="fee","fee",IF(VALUE(G9)>0,"debit",IF(VALUE(H9)>0,"credit","error"))),"") | Y9: =ROUND(IF(ROW(U9) = 2,K9,0)+IF(H9<>"",H9,0) + IF(R9<>"",R9,0) - IF(G9<>"",G9,0),9) -> 0.11621987
A10: 5Eq8C1NoLah4DaahQLMQ6wPLTSiAoiP35kVs9VMjaEqcSmdF | B10: 4655827 | C10: 2025-01-07T23:59:48+00:00 | D10: finney | E10: TAO | K10: 257.34256 | L10: 2.6901865 | M10: 254.65237 | N10: 0 | O10: 0 | P10: 501.76673194932215 | Q10: 1 | R10: 0.11733869 | S10: 58.87 | T10: 45664 | V10: ="S-"&IF(LEN(I10)=0,B10,I10&IF(F10="fee","-00",IF(LEN(G10)>0,"-01","-02"))) -> S-4655827 | W10: =COUNTIF(I:I,I10) -> 0 | X10: =IF(LEN(I10)>0,I10&IF(F10="fee","fee",IF(VALUE(G10)>0,"debit",IF(VALUE(H10)>0,"credit","error"))),"") | Y10: =ROUND(IF(ROW(U10) = 2,K10,0)+IF(H10<>"",H10,0) + IF(R10<>"",R10,0) - IF(G10<>"",G10,0),9) -> 0.11733869
A11: 5Eq8C1NoLah4DaahQLMQ6wPLTSiAoiP35kVs9VMjaEqcSmdF | B11: 4663027 | C11: 2025-01-08T23:59:48+00:00 | D11: finney | E11: TAO | K11: 257.45859 | L11: 2.6901865 | M11: 254.76841 | N11: 0 | O11: 0 | P11: 468.2963637012752 | Q11: 1 | R11: 0.11603302 | S11: 54.33 | T11: 45665 | V11: ="S-"&IF(LEN(I11)=0,B11,I11&IF(F11="fee","-00",IF(LEN(G11)>0,"-01","-02"))) -> S-4663027 | W11: =COUNTIF(I:I,I11) -> 0 | X11: =IF(LEN(I11)>0,I11&IF(F11="fee","fee",IF(VALUE(G11)>0,"debit",IF(VALUE(H11)>0,"credit","error"))),"") | Y11: =ROUND(IF(ROW(U11) = 2,K11,0)+IF(H11<>"",H11,0) + IF(R11<>"",R11,0) - IF(G11<>"",G11,0),9) -> 0.11603302
A12: 5Eq8C1NoLah4DaahQLMQ6wPLTSiAoiP35kVs9VMjaEqcSmdF | B12: 4670227 | C12: 2025-01-09T23:59:48+00:00 | D12: finney | E12: TAO | K12: 257.56864 | L12: 2.6901865 | M12: 254.87845 | N12: 0 | O12: 0 | P12: 431.32496169673266 | Q12: 1 | R12: 0.11004859 | S12: 47.46 | T12: 45666 | V12: ="S-"&IF(LEN(I12)=0,B12,I12&IF(F12="fee","-00",IF(LEN(G12)>0,"-01","-02"))) -> S-4670227 | W12: =COUNTIF(I:I,I12) -> 0 | X12: =IF(LEN(I12)>0,I12&IF(F12="fee","fee",IF(VALUE(G12)>0,"debit",IF(VALUE(H12)>0,"credit","error"))),"") | Y12: =ROUND(IF(ROW(U12) = 2,K12,0)+IF(H12<>"",H12,0) + IF(R12<>"",R12,0) - IF(G12<>"",G12,0),9) -> 0.11004859
A13: 5Eq8C1NoLah4DaahQLMQ6wPLTSiAoiP35kVs9VMjaEqcSmdF | B13: 4677427 | C13: 2025-01-10T23:59:48+00:00 | D13: finney | E13: TAO | K13: 257.67884 | L13: 2.6901865 | M13: 254.98865 | N13: 0 | O13: 0 | P13: 440.5970263845009 | Q13: 1 | R13: 0.11019781 | S13: 48.55 | T13: 45667 | V13: ="S-"&IF(LEN(I13)=0,B13,I13&IF(F13="fee","-00",IF(LEN(G13)>0,"-01","-02"))) -> S-4677427 | W13: =COUNTIF(I:I,I13) -> 0 | X13: =IF(LEN(I13)>0,I13&IF(F13="fee","fee",IF(VALUE(G13)>0,"debit",IF(VALUE(H13)>0,"credit","error"))),"") | Y13: =ROUND(IF(ROW(U13) = 2,K13,0)+IF(H13<>"",H13,0) + IF(R13<>"",R13,0) - IF(G13<>"",G13,0),9) -> 0.11019781
A14: 5Eq8C1NoLah4DaahQLMQ6wPLTSiAoiP35kVs9VMjaEqcSmdF | B14: 4684626 | C14: 2025-01-11T23:59:48+00:00 | D14: finney | E14: TAO | K14: 257.7909 | L14: 2.6901865 | M14: 255.10071 | N14: 0 | O14: 0 | P14: 447.6506990278048 | Q14: 1 | R14: 0.11206236 | S14: 50.16 | T14: 45668 | V14: ="S-"&IF(LEN(I14)=0,B14,I14&IF(F14="fee","-00",IF(LEN(G14)>0,"-01","-02"))) -> S-4684626 | W14: =COUNTIF(I:I,I14) -> 0 | X14: =IF(LEN(I14)>0,I14&IF(F14="fee","fee",IF(VALUE(G14)>0,"debit",IF(VALUE(H14)>0,"credit","error"))),"") | Y14: =ROUND(IF(ROW(U14) = 2,K14,0)+IF(H14<>"",H14,0) + IF(R14<>"",R14,0) - IF(G14<>"",G14,0),9) -> 0.11206236
A15: 5Eq8C1NoLah4DaahQLMQ6wPLTSiAoiP35kVs9VMjaEqcSmdF | B15: 4691826 | C15: 2025-01-12T23:59:48+00:00 | D15: finney | E15: TAO | K15: 257.90264 | L15: 2.6901865 | M15: 255.21246 | N15: 0 | O15: 0 | P15: 443.41416776212833 | Q15: 1 | R15: 0.11174071 | S15: 49.54 | T15: 45669 | V15: ="S-"&IF(LEN(I15)=0,B15,I15&IF(F15="fee","-00",IF(LEN(G15)>0,"-01","-02"))) -> S-4691826 | W15: =COUNTIF(I:I,I15) -> 0 | X15: =IF(LEN(I15)>0,I15&IF(F15="fee","fee",IF(VALUE(G15)>0,"debit",IF(VALUE(H15)>0,"credit","error"))),"") | Y15: =ROUND(IF(ROW(U15) = 2,K15,0)+IF(H15<>"",H15,0) + IF(R15<>"",R15,0) - IF(G15<>"",G15,0),9) -> 0.11174071
A16: 5Eq8C1NoLah4DaahQLMQ6wPLTSiAoiP35kVs9VMjaEqcSmdF | B16: 4699026 | C16: 2025-01-13T23:59:48.001+00:00 | D16: finney | E16: TAO | K16: 258.01303 | L16: 2.6901865 | M16: 255.32285 | N16: 0 | O16: 0 | P16: 420.58693541865387 | Q16: 1 | R16: 0.11039172 | S16: 46.42 | T16: 45670 | V16: ="S-"&IF(LEN(I16)=0,B16,I16&IF(F16="fee","-00",IF(LEN(G16)>0,"-01","-02"))) -> S-4699026 | W16: =COUNTIF(I:I,I16) -> 0 | X16: =IF(LEN(I16)>0,I16&IF(F16="fee","fee",IF(VALUE(G16)>0,"debit",IF(VALUE(H16)>0,"credit","error"))),"") | Y16: =ROUND(IF(ROW(U16) = 2,K16,0)+IF(H16<>"",H16,0) + IF(R16<>"",R16,0) - IF(G16<>"",G16,0),9) -> 0.11039172
A17: 5Eq8C1NoLah4DaahQLMQ6wPLTSiAoiP35kVs9VMjaEqcSmdF | B17: 4706226 | C17: 2025-01-14T23:59:48+00:00 | D17: finney | E17: TAO | K17: 258.12203 | L17: 2.6901865 | M17: 255.43184 | N17: 0 | O17: 0 | P17: 417.21127 | Q17: 1 | R17: 0.1089928 | S17: 45.47 | T17: 45671 | V17: ="S-"&IF(LEN(I17)=0,B17,I17&IF(F17="fee","-00",IF(LEN(G17)>0,"-01","-02"))) -> S-4706226 | W17: =COUNTIF(I:I,I17) -> 0 | X17: =IF(LEN(I17)>0,I17&IF(F17="fee","fee",IF(VALUE(G17)>0,"debit",IF(VALUE(H17)>0,"credit","error"))),"") | Y17: =ROUND(IF(ROW(U17) = 2,K17,0)+IF(H17<>"",H17,0) + IF(R17<>"",R17,0) - IF(G17<>"",G17,0),9) -> 0.1089928
A18: 5Eq8C1NoLah4DaahQLMQ6wPLTSiAoiP35kVs9VMjaEqcSmdF | B18: 4713426 | C18: 2025-01-15T23:59:48+00:00 | D18: finney | E18: TAO | K18: 258.23076 | L18: 2.6901865 | M18: 255.54057 | N18: 0 | O18: 0 | P18: 457.0246357089349 | Q18: 1 | R18: 0.1087295 | S18: 49.69 | T18: 45672 | V18: ="S-"&IF(LEN(I18)=0,B18,I18&IF(F18="fee","-00",IF(LEN(G18)>0,"-01","-02"))) -> S-4713426 | W18: =COUNTIF(I:I,I18) -> 0 | X18: =IF(LEN(I18)>0,I18&IF(F18="fee","fee",IF(VALUE(G18)>0,"debit",IF(VALUE(H18)>0,"credit","error"))),"") | Y18: =ROUND(IF(ROW(U18) = 2,K18,0)+IF(H18<>"",H18,0) + IF(R18<>"",R18,0) - IF(G18<>"",G18,0),9) -> 0.1087295
A19: 5Eq8C1NoLah4DaahQLMQ6wPLTSiAoiP35kVs9VMjaEqcSmdF | B19: 4720626 | C19: 2025-01-16T23:59:48+00:00 | D19: finney | E19: TAO | K19: 258.33966 | L19: 2.6901865 | M19: 255.64948 | N19: 0 | O19: 0 | P19: 443.5276377025133 | Q19: 1 | R19: 0.10890706 | S19: 48.3 | T19: 45673 | V19: ="S-"&IF(LEN(I19)=0,B19,I19&IF(F19="fee","-00",IF(LEN(G19)>0,"-01","-02"))) -> S-4720626 | W19: =COUNTIF(I:I,I19) -> 0 | X19: =IF(LEN(I19)>0,I19&IF(F19="fee","fee",IF(VALUE(G19)>0,"debit",IF(VALUE(H19)>0,"credit","error"))),"") | Y19: =ROUND(IF(ROW(U19) = 2,K19,0)+IF(H19<>"",H19,0) + IF(R19<>"",R19,0) - IF(G19<>"",G19,0),9) -> 0.10890706
A20: 5Eq8C1NoLah4DaahQLMQ6wPLTSiAoiP35kVs9VMjaEqcSmdF | B20: 4727826 | C20: 2025-01-17T23:59:48+00:00 | D20: finney | E20: TAO | K20: 258.45136 | L20: 2.6901865 | M20: 255.76118 | N20: 0 | O20: 0 | P20: 486.9949653436108 | Q20: 1 | R20: 0.11169907 | S20: 54.39 | T20: 45674 | V20: ="S-"&IF(LEN(I20)=0,B20,I20&IF(F20="fee","-00",IF(LEN(G20)>0,"-01","-02"))) -> S-4727826 | W20: =COUNTIF(I:I,I20) -> 0 | X20: =IF(LEN(I20)>0,I20&IF(F20="fee","fee",IF(VALUE(G20)>0,"debit",IF(VALUE(H20)>0,"credit","error"))),"") | Y20: =ROUND(IF(ROW(U20) = 2,K20,0)+IF(H20<>"",H20,0) + IF(R20<>"",R20,0) - IF(G20<>"",G20,0),9) -> 0.11169907
A21: 5Eq8C1NoLah4DaahQLMQ6wPLTSiAoiP35kVs9VMjaEqcSmdF | B21: 4735025 | C21: 2025-01-18T23:59:48+00:00 | D21: finney | E21: TAO | K21: 258.5665 | L21: 2.6901865 | M21: 255.87631 | N21: 0 | O21: 0 | P21: 460.0504845163183 | Q21: 1 | R21: 0.11513431 | S21: 52.96 | T21: 45675 | V21: ="S-"&IF(LEN(I21)=0,B21,I21&IF(F21="fee","-00",IF(LEN(G21)>0,"-01","-02"))) -> S-4735025 | W21: =COUNTIF(I:I,I21) -> 0 | X21: =IF(LEN(I21)>0,I21&IF(F21="fee","fee",IF(VALUE(G21)>0,"debit",IF(VALUE(H21)>0,"credit","error"))),"") | Y21: =ROUND(IF(ROW(U21) = 2,K21,0)+IF(H21<>"",H21,0) + IF(R21<>"",R21,0) - IF(G21<>"",G21,0),9) -> 0.11513431
A22: 5Eq8C1NoLah4DaahQLMQ6wPLTSiAoiP35kVs9VMjaEqcSmdF | B22: 4742224 | C22: 2025-01-19T23:59:48+00:00 | D22: finney | E22: TAO | K22: 258.68097 | L22: 2.6901865 | M22: 255.99078 | N22: 0 | O22: 0 | P22: 424.48641007258374 | Q22: 1 | R22: 0.11447006 | S22: 48.59 | T22: 45676 | V22: ="S-"&IF(LEN(I22)=0,B22,I22&IF(F22="fee","-00",IF(LEN(G22)>0,"-01","-02"))) -> S-4742224 | W22: =COUNTIF(I:I,I22) -> 0 | X22: =IF(LEN(I22)>0,I22&IF(F22="fee","fee",IF(VALUE(G22)>0,"debit",IF(VALUE(H22)>0,"credit","error"))),"") | Y22: =ROUND(IF(ROW(U22) = 2,K22,0)+IF(H22<>"",H22,0) + IF(R22<>"",R22,0) - IF(G22<>"",G22,0),9) -> 0.11447006
A23: 5Eq8C1NoLah4DaahQLMQ6wPLTSiAoiP35kVs9VMjaEqcSmdF | B23: 4749424 | C23: 2025-01-20T23:59:48+00:00 | D23: finney | E23: TAO | K23: 258.79933 | L23: 2.6901865 | M23: 256.10914 | N23: 0 | O23: 0 | P23: 409.87366320933495 | Q23: 1 | R23: 0.11835984 | S23: 48.51 | T23: 45677 | V23: ="S-"&IF(LEN(I23)=0,B23,I23&IF(F23="fee","-00",IF(LEN(G23)>0,"-01","-02"))) -> S-4749424 | W23: =COUNTIF(I:I,I23) -> 0 | X23: =IF(LEN(I23)>0,I23&IF(F23="fee","fee",IF(VALUE(G23)>0,"debit",IF(VALUE(H23)>0,"credit","error"))),"") | Y23: =ROUND(IF(ROW(U23) = 2,K23,0)+IF(H23<>"",H23,0) + IF(R23<>"",R23,0) - IF(G23<>"",G23,0),9) -> 0.11835984
A24: 5Eq8C1NoLah4DaahQLMQ6wPLTSiAoiP35kVs9VMjaEqcSmdF | B24: 4756623 | C24: 2025-01-21T23:59:48.001+00:00 | D24: finney | E24: TAO | K24: 258.92652 | L24: 2.6901865 | M24: 256.23633 | N24: 0 | O24: 0 | P24: 426.34802246929024 | Q24: 1 | R24: 0.12719171 | S24: 54.22 | T24: 45678 | V24: ="S-"&IF(LEN(I24)=0,B24,I24&IF(F24="fee","-00",IF(LEN(G24)>0,"-01","-02"))) -> S-4756623 | W24: =COUNTIF(I:I,I24) -> 0 | X24: =IF(LEN(I24)>0,I24&IF(F24="fee","fee",IF(VALUE(G24)>0,"debit",IF(VALUE(H24)>0,"credit","error"))),"") | Y24: =ROUND(IF(ROW(U24) = 2,K24,0)+IF(H24<>"",H24,0) + IF(R24<>"",R24,0) - IF(G24<>"",G24,0),9) -> 0.12719171
A25: 5Eq8C1NoLah4DaahQLMQ6wPLTSiAoiP35kVs9VMjaEqcSmdF | B25: 4763823 | C25: 2025-01-22T23:59:48+00:00 | D25: finney | E25: TAO | K25: 259.04237 | L25: 2.6901865 | M25: 256.35218 | N25: 0 | O25: 0 | P25: 401.1287822762729 | Q25: 1 | R25: 0.11585211 | S25: 46.47 | T25: 45679 | V25: ="S-"&IF(LEN(I25)=0,B25,I25&IF(F25="fee","-00",IF(LEN(G25)>0,"-01","-02"))) -> S-4763823 | W25: =COUNTIF(I:I,I25) -> 0 | X25: =IF(LEN(I25)>0,I25&IF(F25="fee","fee",IF(VALUE(G25)>0,"debit",IF(VALUE(H25)>0,"credit","error"))),"") | Y25: =ROUND(IF(ROW(U25) = 2,K25,0)+IF(H25<>"",H25,0) + IF(R25<>"",R25,0) - IF(G25<>"",G25,0),9) -> 0.11585211
A26: 5Eq8C1NoLah4DaahQLMQ6wPLTSiAoiP35kVs9VMjaEqcSmdF | B26: 4771023 | C26: 2025-01-23T23:59:48.001+00:00 | D26: finney | E26: TAO | K26: 259.15634 | L26: 2.6901865 | M26: 256.46615 | N26: 0 | O26: 0 | P26: 380.85226745247263 | Q26: 1 | R26: 0.11396705 | S26: 43.4 | T26: 45680 | V26: ="S-"&IF(LEN(I26)=0,B26,I26&IF(F26="fee","-00",IF(LEN(G26)>0,"-01","-02"))) -> S-4771023 | W26: =COUNTIF(I:I,I26) -> 0 | X26: =IF(LEN(I26)>0,I26&IF(F26="fee","fee",IF(VALUE(G26)>0,"debit",IF(VALUE(H26)>0,"credit","error"))),"") | Y26: =ROUND(IF(ROW(U26) = 2,K26,0)+IF(H26<>"",H26,0) + IF(R26<>"",R26,0) - IF(G26<>"",G26,0),9) -> 0.11396705
A27: 5Eq8C1NoLah4DaahQLMQ6wPLTSiAoiP35kVs9VMjaEqcSmdF | B27: 4778223 | C27: 2025-01-24T23:59:48+00:00 | D27: finney | E27: TAO | K27: 259.27148 | L27: 2.6901865 | M27: 256.58129 | N27: 0 | O27: 0 | P27: 370.5888915790195 | Q27: 1 | R27: 0.11514419 | S27: 42.67 | T27: 45681 | V27: ="S-"&IF(LEN(I27)=0,B27,I27&IF(F27="fee","-00",IF(LEN(G27)>0,"-01","-02"))) -> S-4778223 | W27: =COUNTIF(I:I,I27) -> 0 | X27: =IF(LEN(I27)>0,I27&IF(F27="fee","fee",IF(VALUE(G27)>0,"debit",IF(VALUE(H27)>0,"credit","error"))),"") | Y27: =ROUND(IF(ROW(U27) = 2,K27,0)+IF(H27<>"",H27,0) + IF(R27<>"",R27,0) - IF(G27<>"",G27,0),9) -> 0.11514419
A28: 5Eq8C1NoLah4DaahQLMQ6wPLTSiAoiP35kVs9VMjaEqcSmdF | B28: 4785423 | C28: 2025-01-25T23:59:48+00:00 | D28: finney | E28: TAO | K28: 259.38862 | L28: 2.6901865 | M28: 256.69843 | N28: 0 | O28: 0 | P28: 413.19252714481706 | Q28: 1 | R28: 0.11713619 | S28: 48.39 | T28: 45682 | V28: ="S-"&IF(LEN(I28)=0,B28,I28&IF(F28="fee","-00",IF(LEN(G28)>0,"-01","-02"))) -> S-4785423 | W28: =COUNTIF(I:I,I28) -> 0 | X28: =IF(LEN(I28)>0,I28&IF(F28="fee","fee",IF(VALUE(G28)>0,"debit",IF(VALUE(H28)>0,"credit","error"))),"") | Y28: =ROUND(IF(ROW(U28) = 2,K28,0)+IF(H28<>"",H28,0) + IF(R28<>"",R28,0) - IF(G28<>"",G28,0),9) -> 0.11713619
A29: 5Eq8C1NoLah4DaahQLMQ6wPLTSiAoiP35kVs9VMjaEqcSmdF | B29: 4792622 | C29: 2025-01-26T23:59:48+00:00 | D29: finney | E29: TAO | K29: 259.5058 | L29: 2.6901865 | M29: 256.81561 | N29: 0 | O29: 0 | P29: 433.4903129911173 | Q29: 1 | R29: 0.11718267 | S29: 50.79 | T29: 45683 | V29: ="S-"&IF(LEN(I29)=0,B29,I29&IF(F29="fee","-00",IF(LEN(G29)>0,"-01","-02"))) -> S-4792622 | W29: =COUNTIF(I:I,I29) -> 0 | X29: =IF(LEN(I29)>0,I29&IF(F29="fee","fee",IF(VALUE(G29)>0,"debit",IF(VALUE(H29)>0,"credit","error"))),"") | Y29: =ROUND(IF(ROW(U29) = 2,K29,0)+IF(H29<>"",H29,0) + IF(R29<>"",R29,0) - IF(G29<>"",G29,0),9) -> 0.11718267
... A31: 5Eq8C1NoLah4DaahQLMQ6wPLTSiAoiP35kVs9VMjaEqcSmdF | B31: 4807022 | C31: 2025-01-28T23:59:48+00:00 | D31: finney | E31: TAO | K31: 259.74492 | L31: 2.6901865 | M31: 257.05473 | N31: 0 | O31: 0 | P31: 444.90636618436974 | Q31: 1 | R31: 0.11970531 | S31: 53.25 | T31: 45685 | V31: ="S-"&IF(LEN(I31)=0,B31,I31&IF(F31="fee","-00",IF(LEN(G31)>0,"-01","-02"))) -> S-4807022 | W31: =COUNTIF(I:I,I31) -> 0 | X31: =IF(LEN(I31)>0,I31&IF(F31="fee","fee",IF(VALUE(G31)>0,"debit",IF(VALUE(H31)>0,"credit","error"))),"") | Y31: =ROUND(IF(ROW(U31) = 2,K31,0)+IF(H31<>"",H31,0) + IF(R31<>"",R31,0) - IF(G31<>"",G31,0),9) -> 0.11970531
A32: 5Eq8C1NoLah4DaahQLMQ6wPLTSiAoiP35kVs9VMjaEqcSmdF | B32: 4814222 | C32: 2025-01-29T23:59:48.001+00:00 | D32: finney | E32: TAO | K32: 259.85818 | L32: 2.6901865 | M32: 257.16799 | N32: 0 | O32: 0 | P32: 450.68657 | Q32: 1 | R32: 0.11325916 | S32: 51.04 | T32: 45686 | V32: ="S-"&IF(LEN(I32)=0,B32,I32&IF(F32="fee","-00",IF(LEN(G32)>0,"-01","-02"))) -> S-4814222 | W32: =COUNTIF(I:I,I32) -> 0 | X32: =IF(LEN(I32)>0,I32&IF(F32="fee","fee",IF(VALUE(G32)>0,"debit",IF(VALUE(H32)>0,"credit","error"))),"") | Y32: =ROUND(IF(ROW(U32) = 2,K32,0)+IF(H32<>"",H32,0) + IF(R32<>"",R32,0) - IF(G32<>"",G32,0),9) -> 0.11325916
A33: 5Eq8C1NoLah4DaahQLMQ6wPLTSiAoiP35kVs9VMjaEqcSmdF | B33: 4821422 | C33: 2025-01-30T23:59:48+00:00 | D33: finney | E33: TAO | K33: 259.97457 | L33: 2.6901865 | M33: 257.28438 | N33: 0 | O33: 0 | P33: 454.5244163596316 | Q33: 1 | R33: 0.11638804 | S33: 52.9 | T33: 45687 | V33: ="S-"&IF(LEN(I33)=0,B33,I33&IF(F33="fee","-00",IF(LEN(G33)>0,"-01","-02"))) -> S-4821422 | W33: =COUNTIF(I:I,I33) -> 0 | X33: =IF(LEN(I33)>0,I33&IF(F33="fee","fee",IF(VALUE(G33)>0,"debit",IF(VALUE(H33)>0,"credit","error"))),"") | Y33: =ROUND(IF(ROW(U33) = 2,K33,0)+IF(H33<>"",H33,0) + IF(R33<>"",R33,0) - IF(G33<>"",G33,0),9) -> 0.11638804
A34: 5Eq8C1NoLah4DaahQLMQ6wPLTSiAoiP35kVs9VMjaEqcSmdF | B34: 4828622 | C34: 2025-01-31T23:59:48.001+00:00 | D34: finney | E34: TAO | K34: 260.09391 | L34: 2.6901865 | M34: 257.40372 | N34: 0 | O34: 0 | P34: 448.76411187910935 | Q34: 1 | R34: 0.11934045 | S34: 53.55 | T34: 45688 | V34: ="S-"&IF(LEN(I34)=0,B34,I34&IF(F34="fee","-00",IF(LEN(G34)>0,"-01","-02"))) -> S-4828622 | W34: =COUNTIF(I:I,I34) -> 0 | X34: =IF(LEN(I34)>0,I34&IF(F34="fee","fee",IF(VALUE(G34)>0,"debit",IF(VALUE(H34)>0,"credit","error"))),"") | Y34: =ROUND(IF(ROW(U34) = 2,K34,0)+IF(H34<>"",H34,0) + IF(R34<>"",R34,0) - IF(G34<>"",G34,0),9) -> 0.11934045
A35: 5Eq8C1NoLah4DaahQLMQ6wPLTSiAoiP35kVs9VMjaEqcSmdF | B35: 4835821 | C35: 2025-02-01T23:59:48.001+00:00 | D35: finney | E35: TAO | K35: 260.21314 | L35: 2.6901865 | M35: 257.52295 | N35: 0 | O35: 0 | P35: 395.1650880030533 | Q35: 1 | R35: 0.11922854 | S35: 47.11 | T35: 45689 | V35: ="S-"&IF(LEN(I35)=0,B35,I35&IF(F35="fee","-00",IF(LEN(G35)>0,"-01","-02"))) -> S-4835821 | W35: =COUNTIF(I:I,I35) -> 0 | X35: =IF(LEN(I35)>0,I35&IF(F35="fee","fee",IF(VALUE(G35)>0,"debit",IF(VALUE(H35)>0,"credit","error"))),"") | Y35: =ROUND(IF(ROW(U35) = 2,K35,0)+IF(H35<>"",H35,0) + IF(R35<>"",R35,0) - IF(G35<>"",G35,0),9) -> 0.11922854
A36: 5Eq8C1NoLah4DaahQLMQ6wPLTSiAoiP35kVs9VMjaEqcSmdF | B36: 4843021 | C36: 2025-02-02T23:59:48+00:00 | D36: finney | E36: TAO | K36: 260.33092 | L36: 2.6901865 | M36: 257.64074 | N36: 0 | O36: 0 | P36: 347.5191253328133 | Q36: 1 | R36: 0.11778453 | S36: 40.93 | T36: 45690 | V36: ="S-"&IF(LEN(I36)=0,B36,I36&IF(F36="fee","-00",IF(LEN(G36)>0,"-01","-02"))) -> S-4843021 | W36: =COUNTIF(I:I,I36) -> 0 | X36: =IF(LEN(I36)>0,I36&IF(F36="fee","fee",IF(VALUE(G36)>0,"debit",IF(VALUE(H36)>0,"credit","error"))),"") | Y36: =ROUND(IF(ROW(U36) = 2,K36,0)+IF(H36<>"",H36,0) + IF(R36<>"",R36,0) - IF(G36<>"",G36,0),9) -> 0.11778453
A37: 5Eq8C1NoLah4DaahQLMQ6wPLTSiAoiP35kVs9VMjaEqcSmdF | B37: 4850221 | C37: 2025-02-03T23:59:48+00:00 | D37: finney | E37: TAO | K37: 260.45122 | L37: 2.6901865 | M37: 257.76103 | N37: 0 | O37: 0 | P37: 391.4238925935672 | Q37: 1 | R37: 0.12029826 | S37: 47.08 | T37: 45691 | V37: ="S-"&IF(LEN(I37)=0,B37,I37&IF(F37="fee","-00",IF(LEN(G37)>0,"-01","-02"))) -> S-4850221 | W37: =COUNTIF(I:I,I37) -> 0 | X37: =IF(LEN(I37)>0,I37&IF(F37="fee","fee",IF(VALUE(G37)>0,"debit",IF(VALUE(H37)>0,"credit","error"))),"") | Y37: =ROUND(IF(ROW(U37) = 2,K37,0)+IF(H37<>"",H37,0) + IF(R37<>"",R37,0) - IF(G37<>"",G37,0),9) -> 0.12029826
A38: 5Eq8C1NoLah4DaahQLMQ6wPLTSiAoiP35kVs9VMjaEqcSmdF | B38: 4857421 | C38: 2025-02-04T23:59:48+00:00 | D38: finney | E38: TAO | K38: 260.56887 | L38: 2.6901865 | M38: 257.87868 | N38: 0 | O38: 0 | P38: 357.5705242975157 | Q38: 1 | R38: 0.11764868 | S38: 42.06 | T38: 45692 | V38: ="S-"&IF(LEN(I38)=0,B38,I38&IF(F38="fee","-00",IF(LEN(G38)>0,"-01","-02"))) -> S-4857421 | W38: =COUNTIF(I:I,I38) -> 0 | X38: =IF(LEN(I38)>0,I38&IF(F38="fee","fee",IF(VALUE(G38)>0,"debit",IF(VALUE(H38)>0,"credit","error"))),"") | Y38: =ROUND(IF(ROW(U38) = 2,K38,0)+IF(H38<>"",H38,0) + IF(R38<>"",R38,0) - IF(G38<>"",G38,0),9) -> 0.11764868
A39: 5Eq8C1NoLah4DaahQLMQ6wPLTSiAoiP35kVs9VMjaEqcSmdF | B39: 4864621 | C39: 2025-02-05T23:59:48+00:00 | D39: finney | E39: TAO | K39: 260.68489 | L39: 2.6901865 | M39: 257.9947 | N39: 0 | O39: 0 | P39: 351.1294191389967 | Q39: 1 | R39: 0.11601707 | S39: 40.73 | T39: 45693 | V39: ="S-"&IF(LEN(I39)=0,B39,I39&IF(F39="fee","-00",IF(LEN(G39)>0,"-01","-02"))) -> S-4864621 | W39: =COUNTIF(I:I,I39) -> 0 | X39: =IF(LEN(I39)>0,I39&IF(F39="fee","fee",IF(VALUE(G39)>0,"debit",IF(VALUE(H39)>0,"credit","error"))),"") | Y39: =ROUND(IF(ROW(U39) = 2,K39,0)+IF(H39<>"",H39,0) + IF(R39<>"",R39,0) - IF(G39<>"",G39,0),9) -> 0.11601707
A40: 5Eq8C1NoLah4DaahQLMQ6wPLTSiAoiP35kVs9VMjaEqcSmdF | B40: 4871820 | C40: 2025-02-06T23:59:48+00:00 | D40: finney | E40: TAO | K40: 260.80759 | L40: 2.6901865 | M40: 258.11741 | N40: 0 | O40: 0 | P40: 325.04556 | Q40: 1 | R40: 0.12270668 | S40: 39.88 | T40: 45694 | V40: ="S-"&IF(LEN(I40)=0,B40,I40&IF(F40="fee","-00",IF(LEN(G40)>0,"-01","-02"))) -> S-4871820 | W40: =COUNTIF(I:I,I40) -> 0 | X40: =IF(LEN(I40)>0,I40&IF(F40="fee","fee",IF(VALUE(G40)>0,"debit",IF(VALUE(H40)>0,"credit","error"))),"") | Y40: =ROUND(IF(ROW(U40) = 2,K40,0)+IF(H40<>"",H40,0) + IF(R40<>"",R40,0) - IF(G40<>"",G40,0),9) -> 0.12270668
A41: 5Eq8C1NoLah4DaahQLMQ6wPLTSiAoiP35kVs9VMjaEqcSmdF | B41: 4878757 | C41: 2025-02-07T23:59:48+00:00 | D41: finney | E41: TAO | K41: 260.93076 | L41: 2.6901865 | M41: 258.24058 | N41: 0 | O41: 0 | P41: 319.8709765876021 | Q41: 1 | R41: 0.12317118 | S41: 39.39 | T41: 45695 | V41: ="S-"&IF(LEN(I41)=0,B41,I41&IF(F41="fee","-00",IF(LEN(G41)>0,"-01","-02"))) -> S-4878757 | W41: =COUNTIF(I:I,I41) -> 0 | X41: =IF(LEN(I41)>0,I41&IF(F41="fee","fee",IF(VALUE(G41)>0,"debit",IF(VALUE(H41)>0,"credit","error"))),"") | Y41: =ROUND(IF(ROW(U41) = 2,K41,0)+IF(H41<>"",H41,0) + IF(R41<>"",R41,0) - IF(G41<>"",G41,0),9) -> 0.12317118
A42: 5Eq8C1NoLah4DaahQLMQ6wPLTSiAoiP35kVs9VMjaEqcSmdF | B42: 4885596 | C42: 2025-02-08T23:59:48+00:00 | D42: finney | E42: TAO | K42: 261.05678 | L42: 2.6901865 | M42: 258.36659 | N42: 0 | O42: 0 | P42: 351.7078577448325 | Q42: 1 | R42: 0.12601254 | S42: 44.31 | T42: 45696 | V42: ="S-"&IF(LEN(I42)=0,B42,I42&IF(F42="fee","-00",IF(LEN(G42)>0,"-01","-02"))) -> S-4885596 | W42: =COUNTIF(I:I,I42) -> 0 | X42: =IF(LEN(I42)>0,I42&IF(F42="fee","fee",IF(VALUE(G42)>0,"debit",IF(VALUE(H42)>0,"credit","error"))),"") | Y42: =ROUND(IF(ROW(U42) = 2,K42,0)+IF(H42<>"",H42,0) + IF(R42<>"",R42,0) - IF(G42<>"",G42,0),9) -> 0.12601254
A43: 5Eq8C1NoLah4DaahQLMQ6wPLTSiAoiP35kVs9VMjaEqcSmdF | B43: 4892436 | C43: 2025-02-09T23:59:48+00:00 | D43: finney | E43: TAO | K43: 261.18239 | L43: 2.6901865 | M43: 258.4922 | N43: 0 | O43: 0 | P43: 366.5424195159707 | Q43: 1 | R43: 0.12561287 | S43: 46.04 | T43: 45697 | V43: ="S-"&IF(LEN(I43)=0,B43,I43&IF(F43="fee","-00",IF(LEN(G43)>0,"-01","-02"))) -> S-4892436 | W43: =COUNTIF(I:I,I43) -> 0 | X43: =IF(LEN(I43)>0,I43&IF(F43="fee","fee",IF(VALUE(G43)>0,"debit",IF(VALUE(H43)>0,"credit","error"))),"") | Y43: =ROUND(IF(ROW(U43) = 2,K43,0)+IF(H43<>"",H43,0) + IF(R43<>"",R43,0) - IF(G43<>"",G43,0),9) -> 0.12561287
A44: 5Eq8C1NoLah4DaahQLMQ6wPLTSiAoiP35kVs9VMjaEqcSmdF | B44: 4899446 | C44: 2025-02-10T23:59:48+00:00 | D44: finney | E44: TAO | K44: 261.31092 | L44: 2.6901865 | M44: 258.62073 | N44: 0 | O44: 0 | P44: 383.4704222043313 | Q44: 1 | R44: 0.12852951 | S44: 49.28 | T44: 45698 | V44: ="S-"&IF(LEN(I44)=0,B44,I44&IF(F44="fee","-00",IF(LEN(G44)>0,"-01","-02"))) -> S-4899446 | W44: =COUNTIF(I:I,I44) -> 0 | X44: =IF(LEN(I44)>0,I44&IF(F44="fee","fee",IF(VALUE(G44)>0,"debit",IF(VALUE(H44)>0,"credit","error"))),"") | Y44: =ROUND(IF(ROW(U44) = 2,K44,0)+IF(H44<>"",H44,0) + IF(R44<>"",R44,0) - IF(G44<>"",G44,0),9) -> 0.12852951
A45: 5Eq8C1NoLah4DaahQLMQ6wPLTSiAoiP35kVs9VMjaEqcSmdF | B45: 4906646 | C45: 2025-02-11T23:59:48.001+00:00 | D45: finney | E45: TAO | K45: 261.43653 | L45: 2.6901865 | M45: 258.74634 | N45: 0 | O45: 0 | P45: 411.68538980363576 | Q45: 1 | R45: 0.12560892 | S45: 51.71 | T45: 45699 | V45: ="S-"&IF(LEN(I45)=0,B45,I45&IF(F45="fee","-00",IF(LEN(G45)>0,"-01","-02"))) -> S-4906646 | W45: =COUNTIF(I:I,I45) -> 0 | X45: =IF(LEN(I45)>0,I45&IF(F45="fee","fee",IF(VALUE(G45)>0,"debit",IF(VALUE(H45)>0,"credit","error"))),"") | Y45: =ROUND(IF(ROW(U45) = 2,K45,0)+IF(H45<>"",H45,0) + IF(R45<>"",R45,0) - IF(G45<>"",G45,0),9) -> 0.12560892
A46: 5Eq8C1NoLah4DaahQLMQ6wPLTSiAoiP35kVs9VMjaEqcSmdF | B46: 4913846 | C46: 2025-02-12T23:59:48+00:00 | D46: finney | E46: TAO | K46: 261.56558 | L46: 2.6901865 | M46: 258.87539 | N46: 0 | O46: 0 | P46: 401.5705056616309 | Q46: 1 | R46: 0.12904778 | S46: 51.82 | T46: 45700 | V46: ="S-"&IF(LEN(I46)=0,B46,I46&IF(F46="fee","-00",IF(LEN(G46)>0,"-01","-02"))) -> S-4913846 | W46: =COUNTIF(I:I,I46) -> 0 | X46: =IF(LEN(I46)>0,I46&IF(F46="fee","fee",IF(VALUE(G46)>0,"debit",IF(VALUE(H46)>0,"credit","error"))),"") | Y46: =ROUND(IF(ROW(U46) = 2,K46,0)+IF(H46<>"",H46,0) + IF(R46<>"",R46,0) - IF(G46<>"",G46,0),9) -> 0.12904778
A47: 5Eq8C1NoLah4DaahQLMQ6wPLTSiAoiP35kVs9VMjaEqcSmdF | B47: 4921036 | C47: 2025-02-13T23:59:48.001+00:00 | D47: finney | E47: TAO | K47: 261.67048 | L47: 2.6901865 | M47: 258.98029 | N47: 0 | O47: 0 | P47: 384.18518953981834 | Q47: 1 | R47: 0.10490019 | S47: 40.3 | T47: 45701 | V47: ="S-"&IF(LEN(I47)=0,B47,I47&IF(F47="fee","-00",IF(LEN(G47)>0,"-01","-02"))) -> S-4921036 | W47: =COUNTIF(I:I,I47) -> 0 | X47: =IF(LEN(I47)>0,I47&IF(F47="fee","fee",IF(VALUE(G47)>0,"debit",IF(VALUE(H47)>0,"credit","error"))),"") | Y47: =ROUND(IF(ROW(U47) = 2,K47,0)+IF(H47<>"",H47,0) + IF(R47<>"",R47,0) - IF(G47<>"",G47,0),9) -> 0.10490019
A48: 5Eq8C1NoLah4DaahQLMQ6wPLTSiAoiP35kVs9VMjaEqcSmdF | B48: 4928236 | C48: 2025-02-14T23:59:48+00:00 | D48: finney | E48: TAO | K48: 261.99115 | L48: 2.6901865 | M48: 259.30096 | N48: 0 | O48: 0 | P48: 389.71824197592656 | Q48: 1 | R48: 0.32067343 | S48: 124.97 | T48: 45702 | V48: ="S-"&IF(LEN(I48)=0,B48,I48&IF(F48="fee","-00",IF(LEN(G48)>0,"-01","-02"))) -> S-4928236 | W48: =COUNTIF(I:I,I48) -> 0 | X48: =IF(LEN(I48)>0,I48&IF(F48="fee","fee",IF(VALUE(G48)>0,"debit",IF(VALUE(H48)>0,"credit","error"))),"") | Y48: =ROUND(IF(ROW(U48) = 2,K48,0)+IF(H48<>"",H48,0) + IF(R48<>"",R48,0) - IF(G48<>"",G48,0),9) -> 0.32067343
A49: 5Eq8C1NoLah4DaahQLMQ6wPLTSiAoiP35kVs9VMjaEqcSmdF | B49: 4935436 | C49: 2025-02-15T23:59:48+00:00 | D49: finney | E49: TAO | K49: 262.17205 | L49: 2.6901865 | M49: 259.48186 | N49: 0 | O49: 0 | P49: 376.0996114424311 | Q49: 1 | R49: 0.18090048 | S49: 68.03 | T49: 45703 | V49: ="S-"&IF(LEN(I49)=0,B49,I49&IF(F49="fee","-00",IF(LEN(G49)>0,"-01","-02"))) -> S-4935436 | W49: =COUNTIF(I:I,I49) -> 0 | X49: =IF(LEN(I49)>0,I49&IF(F49="fee","fee",IF(VALUE(G49)>0,"debit",IF(VALUE(H49)>0,"credit","error"))),"") | Y49: =ROUND(IF(ROW(U49) = 2,K49,0)+IF(H49<>"",H49,0) + IF(R49<>"",R49,0) - IF(G49<>"",G49,0),9) -> 0.18090048
A50: 5Eq8C1NoLah4DaahQLMQ6wPLTSiAoiP35kVs9VMjaEqcSmdF | B50: 4942636 | C50: 2025-02-16T23:59:48+00:00 | D50: finney | E50: TAO | K50: 262.30384 | L50: 2.6901865 | M50: 259.61366 | N50: 0 | O50: 0 | P50: 361.41265 | Q50: 1 | R50: 0.1317942 | S50: 47.63 | T50: 45704 | V50: ="S-"&IF(LEN(I50)=0,B50,I50&IF(F50="fee","-00",IF(LEN(G50)>0,"-01","-02"))) -> S-4942636 | W50: =COUNTIF(I:I,I50) -> 0 | X50: =IF(LEN(I50)>0,I50&IF(F50="fee","fee",IF(VALUE(G50)>0,"debit",IF(VALUE(H50)>0,"credit","error"))),"") | Y50: =ROUND(IF(ROW(U50) = 2,K50,0)+IF(H50<>"",H50,0) + IF(R50<>"",R50,0) - IF(G50<>"",G50,0),9) -> 0.1317942
A51: 5Eq8C1NoLah4DaahQLMQ6wPLTSiAoiP35kVs9VMjaEqcSmdF | B51: 4949836 | C51: 2025-02-17T23:59:48.001+00:00 | D51: finney | E51: TAO | K51: 262.44098 | L51: 2.6901865 | M51: 259.7508 | N51: 0 | O51: 0 | P51: 360.08732120198067 | Q51: 1 | R51: 0.13713939 | S51: 49.38 | T51: 45705 | V51: ="S-"&IF(LEN(I51)=0,B51,I51&IF(F51="fee","-00",IF(LEN(G51)>0,"-01","-02"))) -> S-4949836 | W51: =COUNTIF(I:I,I51) -> 0 | X51: =IF(LEN(I51)>0,I51&IF(F51="fee","fee",IF(VALUE(G51)>0,"debit",IF(VALUE(H51)>0,"credit","error"))),"") | Y51: =ROUND(IF(ROW(U51) = 2,K51,0)+IF(H51<>"",H51,0) + IF(R51<>"",R51,0) - IF(G51<>"",G51,0),9) -> 0.13713939
A52: 5Eq8C1NoLah4DaahQLMQ6wPLTSiAoiP35kVs9VMjaEqcSmdF | B52: 4957036 | C52: 2025-02-18T23:59:48.001+00:00 | D52: finney | E52: TAO | K52: 262.61749 | L52: 2.6901865 | M52: 259.92731 | N52: 0 | O52: 0 | P52: 373.9885586248297 | Q52: 1 | R52: 0.17651095 | S52: 66.01 | T52: 45706 | V52: ="S-"&IF(LEN(I52)=0,B52,I52&IF(F52="fee","-00",IF(LEN(G52)>0,"-01","-02"))) -> S-4957036 | W52: =COUNTIF(I:I,I52) -> 0 | X52: =IF(LEN(I52)>0,I52&IF(F52="fee","fee",IF(VALUE(G52)>0,"debit",IF(VALUE(H52)>0,"credit","error"))),"") | Y52: =ROUND(IF(ROW(U52) = 2,K52,0)+IF(H52<>"",H52,0) + IF(R52<>"",R52,0) - IF(G52<>"",G52,0),9) -> 0.17651095
A53: 5Eq8C1NoLah4DaahQLMQ6wPLTSiAoiP35kVs9VMjaEqcSmdF | B53: 4964236 | C53: 2025-02-19T23:59:48+00:00 | D53: finney | E53: TAO | K53: 262.95385 | L53: 2.6901865 | M53: 260.26367 | N53: 0 | O53: 0 | P53: 417.3923873232211 | Q53: 1 | R53: 0.33636072 | S53: 140.39 | T53: 45707 | V53: ="S-"&IF(LEN(I53)=0,B53,I53&IF(F53="fee","-00",IF(LEN(G53)>0,"-01","-02"))) -> S-4964236 | W53: =COUNTIF(I:I,I53) -> 0 | X53: =IF(LEN(I53)>0,I53&IF(F53="fee","fee",IF(VALUE(G53)>0,"debit",IF(VALUE(H53)>0,"credit","error"))),"") | Y53: =ROUND(IF(ROW(U53) = 2,K53,0)+IF(H53<>"",H53,0) + IF(R53<>"",R53,0) - IF(G53<>"",G53,0),9) -> 0.33636072
A54: 5Eq8C1NoLah4DaahQLMQ6wPLTSiAoiP35kVs9VMjaEqcSmdF | B54: 4971436 | C54: 2025-02-20T23:59:48.001+00:00 | D54: finney | E54: TAO | K54: 263.17954 | L54: 2.6901865 | M54: 260.48935 | N54: 0 | O54: 0 | P54: 463.8020780768946 | Q54: 1 | R54: 0.22568601 | S54: 104.67 | T54: 45708 | V54: ="S-"&IF(LEN(I54)=0,B54,I54&IF(F54="fee","-00",IF(LEN(G54)>0,"-01","-02"))) -> S-4971436 | W54: =COUNTIF(I:I,I54) -> 0 | X54: =IF(LEN(I54)>0,I54&IF(F54="fee","fee",IF(VALUE(G54)>0,"debit",IF(VALUE(H54)>0,"credit","error"))),"") | Y54: =ROUND(IF(ROW(U54) = 2,K54,0)+IF(H54<>"",H54,0) + IF(R54<>"",R54,0) - IF(G54<>"",G54,0),9) -> 0.22568601
A55: 5Eq8C1NoLah4DaahQLMQ6wPLTSiAoiP35kVs9VMjaEqcSmdF | B55: 4978636 | C55: 2025-02-21T23:59:48+00:00 | D55: finney | E55: TAO | K55: 263.41016 | L55: 2.6901865 | M55: 260.71998 | N55: 0 | O55: 0 | P55: 441.7635466522848 | Q55: 1 | R55: 0.2306211 | S55: 101.87 | T55: 45709 | V55: ="S-"&IF(LEN(I55)=0,B55,I55&IF(F55="fee","-00",IF(LEN(G55)>0,"-01","-02"))) -> S-4978636 | W55: =COUNTIF(I:I,I55) -> 0 | X55: =IF(LEN(I55)>0,I55&IF(F55="fee","fee",IF(VALUE(G55)>0,"debit",IF(VALUE(H55)>0,"credit","error"))),"") | Y55: =ROUND(IF(ROW(U55) = 2,K55,0)+IF(H55<>"",H55,0) + IF(R55<>"",R55,0) - IF(G55<>"",G55,0),9) -> 0.2306211
A56: 5Eq8C1NoLah4DaahQLMQ6wPLTSiAoiP35kVs9VMjaEqcSmdF | B56: 4985836 | C56: 2025-02-22T23:59:48+00:00 | D56: finney | E56: TAO | K56: 263.63519 | L56: 2.6901865 | M56: 260.945 | N56: 0 | O56: 0 | P56: 434.6695416651483 | Q56: 1 | R56: 0.22502739 | S56: 97.81 | T56: 45710 | V56: ="S-"&IF(LEN(I56)=0,B56,I56&IF(F56="fee","-00",IF(LEN(G56)>0,"-01","-02"))) -> S-4985836 | W56: =COUNTIF(I:I,I56) -> 0 | X56: =IF(LEN(I56)>0,I56&IF(F56="fee","fee",IF(VALUE(G56)>0,"debit",IF(VALUE(H56)>0,"credit","error"))),"") | Y56: =ROUND(IF(ROW(U56) = 2,K56,0)+IF(H56<>"",H56,0) + IF(R56<>"",R56,0) - IF(G56<>"",G56,0),9) -> 0.22502739
A57: 5Eq8C1NoLah4DaahQLMQ6wPLTSiAoiP35kVs9VMjaEqcSmdF | B57: 4993036 | C57: 2025-02-23T23:59:48+00:00 | D57: finney | E57: TAO | K57: 263.84209 | L57: 2.6901865 | M57: 261.1519 | N57: 0 | O57: 0 | P57: 431.70272 | Q57: 1 | R57: 0.20689953 | S57: 89.31 | T57: 45711 | V57: ="S-"&IF(LEN(I57)=0,B57,I57&IF(F57="fee","-00",IF(LEN(G57)>0,"-01","-02"))) -> S-4993036 | W57: =COUNTIF(I:I,I57) -> 0 | X57: =IF(LEN(I57)>0,I57&IF(F57="fee","fee",IF(VALUE(G57)>0,"debit",IF(VALUE(H57)>0,"credit","error"))),"") | Y57: =ROUND(IF(ROW(U57) = 2,K57,0)+IF(H57<>"",H57,0) + IF(R57<>"",R57,0) - IF(G57<>"",G57,0),9) -> 0.20689953
A58: 5Eq8C1NoLah4DaahQLMQ6wPLTSiAoiP35kVs9VMjaEqcSmdF | B58: 5000231 | C58: 2025-02-24T23:59:48.001+00:00 | D58: finney | E58: TAO | K58: 264.01392 | L58: 2.6901865 | M58: 261.32374 | N58: 0 | O58: 0 | P58: 404.22859682248566 | Q58: 1 | R58: 0.17183394 | S58: 69.46 | T58: 45712 | V58: ="S-"&IF(LEN(I58)=0,B58,I58&IF(F58="fee","-00",IF(LEN(G58)>0,"-01","-02"))) -> S-5000231 | W58: =COUNTIF(I:I,I58) -> 0 | X58: =IF(LEN(I58)>0,I58&IF(F58="fee","fee",IF(VALUE(G58)>0,"debit",IF(VALUE(H58)>0,"credit","error"))),"") | Y58: =ROUND(IF(ROW(U58) = 2,K58,0)+IF(H58<>"",H58,0) + IF(R58<>"",R58,0) - IF(G58<>"",G58,0),9) -> 0.17183394
A59: 5Eq8C1NoLah4DaahQLMQ6wPLTSiAoiP35kVs9VMjaEqcSmdF | B59: 5007431 | C59: 2025-02-25T23:59:48+00:00 | D59: finney | E59: TAO | K59: 264.16595 | L59: 2.6901865 | M59: 261.47576 | N59: 0 | O59: 0 | P59: 381.5133179578216 | Q59: 1 | R59: 0.15202322 | S59: 57.99 | T59: 45713 | V59: ="S-"&IF(LEN(I59)=0,B59,I59&IF(F59="fee","-00",IF(LEN(G59)>0,"-01","-02"))) -> S-5007431 | W59: =COUNTIF(I:I,I59) -> 0 | X59: =IF(LEN(I59)>0,I59&IF(F59="fee","fee",IF(VALUE(G59)>0,"debit",IF(VALUE(H59)>0,"credit","error"))),"") | Y59: =ROUND(IF(ROW(U59) = 2,K59,0)+IF(H59<>"",H59,0) + IF(R59<>"",R59,0) - IF(G59<>"",G59,0),9) -> 0.15202322
A60: 5Eq8C1NoLah4DaahQLMQ6wPLTSiAoiP35kVs9VMjaEqcSmdF | B60: 5011678 | C60: 2025-02-26T14:09:12+00:00 | D60: finney | E60: TAO | F60: fee | G60: 0.000135261 | I60: 5011678-0003 | J60: Balances.transfer_keep_alive | Q60: 1 | V60: ="S-"&IF(LEN(I60)=0,B60,I60&IF(F60="fee","-00",IF(LEN(G60)>0,"-01","-02"))) -> S-5011678-0003-00 | W60: =COUNTIF(I:I,I60) -> 2 | X60: =IF(LEN(I60)>0,I60&IF(F60="fee","fee",IF(VALUE(G60)>0,"debit",IF(VALUE(H60)>0,"credit","error"))),"") -> 5011678-0003fee | Y60: =ROUND(IF(ROW(U60) = 2,K60,0)+IF(H60<>"",H60,0) + IF(R60<>"",R60,0) - IF(G60<>"",G60,0),9) -> -0.000135261
A61: 5Eq8C1NoLah4DaahQLMQ6wPLTSiAoiP35kVs9VMjaEqcSmdF | B61: 5011678 | C61: 2025-02-26T14:09:12+00:00 | D61: finney | E61: TAO | F61: transfer_out | G61: 1 | I61: 5011678-0003 | J61: 5HbnKZMzGk3GT3mpWZgKuQHq3CC8LeW2tbNq1FkBLQhzUX6L | Q61: 1 | V61: ="S-"&IF(LEN(I61)=0,B61,I61&IF(F61="fee","-00",IF(LEN(G61)>0,"-01","-02"))) -> S-5011678-0003-01 | W61: =COUNTIF(I:I,I61) -> 2 | X61: =IF(LEN(I61)>0,I61&IF(F61="fee","fee",IF(VALUE(G61)>0,"debit",IF(VALUE(H61)>0,"credit","error"))),"") -> 5011678-0003debit | Y61: =ROUND(IF(ROW(U61) = 2,K61,0)+IF(H61<>"",H61,0) + IF(R61<>"",R61,0) - IF(G61<>"",G61,0),9) -> -1
A62: 5Eq8C1NoLah4DaahQLMQ6wPLTSiAoiP35kVs9VMjaEqcSmdF | B62: 5011793 | C62: 2025-02-26T14:32:12+00:00 | D62: finney | E62: TAO | F62: fee | G62: 5e-05 | I62: 5011793-0005 | J62: root_staking_fee | Q62: 1 | V62: ="S-"&IF(LEN(I62)=0,B62,I62&IF(F62="fee","-00",IF(LEN(G62)>0,"-01","-02"))) -> S-5011793-0005-00 | W62: =COUNTIF(I:I,I62) -> 1 | X62: =IF(LEN(I62)>0,I62&IF(F62="fee","fee",IF(VALUE(G62)>0,"debit",IF(VALUE(H62)>0,"credit","error"))),"") -> 5011793-0005fee | Y62: =ROUND(IF(ROW(U62) = 2,K62,0)+IF(H62<>"",H62,0) + IF(R62<>"",R62,0) - IF(G62<>"",G62,0),9) -> -5e-05
A63: 5Eq8C1NoLah4DaahQLMQ6wPLTSiAoiP35kVs9VMjaEqcSmdF | B63: 5012969 | C63: 2025-02-26T18:27:24+00:00 | D63: finney | E63: TAO | F63: fee | G63: 5e-05 | I63: 5012969-0007 | J63: root_staking_fee | Q63: 1 | V63: ="S-"&IF(LEN(I63)=0,B63,I63&IF(F63="fee","-00",IF(LEN(G63)>0,"-01","-02"))) -> S-5012969-0007-00 | W63: =COUNTIF(I:I,I63) -> 1 | X63: =IF(LEN(I63)>0,I63&IF(F63="fee","fee",IF(VALUE(G63)>0,"debit",IF(VALUE(H63)>0,"credit","error"))),"") -> 5012969-0007fee | Y63: =ROUND(IF(ROW(U63) = 2,K63,0)+IF(H63<>"",H63,0) + IF(R63<>"",R63,0) - IF(G63<>"",G63,0),9) -> -5e-05
A64: 5Eq8C1NoLah4DaahQLMQ6wPLTSiAoiP35kVs9VMjaEqcSmdF | B64: 5012975 | C64: 2025-02-26T18:28:36.001+00:00 | D64: finney | E64: TAO | F64: fee | G64: 0.000135263 | I64: 5012975-0006 | J64: Balances.transfer_keep_alive | Q64: 1 | V64: ="S-"&IF(LEN(I64)=0,B64,I64&IF(F64="fee","-00",IF(LEN(G64)>0,"-01","-02"))) -> S-5012975-0006-00 | W64: =COUNTIF(I:I,I64) -> 2 | X64: =IF(LEN(I64)>0,I64&IF(F64="fee","fee",IF(VALUE(G64)>0,"debit",IF(VALUE(H64)>0,"credit","error"))),"") -> 5012975-0006fee | Y64: =ROUND(IF(ROW(U64) = 2,K64,0)+IF(H64<>"",H64,0) + IF(R64<>"",R64,0) - IF(G64<>"",G64,0),9) -> -0.000135263
A65: 5Eq8C1NoLah4DaahQLMQ6wPLTSiAoiP35kVs9VMjaEqcSmdF | B65: 5012975 | C65: 2025-02-26T18:28:36.001+00:00 | D65: finney | E65: TAO | F65: transfer_out | G65: 10 | I65: 5012975-0006 | J65: 5HbnKZMzGk3GT3mpWZgKuQHq3CC8LeW2tbNq1FkBLQhzUX6L | Q65: 1 | V65: ="S-"&IF(LEN(I65)=0,B65,I65&IF(F65="fee","-00",IF(LEN(G65)>0,"-01","-02"))) -> S-5012975-0006-01 | W65: =COUNTIF(I:I,I65) -> 2 | X65: =IF(LEN(I65)>0,I65&IF(F65="fee","fee",IF(VALUE(G65)>0,"debit",IF(VALUE(H65)>0,"credit","error"))),"") -> 5012975-0006debit | Y65: =ROUND(IF(ROW(U65) = 2,K65,0)+IF(H65<>"",H65,0) + IF(R65<>"",R65,0) - IF(G65<>"",G65,0),9) -> -10
A66: 5Eq8C1NoLah4DaahQLMQ6wPLTSiAoiP35kVs9VMjaEqcSmdF | B66: 5012985 | C66: 2025-02-26T18:30:36+00:00 | D66: finney | E66: TAO | F66: fee | G66: 5e-05 | I66: 5012985-0004 | J66: root_staking_fee | Q66: 1 | V66: ="S-"&IF(LEN(I66)=0,B66,I66&IF(F66="fee","-00",IF(LEN(G66)>0,"-01","-02"))) -> S-5012985-0004-00 | W66: =COUNTIF(I:I,I66) -> 1 | X66: =IF(LEN(I66)>0,I66&IF(F66="fee","fee",IF(VALUE(G66)>0,"debit",IF(VALUE(H66)>0,"credit","error"))),"") -> 5012985-0004fee | Y66: =ROUND(IF(ROW(U66) = 2,K66,0)+IF(H66<>"",H66,0) + IF(R66<>"",R66,0) - IF(G66<>"",G66,0),9) -> -5e-05
A67: 5Eq8C1NoLah4DaahQLMQ6wPLTSiAoiP35kVs9VMjaEqcSmdF | B67: 5012990 | C67: 2025-02-26T18:31:36+00:00 | D67: finney | E67: TAO | F67: fee | G67: 0.000135263 | I67: 5012990-0005 | J67: Balances.transfer_keep_alive | Q67: 1 | V67: ="S-"&IF(LEN(I67)=0,B67,I67&IF(F67="fee","-00",IF(LEN(G67)>0,"-01","-02"))) -> S-5012990-0005-00 | W67: =COUNTIF(I:I,I67) -> 2 | X67: =IF(LEN(I67)>0,I67&IF(F67="fee","fee",IF(VALUE(G67)>0,"debit",IF(VALUE(H67)>0,"credit","error"))),"") -> 5012990-0005fee | Y67: =ROUND(IF(ROW(U67) = 2,K67,0)+IF(H67<>"",H67,0) + IF(R67<>"",R67,0) - IF(G67<>"",G67,0),9) -> -0.000135263
A68: 5Eq8C1NoLah4DaahQLMQ6wPLTSiAoiP35kVs9VMjaEqcSmdF | B68: 5012990 | C68: 2025-02-26T18:31:36+00:00 | D68: finney | E68: TAO | F68: transfer_out | G68: 30 | I68: 5012990-0005 | J68: 5HbnKZMzGk3GT3mpWZgKuQHq3CC8LeW2tbNq1FkBLQhzUX6L | Q68: 1 | V68: ="S-"&IF(LEN(I68)=0,B68,I68&IF(F68="fee","-00",IF(LEN(G68)>0,"-01","-02"))) -> S-5012990-0005-01 | W68: =COUNTIF(I:I,I68) -> 2 | X68: =IF(LEN(I68)>0,I68&IF(F68="fee","fee",IF(VALUE(G68)>0,"debit",IF(VALUE(H68)>0,"credit","error"))),"") -> 5012990-0005debit | Y68: =ROUND(IF(ROW(U68) = 2,K68,0)+IF(H68<>"",H68,0) + IF(R68<>"",R68,0) - IF(G68<>"",G68,0),9) -> -30
A69: 5Eq8C1NoLah4DaahQLMQ6wPLTSiAoiP35kVs9VMjaEqcSmdF | B69: 5013006 | C69: 2025-02-26T18:34:48+00:00 | D69: finney | E69: TAO | F69: fee | G69: 5e-05 | I69: 5013006-0007 | J69: root_staking_fee | Q69: 1 | V69: ="S-"&IF(LEN(I69)=0,B69,I69&IF(F69="fee","-00",IF(LEN(G69)>0,"-01","-02"))) -> S-5013006-0007-00 | W69: =COUNTIF(I:I,I69) -> 1 | X69: =IF(LEN(I69)>0,I69&IF(F69="fee","fee",IF(VALUE(G69)>0,"debit",IF(VALUE(H69)>0,"credit","error"))),"") -> 5013006-0007fee | Y69: =ROUND(IF(ROW(U69) = 2,K69,0)+IF(H69<>"",H69,0) + IF(R69<>"",R69,0) - IF(G69<>"",G69,0),9) -> -5e-05
A70: 5Eq8C1NoLah4DaahQLMQ6wPLTSiAoiP35kVs9VMjaEqcSmdF | B70: 5013009 | C70: 2025-02-26T18:35:24.001+00:00 | D70: finney | E70: TAO | F70: fee | G70: 0.000135263 | I70: 5013009-0009 | J70: Balances.transfer_keep_alive | Q70: 1 | V70: ="S-"&IF(LEN(I70)=0,B70,I70&IF(F70="fee","-00",IF(LEN(G70)>0,"-01","-02"))) -> S-5013009-0009-00 | W70: =COUNTIF(I:I,I70) -> 2 | X70: =IF(LEN(I70)>0,I70&IF(F70="fee","fee",IF(VALUE(G70)>0,"debit",IF(VALUE(H70)>0,"credit","error"))),"") -> 5013009-0009fee | Y70: =ROUND(IF(ROW(U70) = 2,K70,0)+IF(H70<>"",H70,0) + IF(R70<>"",R70,0) - IF(G70<>"",G70,0),9) -> -0.000135263
A71: 5Eq8C1NoLah4DaahQLMQ6wPLTSiAoiP35kVs9VMjaEqcSmdF | B71: 5013009 | C71: 2025-02-26T18:35:24.001+00:00 | D71: finney | E71: TAO | F71: transfer_out | G71: 22.78 | I71: 5013009-0009 | J71: 5HbnKZMzGk3GT3mpWZgKuQHq3CC8LeW2tbNq1FkBLQhzUX6L | Q71: 1 | V71: ="S-"&IF(LEN(I71)=0,B71,I71&IF(F71="fee","-00",IF(LEN(G71)>0,"-01","-02"))) -> S-5013009-0009-01 | W71: =COUNTIF(I:I,I71) -> 2 | X71: =IF(LEN(I71)>0,I71&IF(F71="fee","fee",IF(VALUE(G71)>0,"debit",IF(VALUE(H71)>0,"credit","error"))),"") -> 5013009-0009debit | Y71: =ROUND(IF(ROW(U71) = 2,K71,0)+IF(H71<>"",H71,0) + IF(R71<>"",R71,0) - IF(G71<>"",G71,0),9) -> -22.78
A72: 5Eq8C1NoLah4DaahQLMQ6wPLTSiAoiP35kVs9VMjaEqcSmdF | B72: 5014631 | C72: 2025-02-26T23:59:48+00:00 | D72: finney | E72: TAO | K72: 200.51022 | L72: 0.009445436 | M72: 200.50077 | N72: 0 | O72: 0 | P72: 353.0276651136952 | Q72: 1 | R72: 0.12501014 | S72: 44.13 | T72: 45714 | V72: ="S-"&IF(LEN(I72)=0,B72,I72&IF(F72="fee","-00",IF(LEN(G72)>0,"-01","-02"))) -> S-5014631 | W72: =COUNTIF(I:I,I72) -> 0 | X72: =IF(LEN(I72)>0,I72&IF(F72="fee","fee",IF(VALUE(G72)>0,"debit",IF(VALUE(H72)>0,"credit","error"))),"") | Y72: =ROUND(IF(ROW(U72) = 2,K72,0)+IF(H72<>"",H72,0) + IF(R72<>"",R72,0) - IF(G72<>"",G72,0),9) -> 0.12501014
A73: 5Eq8C1NoLah4DaahQLMQ6wPLTSiAoiP35kVs9VMjaEqcSmdF | B73: 5021831 | C73: 2025-02-27T23:59:48.001+00:00 | D73: finney | E73: TAO | K73: 200.60801 | L73: 0.009445436 | M73: 200.59856 | N73: 0 | O73: 0 | P73: 328.4399689862061 | Q73: 1 | R73: 0.097794089 | S73: 32.11 | T73: 45715 | V73: ="S-"&IF(LEN(I73)=0,B73,I73&IF(F73="fee","-00",IF(LEN(G73)>0,"-01","-02"))) -> S-5021831 | W73: =COUNTIF(I:I,I73) -> 0 | X73: =IF(LEN(I73)>0,I73&IF(F73="fee","fee",IF(VALUE(G73)>0,"debit",IF(VALUE(H73)>0,"credit","error"))),"") | Y73: =ROUND(IF(ROW(U73) = 2,K73,0)+IF(H73<>"",H73,0) + IF(R73<>"",R73,0) - IF(G73<>"",G73,0),9) -> 0.097794089
A74: 5Eq8C1NoLah4DaahQLMQ6wPLTSiAoiP35kVs9VMjaEqcSmdF | B74: 5029031 | C74: 2025-02-28T23:59:48.001+00:00 | D74: finney | E74: TAO | K74: 200.70232 | L74: 0.009445436 | M74: 200.69287 | N74: 0 | O74: 0 | P74: 328.2682382391846 | Q74: 1 | R74: 0.09431049 | S74: 30.95 | T74: 45716 | V74: ="S-"&IF(LEN(I74)=0,B74,I74&IF(F74="fee","-00",IF(LEN(G74)>0,"-01","-02"))) -> S-5029031 | W74: =COUNTIF(I:I,I74) -> 0 | X74: =IF(LEN(I74)>0,I74&IF(F74="fee","fee",IF(VALUE(G74)>0,"debit",IF(VALUE(H74)>0,"credit","error"))),"") | Y74: =ROUND(IF(ROW(U74) = 2,K74,0)+IF(H74<>"",H74,0) + IF(R74<>"",R74,0) - IF(G74<>"",G74,0),9) -> 0.09431049
A75: 5Eq8C1NoLah4DaahQLMQ6wPLTSiAoiP35kVs9VMjaEqcSmdF | B75: 5036231 | C75: 2025-03-01T23:59:48+00:00 | D75: finney | E75: TAO | K75: 200.80387 | L75: 0.009445436 | M75: 200.79442 | N75: 0 | O75: 0 | P75: 333.83509159209814 | Q75: 1 | R75: 0.10154583 | S75: 33.89 | T75: 45717 | V75: ="S-"&IF(LEN(I75)=0,B75,I75&IF(F75="fee","-00",IF(LEN(G75)>0,"-01","-02"))) -> S-5036231 | W75: =COUNTIF(I:I,I75) -> 0 | X75: =IF(LEN(I75)>0,I75&IF(F75="fee","fee",IF(VALUE(G75)>0,"debit",IF(VALUE(H75)>0,"credit","error"))),"") | Y75: =ROUND(IF(ROW(U75) = 2,K75,0)+IF(H75<>"",H75,0) + IF(R75<>"",R75,0) - IF(G75<>"",G75,0),9) -> 0.10154583
A76: 5Eq8C1NoLah4DaahQLMQ6wPLTSiAoiP35kVs9VMjaEqcSmdF | B76: 5043431 | C76: 2025-03-02T23:59:48+00:00 | D76: finney | E76: TAO | K76: 200.90406 | L76: 0.009445436 | M76: 200.89462 | N76: 0 | O76: 0 | P76: 354.1050065689894 | Q76: 1 | R76: 0.10019769 | S76: 35.48 | T76: 45718 | V76: ="S-"&IF(LEN(I76)=0,B76,I76&IF(F76="fee","-00",IF(LEN(G76)>0,"-01","-02"))) -> S-5043431 | W76: =COUNTIF(I:I,I76) -> 0 | X76: =IF(LEN(I76)>0,I76&IF(F76="fee","fee",IF(VALUE(G76)>0,"debit",IF(VALUE(H76)>0,"credit","error"))),"") | Y76: =ROUND(IF(ROW(U76) = 2,K76,0)+IF(H76<>"",H76,0) + IF(R76<>"",R76,0) - IF(G76<>"",G76,0),9) -> 0.10019769
A77: 5Eq8C1NoLah4DaahQLMQ6wPLTSiAoiP35kVs9VMjaEqcSmdF | B77: 5050631 | C77: 2025-03-03T23:59:48+00:00 | D77: finney | E77: TAO | K77: 201.01158 | L77: 0.009445436 | M77: 201.00214 | N77: 0 | O77: 0 | P77: 299.58360999929397 | Q77: 1 | R77: 0.10751835 | S77: 32.21 | T77: 45719 | V77: ="S-"&IF(LEN(I77)=0,B77,I77&IF(F77="fee","-00",IF(LEN(G77)>0,"-01","-02"))) -> S-5050631 | W77: =COUNTIF(I:I,I77) -> 0 | X77: =IF(LEN(I77)>0,I77&IF(F77="fee","fee",IF(VALUE(G77)>0,"debit",IF(VALUE(H77)>0,"credit","error"))),"") | Y77: =ROUND(IF(ROW(U77) = 2,K77,0)+IF(H77<>"",H77,0) + IF(R77<>"",R77,0) - IF(G77<>"",G77,0),9) -> 0.10751835
A78: 5Eq8C1NoLah4DaahQLMQ6wPLTSiAoiP35kVs9VMjaEqcSmdF | B78: 5055665 | C78: 2025-03-04T16:46:36+00:00 | D78: finney | E78: TAO | F78: fee | G78: 5e-05 | I78: 5055665-0003 | J78: root_staking_fee | Q78: 1 | V78: ="S-"&IF(LEN(I78)=0,B78,I78&IF(F78="fee","-00",IF(LEN(G78)>0,"-01","-02"))) -> S-5055665-0003-00 | W78: =COUNTIF(I:I,I78) -> 1 | X78: =IF(LEN(I78)>0,I78&IF(F78="fee","fee",IF(VALUE(G78)>0,"debit",IF(VALUE(H78)>0,"credit","error"))),"") -> 5055665-0003fee | Y78: =ROUND(IF(ROW(U78) = 2,K78,0)+IF(H78<>"",H78,0) + IF(R78<>"",R78,0) - IF(G78<>"",G78,0),9) -> -5e-05
A79: 5Eq8C1NoLah4DaahQLMQ6wPLTSiAoiP35kVs9VMjaEqcSmdF | B79: 5055670 | C79: 2025-03-04T16:47:36+00:00 | D79: finney | E79: TAO | F79: fee | G79: 0.000135263 | I79: 5055670-0007 | J79: Balances.transfer_keep_alive | Q79: 1 | V79: ="S-"&IF(LEN(I79)=0,B79,I79&IF(F79="fee","-00",IF(LEN(G79)>0,"-01","-02"))) -> S-5055670-0007-00 | W79: =COUNTIF(I:I,I79) -> 2 | X79: =IF(LEN(I79)>0,I79&IF(F79="fee","fee",IF(VALUE(G79)>0,"debit",IF(VALUE(H79)>0,"credit","error"))),"") -> 5055670-0007fee | Y79: =ROUND(IF(ROW(U79) = 2,K79,0)+IF(H79<>"",H79,0) + IF(R79<>"",R79,0) - IF(G79<>"",G79,0),9) -> -0.000135263
A80: 5Eq8C1NoLah4DaahQLMQ6wPLTSiAoiP35kVs9VMjaEqcSmdF | B80: 5055670 | C80: 2025-03-04T16:47:36+00:00 | D80: finney | E80: TAO | F80: transfer_out | G80: 50 | I80: 5055670-0007 | J80: 5HbnKZMzGk3GT3mpWZgKuQHq3CC8LeW2tbNq1FkBLQhzUX6L | Q80: 1 | V80: ="S-"&IF(LEN(I80)=0,B80,I80&IF(F80="fee","-00",IF(LEN(G80)>0,"-01","-02"))) -> S-5055670-0007-01 | W80: =COUNTIF(I:I,I80) -> 2 | X80: =IF(LEN(I80)>0,I80&IF(F80="fee","fee",IF(VALUE(G80)>0,"debit",IF(VALUE(H80)>0,"credit","error"))),"") -> 5055670-0007debit | Y80: =ROUND(IF(ROW(U80) = 2,K80,0)+IF(H80<>"",H80,0) + IF(R80<>"",R80,0) - IF(G80<>"",G80,0),9) -> -50
A81: 5Eq8C1NoLah4DaahQLMQ6wPLTSiAoiP35kVs9VMjaEqcSmdF | B81: 5055718 | C81: 2025-03-04T16:57:12+00:00 | D81: finney | E81: TAO | F81: fee | G81: 0.000135263 | I81: 5055718-0007 | J81: Balances.transfer_keep_alive | Q81: 1 | V81: ="S-"&IF(LEN(I81)=0,B81,I81&IF(F81="fee","-00",IF(LEN(G81)>0,"-01","-02"))) -> S-5055718-0007-00 | W81: =COUNTIF(I:I,I81) -> 2 | X81: =IF(LEN(I81)>0,I81&IF(F81="fee","fee",IF(VALUE(G81)>0,"debit",IF(VALUE(H81)>0,"credit","error"))),"") -> 5055718-0007fee | Y81: =ROUND(IF(ROW(U81) = 2,K81,0)+IF(H81<>"",H81,0) + IF(R81<>"",R81,0) - IF(G81<>"",G81,0),9) -> -0.000135263
A82: 5Eq8C1NoLah4DaahQLMQ6wPLTSiAoiP35kVs9VMjaEqcSmdF | B82: 5055718 | C82: 2025-03-04T16:57:12+00:00 | D82: finney | E82: TAO | F82: transfer_out | G82: 50 | I82: 5055718-0007 | J82: 5HbnKZMzGk3GT3mpWZgKuQHq3CC8LeW2tbNq1FkBLQhzUX6L | Q82: 1 | V82: ="S-"&IF(LEN(I82)=0,B82,I82&IF(F82="fee","-00",IF(LEN(G82)>0,"-01","-02"))) -> S-5055718-0007-01 | W82: =COUNTIF(I:I,I82) -> 2 | X82: =IF(LEN(I82)>0,I82&IF(F82="fee","fee",IF(VALUE(G82)>0,"debit",IF(VALUE(H82)>0,"credit","error"))),"") -> 5055718-0007debit | Y82: =ROUND(IF(ROW(U82) = 2,K82,0)+IF(H82<>"",H82,0) + IF(R82<>"",R82,0) - IF(G82<>"",G82,0),9) -> -50
A83: 5Eq8C1NoLah4DaahQLMQ6wPLTSiAoiP35kVs9VMjaEqcSmdF | B83: 5057831 | C83: 2025-03-04T23:59:48.001+00:00 | D83: finney | E83: TAO | K83: 101.11302 | L83: 0.00912491 | M83: 101.1039 | N83: 0 | O83: 0 | P83: 287.3521958204767 | Q83: 1 | R83: 0.10176345 | S83: 29.24 | T83: 45720 | V83: ="S-"&IF(LEN(I83)=0,B83,I83&IF(F83="fee","-00",IF(LEN(G83)>0,"-01","-02"))) -> S-5057831 | W83: =COUNTIF(I:I,I83) -> 0 | X83: =IF(LEN(I83)>0,I83&IF(F83="fee","fee",IF(VALUE(G83)>0,"debit",IF(VALUE(H83)>0,"credit","error"))),"") | Y83: =ROUND(IF(ROW(U83) = 2,K83,0)+IF(H83<>"",H83,0) + IF(R83<>"",R83,0) - IF(G83<>"",G83,0),9) -> 0.10176345
A84: 5Eq8C1NoLah4DaahQLMQ6wPLTSiAoiP35kVs9VMjaEqcSmdF | B84: 5065031 | C84: 2025-03-05T23:59:48+00:00 | D84: finney | E84: TAO | K84: 101.17687 | L84: 0.00912491 | M84: 101.16774 | N84: 0 | O84: 0 | P84: 301.40248330418353 | Q84: 1 | R84: 0.063845141 | S84: 19.24 | T84: 45721 | V84: ="S-"&IF(LEN(I84)=0,B84,I84&IF(F84="fee","-00",IF(LEN(G84)>0,"-01","-02"))) -> S-5065031 | W84: =COUNTIF(I:I,I84) -> 0 | X84: =IF(LEN(I84)>0,I84&IF(F84="fee","fee",IF(VALUE(G84)>0,"debit",IF(VALUE(H84)>0,"credit","error"))),"") | Y84: =ROUND(IF(ROW(U84) = 2,K84,0)+IF(H84<>"",H84,0) + IF(R84<>"",R84,0) - IF(G84<>"",G84,0),9) -> 0.063845141
A85: 5Eq8C1NoLah4DaahQLMQ6wPLTSiAoiP35kVs9VMjaEqcSmdF | B85: 5072231 | C85: 2025-03-06T23:59:48+00:00 | D85: finney | E85: TAO | K85: 101.23912 | L85: 0.00912491 | M85: 101.23 | N85: 0 | O85: 0 | P85: 289.33940199981885 | Q85: 1 | R85: 0.062255145 | S85: 18.01 | T85: 45722 | V85: ="S-"&IF(LEN(I85)=0,B85,I85&IF(F85="fee","-00",IF(LEN(G85)>0,"-01","-02"))) -> S-5072231 | W85: =COUNTIF(I:I,I85) -> 0 | X85: =IF(LEN(I85)>0,I85&IF(F85="fee","fee",IF(VALUE(G85)>0,"debit",IF(VALUE(H85)>0,"credit","error"))),"") | Y85: =ROUND(IF(ROW(U85) = 2,K85,0)+IF(H85<>"",H85,0) + IF(R85<>"",R85,0) - IF(G85<>"",G85,0),9) -> 0.062255145
A86: 5Eq8C1NoLah4DaahQLMQ6wPLTSiAoiP35kVs9VMjaEqcSmdF | B86: 5079431 | C86: 2025-03-07T23:59:48+00:00 | D86: finney | E86: TAO | K86: 101.3011 | L86: 0.00912491 | M86: 101.29197 | N86: 0 | O86: 0 | P86: 273.7010887205826 | Q86: 1 | R86: 0.06197379 | S86: 16.96 | T86: 45723 | V86: ="S-"&IF(LEN(I86)=0,B86,I86&IF(F86="fee","-00",IF(LEN(G86)>0,"-01","-02"))) -> S-5079431 | W86: =COUNTIF(I:I,I86) -> 0 | X86: =IF(LEN(I86)>0,I86&IF(F86="fee","fee",IF(VALUE(G86)>0,"debit",IF(VALUE(H86)>0,"credit","error"))),"") | Y86: =ROUND(IF(ROW(U86) = 2,K86,0)+IF(H86<>"",H86,0) + IF(R86<>"",R86,0) - IF(G86<>"",G86,0),9) -> 0.06197379
A87: 5Eq8C1NoLah4DaahQLMQ6wPLTSiAoiP35kVs9VMjaEqcSmdF | B87: 5086631 | C87: 2025-03-08T23:59:48+00:00 | D87: finney | E87: TAO | K87: 101.36247 | L87: 0.00912491 | M87: 101.35334 | N87: 0 | O87: 0 | P87: 274.75841 | Q87: 1 | R87: 0.061367857 | S87: 16.86 | T87: 45724 | V87: ="S-"&IF(LEN(I87)=0,B87,I87&IF(F87="fee","-00",IF(LEN(G87)>0,"-01","-02"))) -> S-5086631 | W87: =COUNTIF(I:I,I87) -> 0 | X87: =IF(LEN(I87)>0,I87&IF(F87="fee","fee",IF(VALUE(G87)>0,"debit",IF(VALUE(H87)>0,"credit","error"))),"") | Y87: =ROUND(IF(ROW(U87) = 2,K87,0)+IF(H87<>"",H87,0) + IF(R87<>"",R87,0) - IF(G87<>"",G87,0),9) -> 0.061367857
A88: 5Eq8C1NoLah4DaahQLMQ6wPLTSiAoiP35kVs9VMjaEqcSmdF | B88: 5093831 | C88: 2025-03-09T23:59:48+00:00 | D88: finney | E88: TAO | K88: 101.42406 | L88: 0.00912491 | M88: 101.41494 | N88: 0 | O88: 0 | P88: 242.76481749745057 | Q88: 1 | R88: 0.061593839 | S88: 14.95 | T88: 45725 | V88: ="S-"&IF(LEN(I88)=0,B88,I88&IF(F88="fee","-00",IF(LEN(G88)>0,"-01","-02"))) -> S-5093831 | W88: =COUNTIF(I:I,I88) -> 0 | X88: =IF(LEN(I88)>0,I88&IF(F88="fee","fee",IF(VALUE(G88)>0,"debit",IF(VALUE(H88)>0,"credit","error"))),"") | Y88: =ROUND(IF(ROW(U88) = 2,K88,0)+IF(H88<>"",H88,0) + IF(R88<>"",R88,0) - IF(G88<>"",G88,0),9) -> 0.061593839
A89: 5Eq8C1NoLah4DaahQLMQ6wPLTSiAoiP35kVs9VMjaEqcSmdF | B89: 5101031 | C89: 2025-03-10T23:59:48+00:00 | D89: finney | E89: TAO | K89: 101.48192 | L89: 0.00912491 | M89: 101.4728 | N89: 0 | O89: 0 | P89: 229.27625012042927 | Q89: 1 | R89: 0.057860691 | S89: 13.26 | T89: 45726 | V89: ="S-"&IF(LEN(I89)=0,B89,I89&IF(F89="fee","-00",IF(LEN(G89)>0,"-01","-02"))) -> S-5101031 | W89: =COUNTIF(I:I,I89) -> 0 | X89: =IF(LEN(I89)>0,I89&IF(F89="fee","fee",IF(VALUE(G89)>0,"debit",IF(VALUE(H89)>0,"credit","error"))),"") | Y89: =ROUND(IF(ROW(U89) = 2,K89,0)+IF(H89<>"",H89,0) + IF(R89<>"",R89,0) - IF(G89<>"",G89,0),9) -> 0.057860691
A90: 5Eq8C1NoLah4DaahQLMQ6wPLTSiAoiP35kVs9VMjaEqcSmdF | B90: 5108231 | C90: 2025-03-11T23:59:48+00:00 | D90: finney | E90: TAO | K90: 101.53432 | L90: 0.00912491 | M90: 101.52519 | N90: 0 | O90: 0 | P90: 259.1499531050776 | Q90: 1 | R90: 0.052396977 | S90: 13.57 | T90: 45727 | V90: ="S-"&IF(LEN(I90)=0,B90,I90&IF(F90="fee","-00",IF(LEN(G90)>0,"-01","-02"))) -> S-5108231 | W90: =COUNTIF(I:I,I90) -> 0 | X90: =IF(LEN(I90)>0,I90&IF(F90="fee","fee",IF(VALUE(G90)>0,"debit",IF(VALUE(H90)>0,"credit","error"))),"") | Y90: =ROUND(IF(ROW(U90) = 2,K90,0)+IF(H90<>"",H90,0) + IF(R90<>"",R90,0) - IF(G90<>"",G90,0),9) -> 0.052396977
A91: 5Eq8C1NoLah4DaahQLMQ6wPLTSiAoiP35kVs9VMjaEqcSmdF | B91: 5115431 | C91: 2025-03-12T23:59:48.001+00:00 | D91: finney | E91: TAO | K91: 101.58261 | L91: 0.00912491 | M91: 101.57348 | N91: 0 | O91: 0 | P91: 258.62136606697896 | Q91: 1 | R91: 0.048289917 | S91: 12.48 | T91: 45728 | V91: ="S-"&IF(LEN(I91)=0,B91,I91&IF(F91="fee","-00",IF(LEN(G91)>0,"-01","-02"))) -> S-5115431 | W91: =COUNTIF(I:I,I91) -> 0 | X91: =IF(LEN(I91)>0,I91&IF(F91="fee","fee",IF(VALUE(G91)>0,"debit",IF(VALUE(H91)>0,"credit","error"))),"") | Y91: =ROUND(IF(ROW(U91) = 2,K91,0)+IF(H91<>"",H91,0) + IF(R91<>"",R91,0) - IF(G91<>"",G91,0),9) -> 0.048289917
A92: 5Eq8C1NoLah4DaahQLMQ6wPLTSiAoiP35kVs9VMjaEqcSmdF | B92: 5122631 | C92: 2025-03-13T23:59:48+00:00 | D92: finney | E92: TAO | K92: 101.62806 | L92: 0.00912491 | M92: 101.61893 | N92: 0 | O92: 0 | P92: 238.0610245131248 | Q92: 1 | R92: 0.045447525 | S92: 10.81 | T92: 45729 | V92: ="S-"&IF(LEN(I92)=0,B92,I92&IF(F92="fee","-00",IF(LEN(G92)>0,"-01","-02"))) -> S-5122631 | W92: =COUNTIF(I:I,I92) -> 0 | X92: =IF(LEN(I92)>0,I92&IF(F92="fee","fee",IF(VALUE(G92)>0,"debit",IF(VALUE(H92)>0,"credit","error"))),"") | Y92: =ROUND(IF(ROW(U92) = 2,K92,0)+IF(H92<>"",H92,0) + IF(R92<>"",R92,0) - IF(G92<>"",G92,0),9) -> 0.045447525
A93: 5Eq8C1NoLah4DaahQLMQ6wPLTSiAoiP35kVs9VMjaEqcSmdF | B93: 5129831 | C93: 2025-03-14T23:59:48+00:00 | D93: finney | E93: TAO | K93: 101.67181 | L93: 0.00912491 | M93: 101.66268 | N93: 0 | O93: 0 | P93: 259.1621695866515 | Q93: 1 | R93: 0.043750627 | S93: 11.33 | T93: 45730 | V93: ="S-"&IF(LEN(I93)=0,B93,I93&IF(F93="fee","-00",IF(LEN(G93)>0,"-01","-02"))) -> S-5129831 | W93: =COUNTIF(I:I,I93) -> 0 | X93: =IF(LEN(I93)>0,I93&IF(F93="fee","fee",IF(VALUE(G93)>0,"debit",IF(VALUE(H93)>0,"credit","error"))),"") | Y93: =ROUND(IF(ROW(U93) = 2,K93,0)+IF(H93<>"",H93,0) + IF(R93<>"",R93,0) - IF(G93<>"",G93,0),9) -> 0.043750627
A94: 5Eq8C1NoLah4DaahQLMQ6wPLTSiAoiP35kVs9VMjaEqcSmdF | B94: 5137031 | C94: 2025-03-15T23:59:48+00:00 | D94: finney | E94: TAO | K94: 101.71281 | L94: 0.00912491 | M94: 101.70369 | N94: 0 | O94: 0 | P94: 258.32030492499484 | Q94: 1 | R94: 0.04100522 | S94: 10.59 | T94: 45731 | V94: ="S-"&IF(LEN(I94)=0,B94,I94&IF(F94="fee","-00",IF(LEN(G94)>0,"-01","-02"))) -> S-5137031 | W94: =COUNTIF(I:I,I94) -> 0 | X94: =IF(LEN(I94)>0,I94&IF(F94="fee","fee",IF(VALUE(G94)>0,"debit",IF(VALUE(H94)>0,"credit","error"))),"") | Y94: =ROUND(IF(ROW(U94) = 2,K94,0)+IF(H94<>"",H94,0) + IF(R94<>"",R94,0) - IF(G94<>"",G94,0),9) -> 0.04100522
A95: 5Eq8C1NoLah4DaahQLMQ6wPLTSiAoiP35kVs9VMjaEqcSmdF | B95: 5144231 | C95: 2025-03-16T23:59:48+00:00 | D95: finney | E95: TAO | K95: 101.75376 | L95: 0.00912491 | M95: 101.74464 | N95: 0 | O95: 0 | P95: 241.73464126415553 | Q95: 1 | R95: 0.040952288 | S95: 9.89 | T95: 45732 | V95: ="S-"&IF(LEN(I95)=0,B95,I95&IF(F95="fee","-00",IF(LEN(G95)>0,"-01","-02"))) -> S-5144231 | W95: =COUNTIF(I:I,I95) -> 0 | X95: =IF(LEN(I95)>0,I95&IF(F95="fee","fee",IF(VALUE(G95)>0,"debit",IF(VALUE(H95)>0,"credit","error"))),"") | Y95: =ROUND(IF(ROW(U95) = 2,K95,0)+IF(H95<>"",H95,0) + IF(R95<>"",R95,0) - IF(G95<>"",G95,0),9) -> 0.040952288
A96: 5Eq8C1NoLah4DaahQLMQ6wPLTSiAoiP35kVs9VMjaEqcSmdF | B96: 5151431 | C96: 2025-03-17T23:59:48+00:00 | D96: finney | E96: TAO | K96: 101.79413 | L96: 0.00912491 | M96: 101.785 | N96: 0 | O96: 0 | P96: 254.8595370934711 | Q96: 1 | R96: 0.040362484 | S96: 10.28 | T96: 45733 | V96: ="S-"&IF(LEN(I96)=0,B96,I96&IF(F96="fee","-00",IF(LEN(G96)>0,"-01","-02"))) -> S-5151431 | W96: =COUNTIF(I:I,I96) -> 0 | X96: =IF(LEN(I96)>0,I96&IF(F96="fee","fee",IF(VALUE(G96)>0,"debit",IF(VALUE(H96)>0,"credit","error"))),"") | Y96: =ROUND(IF(ROW(U96) = 2,K96,0)+IF(H96<>"",H96,0) + IF(R96<>"",R96,0) - IF(G96<>"",G96,0),9) -> 0.040362484
A97: 5Eq8C1NoLah4DaahQLMQ6wPLTSiAoiP35kVs9VMjaEqcSmdF | B97: 5158631 | C97: 2025-03-18T23:59:48+00:00 | D97: finney | E97: TAO | K97: 101.83514 | L97: 0.00912491 | M97: 101.82601 | N97: 0 | O97: 0 | P97: 247.69665889339535 | Q97: 1 | R97: 0.041011448 | S97: 10.15 | T97: 45734 | V97: ="S-"&IF(LEN(I97)=0,B97,I97&IF(F97="fee","-00",IF(LEN(G97)>0,"-01","-02"))) -> S-5158631 | W97: =COUNTIF(I:I,I97) -> 0 | X97: =IF(LEN(I97)>0,I97&IF(F97="fee","fee",IF(VALUE(G97)>0,"debit",IF(VALUE(H97)>0,"credit","error"))),"") | Y97: =ROUND(IF(ROW(U97) = 2,K97,0)+IF(H97<>"",H97,0) + IF(R97<>"",R97,0) - IF(G97<>"",G97,0),9) -> 0.041011448
A98: 5Eq8C1NoLah4DaahQLMQ6wPLTSiAoiP35kVs9VMjaEqcSmdF | B98: 5165831 | C98: 2025-03-19T23:59:48+00:00 | D98: finney | E98: TAO | K98: 101.87728 | L98: 0.00912491 | M98: 101.86815 | N98: 0 | O98: 0 | P98: 262.8715481150947 | Q98: 1 | R98: 0.042142183 | S98: 11.07 | T98: 45735 | V98: ="S-"&IF(LEN(I98)=0,B98,I98&IF(F98="fee","-00",IF(LEN(G98)>0,"-01","-02"))) -> S-5165831 | W98: =COUNTIF(I:I,I98) -> 0 | X98: =IF(LEN(I98)>0,I98&IF(F98="fee","fee",IF(VALUE(G98)>0,"debit",IF(VALUE(H98)>0,"credit","error"))),"") | Y98: =ROUND(IF(ROW(U98) = 2,K98,0)+IF(H98<>"",H98,0) + IF(R98<>"",R98,0) - IF(G98<>"",G98,0),9) -> 0.042142183
A99: 5Eq8C1NoLah4DaahQLMQ6wPLTSiAoiP35kVs9VMjaEqcSmdF | B99: 5173031 | C99: 2025-03-20T23:59:48.001+00:00 | D99: finney | E99: TAO | K99: 101.9215 | L99: 0.00912491 | M99: 101.91238 | N99: 0 | O99: 0 | P99: 251.1322633024525 | Q99: 1 | R99: 0.044224138 | S99: 11.1 | T99: 45736 | V99: ="S-"&IF(LEN(I99)=0,B99,I99&IF(F99="fee","-00",IF(LEN(G99)>0,"-01","-02"))) -> S-5173031 | W99: =COUNTIF(I:I,I99) -> 0 | X99: =IF(LEN(I99)>0,I99&IF(F99="fee","fee",IF(VALUE(G99)>0,"debit",IF(VALUE(H99)>0,"credit","error"))),"") | Y99: =ROUND(IF(ROW(U99) = 2,K99,0)+IF(H99<>"",H99,0) + IF(R99<>"",R99,0) - IF(G99<>"",G99,0),9) -> 0.044224138
... A105: 5Eq8C1NoLah4DaahQLMQ6wPLTSiAoiP35kVs9VMjaEqcSmdF | B105: 5216231 | C105: 2025-03-26T23:59:48+00:00 | D105: finney | E105: TAO | K105: 102.14342 | L105: 0.00912491 | M105: 102.13429 | N105: 0 | O105: 0 | P105: 260.8775109564897 | Q105: 1 | R105: 0.035881616 | S105: 9.36 | T105: 45742 | V105: ="S-"&IF(LEN(I105)=0,B105,I105&IF(F105="fee","-00",IF(LEN(G105)>0,"-01","-02"))) -> S-5216231 | W105: =COUNTIF(I:I,I105) -> 0 | X105: =IF(LEN(I105)>0,I105&IF(F105="fee","fee",IF(VALUE(G105)>0,"debit",IF(VALUE(H105)>0,"credit","error"))),"") | Y105: =ROUND(IF(ROW(U105) = 2,K105,0)+IF(H105<>"",H105,0) + IF(R105<>"",R105,0) - IF(G105<>"",G105,0),9) -> 0.035881616
A106: 5Eq8C1NoLah4DaahQLMQ6wPLTSiAoiP35kVs9VMjaEqcSmdF | B106: 5223431 | C106: 2025-03-27T23:59:48+00:00 | D106: finney | E106: TAO | K106: 102.17516 | L106: 0.00912491 | M106: 102.16603 | N106: 0 | O106: 0 | P106: 269.59262 | Q106: 1 | R106: 0.031743127 | S106: 8.55 | T106: 45743 | V106: ="S-"&IF(LEN(I106)=0,B106,I106&IF(F106="fee","-00",IF(LEN(G106)>0,"-01","-02"))) -> S-5223431 | W106: =COUNTIF(I:I,I106) -> 0 | X106: =IF(LEN(I106)>0,I106&IF(F106="fee","fee",IF(VALUE(G106)>0,"debit",IF(VALUE(H106)>0,"credit","error"))),"") | Y106: =ROUND(IF(ROW(U106) = 2,K106,0)+IF(H106<>"",H106,0) + IF(R106<>"",R106,0) - IF(G106<>"",G106,0),9) -> 0.031743127
A107: 5Eq8C1NoLah4DaahQLMQ6wPLTSiAoiP35kVs9VMjaEqcSmdF | B107: 5230631 | C107: 2025-03-28T23:59:48+00:00 | D107: finney | E107: TAO | K107: 102.20692 | L107: 0.00912491 | M107: 102.19779 | N107: 0 | O107: 0 | P107: 244.87748 | Q107: 1 | R107: 0.031756306 | S107: 7.77 | T107: 45744 | V107: ="S-"&IF(LEN(I107)=0,B107,I107&IF(F107="fee","-00",IF(LEN(G107)>0,"-01","-02"))) -> S-5230631 | W107: =COUNTIF(I:I,I107) -> 0 | X107: =IF(LEN(I107)>0,I107&IF(F107="fee","fee",IF(VALUE(G107)>0,"debit",IF(VALUE(H107)>0,"credit","error"))),"") | Y107: =ROUND(IF(ROW(U107) = 2,K107,0)+IF(H107<>"",H107,0) + IF(R107<>"",R107,0) - IF(G107<>"",G107,0),9) -> 0.031756306
...

Sheet website_csv (pro)
D1: debit | F1: credit | H1: fee | N1: fee | O1: debit | P1: credit | X1: From Here Checks to make sure that the Amounts from taostats are not duplicated | AI1: -1e-10
A2: Date (UTC) | B2: Platform (Optional) | C2: Asset Sent | D2: Amount Sent | E2: Asset Received | F2: Amount Received | G2: Fee Currency (Optional) | H2: Fee Amount (Optional) | I2: Type | J2: Description (Optional) | K2: TxHash (Optional) | L2: Net Worth Amount | M2: Net Worth Currency | N2: tx hash fee count | O2: tx Hash debit count | P2: tx Hash credit count | Q2: Merge | R2: count of extrinsics | S2: Text Row or blank row | T2: Import Row | U2: Check Row | W2: fee | X2: debit | Y2: credit | Z2: fee | AB2: import checks - balances not changed | AI2: =-AI1 -> 1e-10
A3: =MID(Taostats_CSV!C3,6,2)&"/"&MID(Taostats_CSV!C3,9,2)&"/"&LEFT(Taostats_CSV!C3,4)&" "&MID(Taostats_CSV!C3,12,8) -> 12/31/2024 23:59:48 | C3: =IF(Q3,OFFSET(Taostats_CSV!$E$1,MATCH(K3&D$1,Taostats_CSV!$X:$X,0)-1,0),IF(Taostats_CSV!F3="fee",IF(VALUE(Taostats_CSV!G3)>0,Taostats_CSV!E3,""),"")) | D3: =IF(Q3,OFFSET(Taostats_CSV!$G$1,MATCH(K3&D$1,Taostats_CSV!$X:$X,0)-1,0),IF(Taostats_CSV!F3="fee",IF(VALUE(Taostats_CSV!G3)>0,Taostats_CSV!G3,""),"")) | E3: =IF(AND(Q3,P3>0),OFFSET(Taostats_CSV!$E$1,MATCH(K3&F$1,Taostats_CSV!$X:$X,0)-1,0),IF(LEN(F3)>0,Taostats_CSV!E3,"")) -> TAO | F3: =TRIM(IF(AND(Q3,P3>0),OFFSET(Taostats_CSV!$H$1,MATCH(K3&F$1,Taostats_CSV!$X:$X,0)-1,0),IF(LEN(Taostats_CSV!H3)>0,Taostats_CSV!H3,Taostats_CSV!R3))) -> 256.530086193 | G3: =IF(AND(Q3,N3=1),OFFSET(Taostats_CSV!$E$1,MATCH(K3&H$1,Taostats_CSV!$X:$X,0)-1,0),"") | H3: =IF(AND(Q3,N3=1),OFFSET(Taostats_CSV!$G$1,MATCH(K3&H$1,Taostats_CSV!$X:$X,0)-1,0),"") | I3: =IF(AND(LEN(K3)=0,LEN(F3)>0),"Income",IF(AND(O3>0,P3>0,C3<>E3),"Trade",IF(AND(NOT(Q3),Taostats_CSV!F3="fee"),'READ ME'!$C$5,""))) -> Income | J3: =SUBSTITUTE(IF(LEN(I3)=0,Taostats_CSV!F3&" "&Taostats_CSV!J3,IF(I3="Cost","Extrinsic fee","")),"_"," ") | K3: =TRIM(IF(LEN(Taostats_CSV!I3)>0,Taostats_CSV!I3,"")) | L3: =IF(Taostats_CSV!E3<>"TAO",IF(LEN(F3)>0,F3,IF(LEN(D3)>0,D3,0))*Taostats_CSV!P3,"") | M3: =IF(LEN(L3)>0,"USD","") | N3: =COUNTIF(Taostats_CSV!$X:$X,Taostats_CSV!$I3&N$1) -> 0 | O3: =COUNTIF(Taostats_CSV!$X:$X,Taostats_CSV!$I3&O$1) -> 0 | P3: =COUNTIF(Taostats_CSV!$X:$X,Taostats_CSV!$I3&P$1) -> 0 | Q3: =AND(O3<=1,N3<=1,P3<=1,O3+N3+P3>=2) -> FALSE | R3: =IF(LEN(K3)>0,COUNTIF($K$3:K3,K3),FALSE) -> FALSE | S3: =IF(Taostats_CSV!A3=Taostats_CSV!$A$2,TRUE,Taostats_CSV!G3+Taostats_CSV!H3+Taostats_CSV!R3=0) -> FALSE | T3: =AND(NOT(S3),OR(NOT(Q3),R3=1)) -> TRUE | U3: {=AND(T3,OR(O3-N3>1,P3>1,ISERROR(A3:P3)))} -> FALSE | W3: =MATCH(K3&$W$2,Taostats_CSV!$X$3:$X$1167,0) -> #N/A | X3: =VALUE(D3) -> #VALUE! | Y3: =VALUE(F3) -> 256.53009 | Z3: =VALUE(H3) -> #VALUE! | AB3: CSV | AE3: Import CSV | AH3: Check | AI3: error highlight
A4: =MID(Taostats_CSV!C4,6,2)&"/"&MID(Taostats_CSV!C4,9,2)&"/"&LEFT(Taostats_CSV!C4,4)&" "&MID(Taostats_CSV!C4,12,8) -> 01/01/2025 23:59:48 | C4: =IF(Q4,OFFSET(Taostats_CSV!$E$1,MATCH(K4&D$1,Taostats_CSV!$X:$X,0)-1,0),IF(Taostats_CSV!F4="fee",IF(VALUE(Taostats_CSV!G4)>0,Taostats_CSV!E4,""),"")) | D4: =IF(Q4,OFFSET(Taostats_CSV!$G$1,MATCH(K4&D$1,Taostats_CSV!$X:$X,0)-1,0),IF(Taostats_CSV!F4="fee",IF(VALUE(Taostats_CSV!G4)>0,Taostats_CSV!G4,""),"")) | E4: =IF(AND(Q4,P4>0),OFFSET(Taostats_CSV!$E$1,MATCH(K4&F$1,Taostats_CSV!$X:$X,0)-1,0),IF(LEN(F4)>0,Taostats_CSV!E4,"")) -> TAO | F4: =TRIM(IF(AND(Q4,P4>0),OFFSET(Taostats_CSV!$H$1,MATCH(K4&F$1,Taostats_CSV!$X:$X,0)-1,0),IF(LEN(Taostats_CSV!H4)>0,Taostats_CSV!H4,Taostats_CSV!R4))) -> 0.130885389 | G4: =IF(AND(Q4,N4=1),OFFSET(Taostats_CSV!$E$1,MATCH(K4&H$1,Taostats_CSV!$X:$X,0)-1,0),"") | H4: =IF(AND(Q4,N4=1),OFFSET(Taostats_CSV!$G$1,MATCH(K4&H$1,Taostats_CSV!$X:$X,0)-1,0),"") | I4: =IF(AND(LEN(K4)=0,LEN(F4)>0),"Income",IF(AND(O4>0,P4>0,C4<>E4),"Trade",IF(AND(NOT(Q4),Taostats_CSV!F4="fee"),'READ ME'!$C$5,""))) -> Income | J4: =SUBSTITUTE(IF(LEN(I4)=0,Taostats_CSV!F4&" "&Taostats_CSV!J4,IF(I4="Cost","Extrinsic fee","")),"_"," ") | K4: =TRIM(IF(LEN(Taostats_CSV!I4)>0,Taostats_CSV!I4,"")) | L4: =IF(Taostats_CSV!E4<>"TAO",IF(LEN(F4)>0,F4,IF(LEN(D4)>0,D4,0))*Taostats_CSV!P4,"") | M4: =IF(LEN(L4)>0,"USD","") | N4: =COUNTIF(Taostats_CSV!$X:$X,Taostats_CSV!$I4&N$1) -> 0 | O4: =COUNTIF(Taostats_CSV!$X:$X,Taostats_CSV!$I4&O$1) -> 0 | P4: =COUNTIF(Taostats_CSV!$X:$X,Taostats_CSV!$I4&P$1) -> 0 | Q4: =AND(O4<=1,N4<=1,P4<=1,O4+N4+P4>=2) -> FALSE | R4: =IF(LEN(K4)>0,COUNTIF($K$3:K4,K4),FALSE) -> FALSE | S4: =IF(Taostats_CSV!A4=Taostats_CSV!$A$2,TRUE,Taostats_CSV!G4+Taostats_CSV!H4+Taostats_CSV!R4=0) -> FALSE | T4: =AND(NOT(S4),OR(NOT(Q4),R4=1)) -> TRUE | U4: {=AND(T4,OR(O4-N4>1,P4>1,ISERROR(A4:P4)))} -> FALSE | W4: =MATCH(K4&$W$2,Taostats_CSV!$X$3:$X$1167,0) -> #N/A | X4: =VALUE(D4) -> #VALUE! | Y4: =VALUE(F4) -> 0.13088539 | Z4: =VALUE(H4) -> #VALUE! | AA4: {=_xlfn.UNIQUE(Taostats_CSV!E2:E9994)} -> Token | AB4: debit | AC4: Credit | AD4: income | AE4: debit | AF4: credit | AG4: fees | AH4: debit | AI4: credit
A5: =MID(Taostats_CSV!C5,6,2)&"/"&MID(Taostats_CSV!C5,9,2)&"/"&LEFT(Taostats_CSV!C5,4)&" "&MID(Taostats_CSV!C5,12,8) -> 01/02/2025 23:59:48 | C5: =IF(Q5,OFFSET(Taostats_CSV!$E$1,MATCH(K5&D$1,Taostats_CSV!$X:$X,0)-1,0),IF(Taostats_CSV!F5="fee",IF(VALUE(Taostats_CSV!G5)>0,Taostats_CSV!E5,""),"")) | D5: =IF(Q5,OFFSET(Taostats_CSV!$G$1,MATCH(K5&D$1,Taostats_CSV!$X:$X,0)-1,0),IF(Taostats_CSV!F5="fee",IF(VALUE(Taostats_CSV!G5)>0,Taostats_CSV!G5,""),"")) | E5: =IF(AND(Q5,P5>0),OFFSET(Taostats_CSV!$E$1,MATCH(K5&F$1,Taostats_CSV!$X:$X,0)-1,0),IF(LEN(F5)>0,Taostats_CSV!E5,"")) -> TAO | F5: =TRIM(IF(AND(Q5,P5>0),OFFSET(Taostats_CSV!$H$1,MATCH(K5&F$1,Taostats_CSV!$X:$X,0)-1,0),IF(LEN(Taostats_CSV!H5)>0,Taostats_CSV!H5,Taostats_CSV!R5))) -> 0.111661269 | G5: =IF(AND(Q5,N5=1),OFFSET(Taostats_CSV!$E$1,MATCH(K5&H$1,Taostats_CSV!$X:$X,0)-1,0),"") | H5: =IF(AND(Q5,N5=1),OFFSET(Taostats_CSV!$G$1,MATCH(K5&H$1,Taostats_CSV!$X:$X,0)-1,0),"") | I5: =IF(AND(LEN(K5)=0,LEN(F5)>0),"Income",IF(AND(O5>0,P5>0,C5<>E5),"Trade",IF(AND(NOT(Q5),Taostats_CSV!F5="fee"),'READ ME'!$C$5,""))) -> Income | J5: =SUBSTITUTE(IF(LEN(I5)=0,Taostats_CSV!F5&" "&Taostats_CSV!J5,IF(I5="Cost","Extrinsic fee","")),"_"," ") | K5: =TRIM(IF(LEN(Taostats_CSV!I5)>0,Taostats_CSV!I5,"")) | L5: =IF(Taostats_CSV!E5<>"TAO",IF(LEN(F5)>0,F5,IF(LEN(D5)>0,D5,0))*Taostats_CSV!P5,"") | M5: =IF(LEN(L5)>0,"USD","") | N5: =COUNTIF(Taostats_CSV!$X:$X,Taostats_CSV!$I5&N$1) -> 0 | O5: =COUNTIF(Taostats_CSV!$X:$X,Taostats_CSV!$I5&O$1) -> 0 | P5: =COUNTIF(Taostats_CSV!$X:$X,Taostats_CSV!$I5&P$1) -> 0 | Q5: =AND(O5<=1,N5<=1,P5<=1,O5+N5+P5>=2) -> FALSE | R5: =IF(LEN(K5)>0,COUNTIF($K$3:K5,K5),FALSE) -> FALSE | S5: =IF(Taostats_CSV!A5=Taostats_CSV!$A$2,TRUE,Taostats_CSV!G5+Taostats_CSV!H5+Taostats_CSV!R5=0) -> FALSE | T5: =AND(NOT(S5),OR(NOT(Q5),R5=1)) -> TRUE | U5: {=AND(T5,OR(O5-N5>1,P5>1,ISERROR(A5:P5)))} -> FALSE | W5: =MATCH(K5&$W$2,Taostats_CSV!$X$3:$X$1167,0) -> #N/A | X5: =VALUE(D5) -> #VALUE! | Y5: =VALUE(F5) -> 0.11166127 | Z5: =VALUE(H5) -> #VALUE! | AA5: TAO | AB5: =SUMIF(Taostats_CSV!$E:$E,AA5,Taostats_CSV!G:G) -> 454.28461 | AC5: =SUMIF(Taostats_CSV!$E:$E,AA5,Taostats_CSV!H:H) -> 186.91962 | AD5: =SUMIF(Taostats_CSV!$E:$E,AA5,Taostats_CSV!R:R) -> 267.39839 | AE5: =SUMIFS($X:$X,$C:$C,$AA5,$T:$T,TRUE) -> 454.28299 | AF5: =SUMIFS($Y:$Y,$E:$E,$AA5,$T:$T,TRUE) -> 454.31801 | AG5: =SUMIFS($H:$H,$G:$G,$AA5,$T:$T,TRUE) -> 0.001619382 | AH5: =AE5+AG5-AB5 -> 0 | AI5: =AF5-AD5-AC5 -> 0
A6: =MID(Taostats_CSV!C6,6,2)&"/"&MID(Taostats_CSV!C6,9,2)&"/"&LEFT(Taostats_CSV!C6,4)&" "&MID(Taostats_CSV!C6,12,8) -> 01/03/2025 23:59:48 | C6: =IF(Q6,OFFSET(Taostats_CSV!$E$1,MATCH(K6&D$1,Taostats_CSV!$X:$X,0)-1,0),IF(Taostats_CSV!F6="fee",IF(VALUE(Taostats_CSV!G6)>0,Taostats_CSV!E6,""),"")) | D6: =IF(Q6,OFFSET(Taostats_CSV!$G$1,MATCH(K6&D$1,Taostats_CSV!$X:$X,0)-1,0),IF(Taostats_CSV!F6="fee",IF(VALUE(Taostats_CSV!G6)>0,Taostats_CSV!G6,""),"")) | E6: =IF(AND(Q6,P6>0),OFFSET(Taostats_CSV!$E$1,MATCH(K6&F$1,Taostats_CSV!$X:$X,0)-1,0),IF(LEN(F6)>0,Taostats_CSV!E6,"")) -> TAO | F6: =TRIM(IF(AND(Q6,P6>0),OFFSET(Taostats_CSV!$H$1,MATCH(K6&F$1,Taostats_CSV!$X:$X,0)-1,0),IF(LEN(Taostats_CSV!H6)>0,Taostats_CSV!H6,Taostats_CSV!R6))) -> 0.112610101 | G6: =IF(AND(Q6,N6=1),OFFSET(Taostats_CSV!$E$1,MATCH(K6&H$1,Taostats_CSV!$X:$X,0)-1,0),"") | H6: =IF(AND(Q6,N6=1),OFFSET(Taostats_CSV!$G$1,MATCH(K6&H$1,Taostats_CSV!$X:$X,0)-1,0),"") | I6: =IF(AND(LEN(K6)=0,LEN(F6)>0),"Income",IF(AND(O6>0,P6>0,C6<>E6),"Trade",IF(AND(NOT(Q6),Taostats_CSV!F6="fee"),'READ ME'!$C$5,""))) -> Income | J6: =SUBSTITUTE(IF(LEN(I6)=0,Taostats_CSV!F6&" "&Taostats_CSV!J6,IF(I6="Cost","Extrinsic fee","")),"_"," ") | K6: =TRIM(IF(LEN(Taostats_CSV!I6)>0,Taostats_CSV!I6,"")) | L6: =IF(Taostats_CSV!E6<>"TAO",IF(LEN(F6)>0,F6,IF(LEN(D6)>0,D6,0))*Taostats_CSV!P6,"") | M6: =IF(LEN(L6)>0,"USD","") | N6: =COUNTIF(Taostats_CSV!$X:$X,Taostats_CSV!$I6&N$1) -> 0 | O6: =COUNTIF(Taostats_CSV!$X:$X,Taostats_CSV!$I6&O$1) -> 0 | P6: =COUNTIF(Taostats_CSV!$X:$X,Taostats_CSV!$I6&P$1) -> 0 | Q6: =AND(O6<=1,N6<=1,P6<=1,O6+N6+P6>=2) -> FALSE | R6: =IF(LEN(K6)>0,COUNTIF($K$3:K6,K6),FALSE) -> FALSE | S6: =IF(Taostats_CSV!A6=Taostats_CSV!$A$2,TRUE,Taostats_CSV!G6+Taostats_CSV!H6+Taostats_CSV!R6=0) -> FALSE | T6: =AND(NOT(S6),OR(NOT(Q6),R6=1)) -> TRUE | U6: {=AND(T6,OR(O6-N6>1,P6>1,ISERROR(A6:P6)))} -> FALSE | W6: =MATCH(K6&$W$2,Taostats_CSV!$X$3:$X$1167,0) -> #N/A | X6: =VALUE(D6) -> #VALUE! | Y6: =VALUE(F6) -> 0.1126101 | Z6: =VALUE(H6) -> #VALUE! | AA6: SN3 | AB6: =SUMIF(Taostats_CSV!$E:$E,AA6,Taostats_CSV!G:G) -> 280.06029 | AC6: =SUMIF(Taostats_CSV!$E:$E,AA6,Taostats_CSV!H:H) -> 201.89081 | AD6: =SUMIF(Taostats_CSV!$E:$E,AA6,Taostats_CSV!R:R) -> 78.169487 | AE6: =SUMIFS($X:$X,$C:$C,$AA6,$T:$T,TRUE) -> 280.06029 | AF6: =SUMIFS($Y:$Y,$E:$E,$AA6,$T:$T,TRUE) -> 280.06029 | AG6: =SUMIFS($H:$H,$G:$G,$AA6,$T:$T,TRUE) -> 0 | AH6: =AE6+AG6-AB6 -> 0 | AI6: =AF6-AD6-AC6 -> 0
A7: =MID(Taostats_CSV!C7,6,2)&"/"&MID(Taostats_CSV!C7,9,2)&"/"&LEFT(Taostats_CSV!C7,4)&" "&MID(Taostats_CSV!C7,12,8) -> 01/04/2025 23:59:48 | C7: =IF(Q7,OFFSET(Taostats_CSV!$E$1,MATCH(K7&D$1,Taostats_CSV!$X:$X,0)-1,0),IF(Taostats_CSV!F7="fee",IF(VALUE(Taostats_CSV!G7)>0,Taostats_CSV!E7,""),"")) | D7: =IF(Q7,OFFSET(Taostats_CSV!$G$1,MATCH(K7&D$1,Taostats_CSV!$X:$X,0)-1,0),IF(Taostats_CSV!F7="fee",IF(VALUE(Taostats_CSV!G7)>0,Taostats_CSV!G7,""),"")) | E7: =IF(AND(Q7,P7>0),OFFSET(Taostats_CSV!$E$1,MATCH(K7&F$1,Taostats_CSV!$X:$X,0)-1,0),IF(LEN(F7)>0,Taostats_CSV!E7,"")) -> TAO | F7: =TRIM(IF(AND(Q7,P7>0),OFFSET(Taostats_CSV!$H$1,MATCH(K7&F$1,Taostats_CSV!$X:$X,0)-1,0),IF(LEN(Taostats_CSV!H7)>0,Taostats_CSV!H7,Taostats_CSV!R7))) -> 0.111114908 | G7: =IF(AND(Q7,N7=1),OFFSET(Taostats_CSV!$E$1,MATCH(K7&H$1,Taostats_CSV!$X:$X,0)-1,0),"") | H7: =IF(AND(Q7,N7=1),OFFSET(Taostats_CSV!$G$1,MATCH(K7&H$1,Taostats_CSV!$X:$X,0)-1,0),"") | I7: =IF(AND(LEN(K7)=0,LEN(F7)>0),"Income",IF(AND(O7>0,P7>0,C7<>E7),"Trade",IF(AND(NOT(Q7),Taostats_CSV!F7="fee"),'READ ME'!$C$5,""))) -> Income | J7: =SUBSTITUTE(IF(LEN(I7)=0,Taostats_CSV!F7&" "&Taostats_CSV!J7,IF(I7="Cost","Extrinsic fee","")),"_"," ") | K7: =TRIM(IF(LEN(Taostats_CSV!I7)>0,Taostats_CSV!I7,"")) | L7: =IF(Taostats_CSV!E7<>"TAO",IF(LEN(F7)>0,F7,IF(LEN(D7)>0,D7,0))*Taostats_CSV!P7,"") | M7: =IF(LEN(L7)>0,"USD","") | N7: =COUNTIF(Taostats_CSV!$X:$X,Taostats_CSV!$I7&N$1) -> 0 | O7: =COUNTIF(Taostats_CSV!$X:$X,Taostats_CSV!$I7&O$1) -> 0 | P7: =COUNTIF(Taostats_CSV!$X:$X,Taostats_CSV!$I7&P$1) -> 0 | Q7: =AND(O7<=1,N7<=1,P7<=1,O7+N7+P7>=2) -> FALSE | R7: =IF(LEN(K7)>0,COUNTIF($K$3:K7,K7),FALSE) -> FALSE | S7: =IF(Taostats_CSV!A7=Taostats_CSV!$A$2,TRUE,Taostats_CSV!G7+Taostats_CSV!H7+Taostats_CSV!R7=0) -> FALSE | T7: =AND(NOT(S7),OR(NOT(Q7),R7=1)) -> TRUE | U7: {=AND(T7,OR(O7-N7>1,P7>1,ISERROR(A7:P7)))} -> FALSE | W7: =MATCH(K7&$W$2,Taostats_CSV!$X$3:$X$1167,0) -> #N/A | X7: =VALUE(D7) -> #VALUE! | Y7: =VALUE(F7) -> 0.11111491 | Z7: =VALUE(H7) -> #VALUE! | AA7: SN4 | AB7: =SUMIF(Taostats_CSV!$E:$E,AA7,Taostats_CSV!G:G) -> 203.17828 | AC7: =SUMIF(Taostats_CSV!$E:$E,AA7,Taostats_CSV!H:H) -> 125.35234 | AD7: =SUMIF(Taostats_CSV!$E:$E,AA7,Taostats_CSV!R:R) -> 77.825938 | AE7: =SUMIFS($X:$X,$C:$C,$AA7,$T:$T,TRUE) -> 203.17828 | AF7: =SUMIFS($Y:$Y,$E:$E,$AA7,$T:$T,TRUE) -> 203.17828 | AG7: =SUMIFS($H:$H,$G:$G,$AA7,$T:$T,TRUE) -> 0 | AH7: =AE7+AG7-AB7 -> 0 | AI7: =AF7-AD7-AC7 -> 0
A8: =MID(Taostats_CSV!C8,6,2)&"/"&MID(Taostats_CSV!C8,9,2)&"/"&LEFT(Taostats_CSV!C8,4)&" "&MID(Taostats_CSV!C8,12,8) -> 01/05/2025 23:59:48 | C8: =IF(Q8,OFFSET(Taostats_CSV!$E$1,MATCH(K8&D$1,Taostats_CSV!$X:$X,0)-1,0),IF(Taostats_CSV!F8="fee",IF(VALUE(Taostats_CSV!G8)>0,Taostats_CSV!E8,""),"")) | D8: =IF(Q8,OFFSET(Taostats_CSV!$G$1,MATCH(K8&D$1,Taostats_CSV!$X:$X,0)-1,0),IF(Taostats_CSV!F8="fee",IF(VALUE(Taostats_CSV!G8)>0,Taostats_CSV!G8,""),"")) | E8: =IF(AND(Q8,P8>0),OFFSET(Taostats_CSV!$E$1,MATCH(K8&F$1,Taostats_CSV!$X:$X,0)-1,0),IF(LEN(F8)>0,Taostats_CSV!E8,"")) -> TAO | F8: =TRIM(IF(AND(Q8,P8>0),OFFSET(Taostats_CSV!$H$1,MATCH(K8&F$1,Taostats_CSV!$X:$X,0)-1,0),IF(LEN(Taostats_CSV!H8)>0,Taostats_CSV!H8,Taostats_CSV!R8))) -> 0.112642665 | G8: =IF(AND(Q8,N8=1),OFFSET(Taostats_CSV!$E$1,MATCH(K8&H$1,Taostats_CSV!$X:$X,0)-1,0),"") | H8: =IF(AND(Q8,N8=1),OFFSET(Taostats_CSV!$G$1,MATCH(K8&H$1,Taostats_CSV!$X:$X,0)-1,0),"") | I8: =IF(AND(LEN(K8)=0,LEN(F8)>0),"Income",IF(AND(O8>0,P8>0,C8<>E8),"Trade",IF(AND(NOT(Q8),Taostats_CSV!F8="fee"),'READ ME'!$C$5,""))) -> Income | J8: =SUBSTITUTE(IF(LEN(I8)=0,Taostats_CSV!F8&" "&Taostats_CSV!J8,IF(I8="Cost","Extrinsic fee","")),"_"," ") | K8: =TRIM(IF(LEN(Taostats_CSV!I8)>0,Taostats_CSV!I8,"")) | L8: =IF(Taostats_CSV!E8<>"TAO",IF(LEN(F8)>0,F8,IF(LEN(D8)>0,D8,0))*Taostats_CSV!P8,"") | M8: =IF(LEN(L8)>0,"USD","") | N8: =COUNTIF(Taostats_CSV!$X:$X,Taostats_CSV!$I8&N$1) -> 0 | O8: =COUNTIF(Taostats_CSV!$X:$X,Taostats_CSV!$I8&O$1) -> 0 | P8: =COUNTIF(Taostats_CSV!$X:$X,Taostats_CSV!$I8&P$1) -> 0 | Q8: =AND(O8<=1,N8<=1,P8<=1,O8+N8+P8>=2) -> FALSE | R8: =IF(LEN(K8)>0,COUNTIF($K$3:K8,K8),FALSE) -> FALSE | S8: =IF(Taostats_CSV!A8=Taostats_CSV!$A$2,TRUE,Taostats_CSV!G8+Taostats_CSV!H8+Taostats_CSV!R8=0) -> FALSE | T8: =AND(NOT(S8),OR(NOT(Q8),R8=1)) -> TRUE | U8: {=AND(T8,OR(O8-N8>1,P8>1,ISERROR(A8:P8)))} -> FALSE | W8: =MATCH(K8&$W$2,Taostats_CSV!$X$3:$X$1167,0) -> #N/A | X8: =VALUE(D8) -> #VALUE! | Y8: =VALUE(F8) -> 0.11264267 | Z8: =VALUE(H8) -> #VALUE! | AA8: SN56 | AB8: =SUMIF(Taostats_CSV!$E:$E,AA8,Taostats_CSV!G:G) -> 176.66136 | AC8: =SUMIF(Taostats_CSV!$E:$E,AA8,Taostats_CSV!H:H) -> 129.76133 | AD8: =SUMIF(Taostats_CSV!$E:$E,AA8,Taostats_CSV!R:R) -> 46.900029 | AE8: =SUMIFS($X:$X,$C:$C,$AA8,$T:$T,TRUE) -> 176.66136 | AF8: =SUMIFS($Y:$Y,$E:$E,$AA8,$T:$T,TRUE) -> 176.66136 | AG8: =SUMIFS($H:$H,$G:$G,$AA8,$T:$T,TRUE) -> 0 | AH8: =AE8+AG8-AB8 -> 0 | AI8: =AF8-AD8-AC8 -> 0
A9: =MID(Taostats_CSV!C9,6,2)&"/"&MID(Taostats_CSV!C9,9,2)&"/"&LEFT(Taostats_CSV!C9,4)&" "&MID(Taostats_CSV!C9,12,8) -> 01/06/2025 23:59:48 | C9: =IF(Q9,OFFSET(Taostats_CSV!$E$1,MATCH(K9&D$1,Taostats_CSV!$X:$X,0)-1,0),IF(Taostats_CSV!F9="fee",IF(VALUE(Taostats_CSV!G9)>0,Taostats_CSV!E9,""),"")) | D9: =IF(Q9,OFFSET(Taostats_CSV!$G$1,MATCH(K9&D$1,Taostats_CSV!$X:$X,0)-1,0),IF(Taostats_CSV!F9="fee",IF(VALUE(Taostats_CSV!G9)>0,Taostats_CSV!G9,""),"")) | E9: =IF(AND(Q9,P9>0),OFFSET(Taostats_CSV!$E$1,MATCH(K9&F$1,Taostats_CSV!$X:$X,0)-1,0),IF(LEN(F9)>0,Taostats_CSV!E9,"")) -> TAO | F9: =TRIM(IF(AND(Q9,P9>0),OFFSET(Taostats_CSV!$H$1,MATCH(K9&F$1,Taostats_CSV!$X:$X,0)-1,0),IF(LEN(Taostats_CSV!H9)>0,Taostats_CSV!H9,Taostats_CSV!R9))) -> 0.116219871 | G9: =IF(AND(Q9,N9=1),OFFSET(Taostats_CSV!$E$1,MATCH(K9&H$1,Taostats_CSV!$X:$X,0)-1,0),"") | H9: =IF(AND(Q9,N9=1),OFFSET(Taostats_CSV!$G$1,MATCH(K9&H$1,Taostats_CSV!$X:$X,0)-1,0),"") | I9: =IF(AND(LEN(K9)=0,LEN(F9)>0),"Income",IF(AND(O9>0,P9>0,C9<>E9),"Trade",IF(AND(NOT(Q9),Taostats_CSV!F9="fee"),'READ ME'!$C$5,""))) -> Income | J9: =SUBSTITUTE(IF(LEN(I9)=0,Taostats_CSV!F9&" "&Taostats_CSV!J9,IF(I9="Cost","Extrinsic fee","")),"_"," ") | K9: =TRIM(IF(LEN(Taostats_CSV!I9)>0,Taostats_CSV!I9,"")) | L9: =IF(Taostats_CSV!E9<>"TAO",IF(LEN(F9)>0,F9,IF(LEN(D9)>0,D9,0))*Taostats_CSV!P9,"") | M9: =IF(LEN(L9)>0,"USD","") | N9: =COUNTIF(Taostats_CSV!$X:$X,Taostats_CSV!$I9&N$1) -> 0 | O9: =COUNTIF(Taostats_CSV!$X:$X,Taostats_CSV!$I9&O$1) -> 0 | P9: =COUNTIF(Taostats_CSV!$X:$X,Taostats_CSV!$I9&P$1) -> 0 | Q9: =AND(O9<=1,N9<=1,P9<=1,O9+N9+P9>=2) -> FALSE | R9: =IF(LEN(K9)>0,COUNTIF($K$3:K9,K9),FALSE) -> FALSE | S9: =IF(Taostats_CSV!A9=Taostats_CSV!$A$2,TRUE,Taostats_CSV!G9+Taostats_CSV!H9+Taostats_CSV!R9=0) -> FALSE | T9: =AND(NOT(S9),OR(NOT(Q9),R9=1)) -> TRUE | U9: {=AND(T9,OR(O9-N9>1,P9>1,ISERROR(A9:P9)))} -> FALSE | W9: =MATCH(K9&$W$2,Taostats_CSV!$X$3:$X$1167,0) -> #N/A | X9: =VALUE(D9) -> #VALUE! | Y9: =VALUE(F9) -> 0.11621987 | Z9: =VALUE(H9) -> #VALUE! | AA9: SN64 | AB9: =SUMIF(Taostats_CSV!$E:$E,AA9,Taostats_CSV!G:G) -> 92.510727 | AC9: =SUMIF(Taostats_CSV!$E:$E,AA9,Taostats_CSV!H:H) -> 66.346213 | AD9: =SUMIF(Taostats_CSV!$E:$E,AA9,Taostats_CSV!R:R) -> 26.164514 | AE9: =SUMIFS($X:$X,$C:$C,$AA9,$T:$T,TRUE) -> 92.510727 | AF9: =SUMIFS($Y:$Y,$E:$E,$AA9,$T:$T,TRUE) -> 92.510727 | AG9: =SUMIFS($H:$H,$G:$G,$AA9,$T:$T,TRUE) -> 0 | AH9: =AE9+AG9-AB9 -> 0 | AI9: =AF9-AD9-AC9 -> 0
A10: =MID(Taostats_CSV!C10,6,2)&"/"&MID(Taostats_CSV!C10,9,2)&"/"&LEFT(Taostats_CSV!C10,4)&" "&MID(Taostats_CSV!C10,12,8) -> 01/07/2025 23:59:48 | C10: =IF(Q10,OFFSET(Taostats_CSV!$E$1,MATCH(K10&D$1,Taostats_CSV!$X:$X,0)-1,0),IF(Taostats_CSV!F10="fee",IF(VALUE(Taostats_CSV!G10)>0,Taostats_CSV!E10,""),"")) | D10: =IF(Q10,OFFSET(Taostats_CSV!$G$1,MATCH(K10&D$1,Taostats_CSV!$X:$X,0)-1,0),IF(Taostats_CSV!F10="fee",IF(VALUE(Taostats_CSV!G10)>0,Taostats_CSV!G10,""),"")) | E10: =IF(AND(Q10,P10>0),OFFSET(Taostats_CSV!$E$1,MATCH(K10&F$1,Taostats_CSV!$X:$X,0)-1,0),IF(LEN(F10)>0,Taostats_CSV!E10,"")) -> TAO | F10: =TRIM(IF(AND(Q10,P10>0),OFFSET(Taostats_CSV!$H$1,MATCH(K10&F$1,Taostats_CSV!$X:$X,0)-1,0),IF(LEN(Taostats_CSV!H10)>0,Taostats_CSV!H10,Taostats_CSV!R10))) -> 0.117338691 | G10: =IF(AND(Q10,N10=1),OFFSET(Taostats_CSV!$E$1,MATCH(K10&H$1,Taostats_CSV!$X:$X,0)-1,0),"") | H10: =IF(AND(Q10,N10=1),OFFSET(Taostats_CSV!$G$1,MATCH(K10&H$1,Taostats_CSV!$X:$X,0)-1,0),"") | I10: =IF(AND(LEN(K10)=0,LEN(F10)>0),"Income",IF(AND(O10>0,P10>0,C10<>E10),"Trade",IF(AND(NOT(Q10),Taostats_CSV!F10="fee"),'READ ME'!$C$5,""))) -> Income | J10: =SUBSTITUTE(IF(LEN(I10)=0,Taostats_CSV!F10&" "&Taostats_CSV!J10,IF(I10="Cost","Extrinsic fee","")),"_"," ") | K10: =TRIM(IF(LEN(Taostats_CSV!I10)>0,Taostats_CSV!I10,"")) | L10: =IF(Taostats_CSV!E10<>"TAO",IF(LEN(F10)>0,F10,IF(LEN(D10)>0,D10,0))*Taostats_CSV!P10,"") | M10: =IF(LEN(L10)>0,"USD","") | N10: =COUNTIF(Taostats_CSV!$X:$X,Taostats_CSV!$I10&N$1) -> 0 | O10: =COUNTIF(Taostats_CSV!$X:$X,Taostats_CSV!$I10&O$1) -> 0 | P10: =COUNTIF(Taostats_CSV!$X:$X,Taostats_CSV!$I10&P$1) -> 0 | Q10: =AND(O10<=1,N10<=1,P10<=1,O10+N10+P10>=2) -> FALSE | R10: =IF(LEN(K10)>0,COUNTIF($K$3:K10,K10),FALSE) -> FALSE | S10: =IF(Taostats_CSV!A10=Taostats_CSV!$A$2,TRUE,Taostats_CSV!G10+Taostats_CSV!H10+Taostats_CSV!R10=0) -> FALSE | T10: =AND(NOT(S10),OR(NOT(Q10),R10=1)) -> TRUE | U10: {=AND(T10,OR(O10-N10>1,P10>1,ISERROR(A10:P10)))} -> FALSE | W10: =MATCH(K10&$W$2,Taostats_CSV!$X$3:$X$1167,0) -> #N/A | X10: =VALUE(D10) -> #VALUE! | Y10: =VALUE(F10) -> 0.11733869 | Z10: =VALUE(H10) -> #VALUE! | AA10: 0 | AB10: =SUMIF(Taostats_CSV!$E:$E,AA10,Taostats_CSV!G:G) -> 0 | AC10: =SUMIF(Taostats_CSV!$E:$E,AA10,Taostats_CSV!H:H) -> 0 | AD10: =SUMIF(Taostats_CSV!$E:$E,AA10,Taostats_CSV!R:R) -> 0 | AE10: =SUMIFS($X:$X,$C:$C,$AA10,$T:$T,TRUE) -> 0 | AF10: =SUMIFS($Y:$Y,$E:$E,$AA10,$T:$T,TRUE) -> 0 | AG10: =SUMIFS($H:$H,$G:$G,$AA10,$T:$T,TRUE) -> 0 | AH10: =AE10+AG10-AB10 -> 0 | AI10: =AF10-AD10-AC10 -> 0
A11: =MID(Taostats_CSV!C11,6,2)&"/"&MID(Taostats_CSV!C11,9,2)&"/"&LEFT(Taostats_CSV!C11,4)&" "&MID(Taostats_CSV!C11,12,8) -> 01/08/2025 23:59:48 | C11: =IF(Q11,OFFSET(Taostats_CSV!$E$1,MATCH(K11&D$1,Taostats_CSV!$X:$X,0)-1,0),IF(Taostats_CSV!F11="fee",IF(VALUE(Taostats_CSV!G11)>0,Taostats_CSV!E11,""),"")) | D11: =IF(Q11,OFFSET(Taostats_CSV!$G$1,MATCH(K11&D$1,Taostats_CSV!$X:$X,0)-1,0),IF(Taostats_CSV!F11="fee",IF(VALUE(Taostats_CSV!G11)>0,Taostats_CSV!G11,""),"")) | E11: =IF(AND(Q11,P11>0),OFFSET(Taostats_CSV!$E$1,MATCH(K11&F$1,Taostats_CSV!$X:$X,0)-1,0),IF(LEN(F11)>0,Taostats_CSV!E11,"")) -> TAO | F11: =TRIM(IF(AND(Q11,P11>0),OFFSET(Taostats_CSV!$H$1,MATCH(K11&F$1,Taostats_CSV!$X:$X,0)-1,0),IF(LEN(Taostats_CSV!H11)>0,Taostats_CSV!H11,Taostats_CSV!R11))) -> 0.11603302 | G11: =IF(AND(Q11,N11=1),OFFSET(Taostats_CSV!$E$1,MATCH(K11&H$1,Taostats_CSV!$X:$X,0)-1,0),"") | H11: =IF(AND(Q11,N11=1),OFFSET(Taostats_CSV!$G$1,MATCH(K11&H$1,Taostats_CSV!$X:$X,0)-1,0),"") | I11: =IF(AND(LEN(K11)=0,LEN(F11)>0),"Income",IF(AND(O11>0,P11>0,C11<>E11),"Trade",IF(AND(NOT(Q11),Taostats_CSV!F11="fee"),'READ ME'!$C$5,""))) -> Income | J11: =SUBSTITUTE(IF(LEN(I11)=0,Taostats_CSV!F11&" "&Taostats_CSV!J11,IF(I11="Cost","Extrinsic fee","")),"_"," ") | K11: =TRIM(IF(LEN(Taostats_CSV!I11)>0,Taostats_CSV!I11,"")) | L11: =IF(Taostats_CSV!E11<>"TAO",IF(LEN(F11)>0,F11,IF(LEN(D11)>0,D11,0))*Taostats_CSV!P11,"") | M11: =IF(LEN(L11)>0,"USD","") | N11: =COUNTIF(Taostats_CSV!$X:$X,Taostats_CSV!$I11&N$1) -> 0 | O11: =COUNTIF(Taostats_CSV!$X:$X,Taostats_CSV!$I11&O$1) -> 0 | P11: =COUNTIF(Taostats_CSV!$X:$X,Taostats_CSV!$I11&P$1) -> 0 | Q11: =AND(O11<=1,N11<=1,P11<=1,O11+N11+P11>=2) -> FALSE | R11: =IF(LEN(K11)>0,COUNTIF($K$3:K11,K11),FALSE) -> FALSE | S11: =IF(Taostats_CSV!A11=Taostats_CSV!$A$2,TRUE,Taostats_CSV!G11+Taostats_CSV!H11+Taostats_CSV!R11=0) -> FALSE | T11: =AND(NOT(S11),OR(NOT(Q11),R11=1)) -> TRUE | U11: {=AND(T11,OR(O11-N11>1,P11>1,ISERROR(A11:P11)))} -> FALSE | W11: =MATCH(K11&$W$2,Taostats_CSV!$X$3:$X$1167,0) -> #N/A | X11: =VALUE(D11) -> #VALUE! | Y11: =VALUE(F11) -> 0.11603302 | Z11: =VALUE(H11) -> #VALUE! | AB11: =SUMIF(Taostats_CSV!$E:$E,AA11,Taostats_CSV!G:G) -> 0 | AC11: =SUMIF(Taostats_CSV!$E:$E,AA11,Taostats_CSV!H:H) -> 0 | AD11: =SUMIF(Taostats_CSV!$E:$E,AA11,Taostats_CSV!R:R) -> 0 | AE11: =SUMIFS($X:$X,$C:$C,$AA11,$T:$T,TRUE) -> 0 | AF11: =SUMIFS($Y:$Y,$E:$E,$AA11,$T:$T,TRUE) -> 0 | AG11: =SUMIFS($H:$H,$G:$G,$AA11,$T:$T,TRUE) -> 0 | AH11: =AE11+AG11-AB11 -> 0 | AI11: =AF11-AD11-AC11 -> 0
A12: =MID(Taostats_CSV!C12,6,2)&"/"&MID(Taostats_CSV!C12,9,2)&"/"&LEFT(Taostats_CSV!C12,4)&" "&MID(Taostats_CSV!C12,12,8) -> 01/09/2025 23:59:48 | C12: =IF(Q12,OFFSET(Taostats_CSV!$E$1,MATCH(K12&D$1,Taostats_CSV!$X:$X,0)-1,0),IF(Taostats_CSV!F12="fee",IF(VALUE(Taostats_CSV!G12)>0,Taostats_CSV!E12,""),"")) | D12: =IF(Q12,OFFSET(Taostats_CSV!$G$1,MATCH(K12&D$1,Taostats_CSV!$X:$X,0)-1,0),IF(Taostats_CSV!F12="fee",IF(VALUE(Taostats_CSV!G12)>0,Taostats_CSV!G12,""),"")) | E12: =IF(AND(Q12,P12>0),OFFSET(Taostats_CSV!$E$1,MATCH(K12&F$1,Taostats_CSV!$X:$X,0)-1,0),IF(LEN(F12)>0,Taostats_CSV!E12,"")) -> TAO | F12: =TRIM(IF(AND(Q12,P12>0),OFFSET(Taostats_CSV!$H$1,MATCH(K12&F$1,Taostats_CSV!$X:$X,0)-1,0),IF(LEN(Taostats_CSV!H12)>0,Taostats_CSV!H12,Taostats_CSV!R12))) -> 0.110048595 | G12: =IF(AND(Q12,N12=1),OFFSET(Taostats_CSV!$E$1,MATCH(K12&H$1,Taostats_CSV!$X:$X,0)-1,0),"") | H12: =IF(AND(Q12,N12=1),OFFSET(Taostats_CSV!$G$1,MATCH(K12&H$1,Taostats_CSV!$X:$X,0)-1,0),"") | I12: =IF(AND(LEN(K12)=0,LEN(F12)>0),"Income",IF(AND(O12>0,P12>0,C12<>E12),"Trade",IF(AND(NOT(Q12),Taostats_CSV!F12="fee"),'READ ME'!$C$5,""))) -> Income | J12: =SUBSTITUTE(IF(LEN(I12)=0,Taostats_CSV!F12&" "&Taostats_CSV!J12,IF(I12="Cost","Extrinsic fee","")),"_"," ") | K12: =TRIM(IF(LEN(Taostats_CSV!I12)>0,Taostats_CSV!I12,"")) | L12: =IF(Taostats_CSV!E12<>"TAO",IF(LEN(F12)>0,F12,IF(LEN(D12)>0,D12,0))*Taostats_CSV!P12,"") | M12: =IF(LEN(L12)>0,"USD","") | N12: =COUNTIF(Taostats_CSV!$X:$X,Taostats_CSV!$I12&N$1) -> 0 | O12: =COUNTIF(Taostats_CSV!$X:$X,Taostats_CSV!$I12&O$1) -> 0 | P12: =COUNTIF(Taostats_CSV!$X:$X,Taostats_CSV!$I12&P$1) -> 0 | Q12: =AND(O12<=1,N12<=1,P12<=1,O12+N12+P12>=2) -> FALSE | R12: =IF(LEN(K12)>0,COUNTIF($K$3:K12,K12),FALSE) -> FALSE | S12: =IF(Taostats_CSV!A12=Taostats_CSV!$A$2,TRUE,Taostats_CSV!G12+Taostats_CSV!H12+Taostats_CSV!R12=0) -> FALSE | T12: =AND(NOT(S12),OR(NOT(Q12),R12=1)) -> TRUE | U12: {=AND(T12,OR(O12-N12>1,P12>1,ISERROR(A12:P12)))} -> FALSE | W12: =MATCH(K12&$W$2,Taostats_CSV!$X$3:$X$1167,0) -> #N/A | X12: =VALUE(D12) -> #VALUE! | Y12: =VALUE(F12) -> 0.11004859 | Z12: =VALUE(H12) -> #VALUE! | AB12: =SUMIF(Taostats_CSV!$E:$E,AA12,Taostats_CSV!G:G) -> 0 | AC12: =SUMIF(Taostats_CSV!$E:$E,AA12,Taostats_CSV!H:H) -> 0 | AD12: =SUMIF(Taostats_CSV!$E:$E,AA12,Taostats_CSV!R:R) -> 0 | AE12: =SUMIFS($X:$X,$C:$C,$AA12,$T:$T,TRUE) -> 0 | AF12: =SUMIFS($Y:$Y,$E:$E,$AA12,$T:$T,TRUE) -> 0 | AG12: =SUMIFS($H:$H,$G:$G,$AA12,$T:$T,TRUE) -> 0 | AH12: =AE12+AG12-AB12 -> 0 | AI12: =AF12-AD12-AC12 -> 0
A13: =MID(Taostats_CSV!C13,6,2)&"/"&MID(Taostats_CSV!C13,9,2)&"/"&LEFT(Taostats_CSV!C13,4)&" "&MID(Taostats_CSV!C13,12,8) -> 01/10/2025 23:59:48 | C13: =IF(Q13,OFFSET(Taostats_CSV!$E$1,MATCH(K13&D$1,Taostats_CSV!$X:$X,0)-1,0),IF(Taostats_CSV!F13="fee",IF(VALUE(Taostats_CSV!G13)>0,Taostats_CSV!E13,""),"")) | D13: =IF(Q13,OFFSET(Taostats_CSV!$G$1,MATCH(K13&D$1,Taostats_CSV!$X:$X,0)-1,0),IF(Taostats_CSV!F13="fee",IF(VALUE(Taostats_CSV!G13)>0,Taostats_CSV!G13,""),"")) | E13: =IF(AND(Q13,P13>0),OFFSET(Taostats_CSV!$E$1,MATCH(K13&F$1,Taostats_CSV!$X:$X,0)-1,0),IF(LEN(F13)>0,Taostats_CSV!E13,"")) -> TAO | F13: =TRIM(IF(AND(Q13,P13>0),OFFSET(Taostats_CSV!$H$1,MATCH(K13&F$1,Taostats_CSV!$X:$X,0)-1,0),IF(LEN(Taostats_CSV!H13)>0,Taostats_CSV!H13,Taostats_CSV!R13))) -> 0.110197807 | G13: =IF(AND(Q13,N13=1),OFFSET(Taostats_CSV!$E$1,MATCH(K13&H$1,Taostats_CSV!$X:$X,0)-1,0),"") | H13: =IF(AND(Q13,N13=1),OFFSET(Taostats_CSV!$G$1,MATCH(K13&H$1,Taostats_CSV!$X:$X,0)-1,0),"") | I13: =IF(AND(LEN(K13)=0,LEN(F13)>0),"Income",IF(AND(O13>0,P13>0,C13<>E13),"Trade",IF(AND(NOT(Q13),Taostats_CSV!F13="fee"),'READ ME'!$C$5,""))) -> Income | J13: =SUBSTITUTE(IF(LEN(I13)=0,Taostats_CSV!F13&" "&Taostats_CSV!J13,IF(I13="Cost","Extrinsic fee","")),"_"," ") | K13: =TRIM(IF(LEN(Taostats_CSV!I13)>0,Taostats_CSV!I13,"")) | L13: =IF(Taostats_CSV!E13<>"TAO",IF(LEN(F13)>0,F13,IF(LEN(D13)>0,D13,0))*Taostats_CSV!P13,"") | M13: =IF(LEN(L13)>0,"USD","") | N13: =COUNTIF(Taostats_CSV!$X:$X,Taostats_CSV!$I13&N$1) -> 0 | O13: =COUNTIF(Taostats_CSV!$X:$X,Taostats_CSV!$I13&O$1) -> 0 | P13: =COUNTIF(Taostats_CSV!$X:$X,Taostats_CSV!$I13&P$1) -> 0 | Q13: =AND(O13<=1,N13<=1,P13<=1,O13+N13+P13>=2) -> FALSE | R13: =IF(LEN(K13)>0,COUNTIF($K$3:K13,K13),FALSE) -> FALSE | S13: =IF(Taostats_CSV!A13=Taostats_CSV!$A$2,TRUE,Taostats_CSV!G13+Taostats_CSV!H13+Taostats_CSV!R13=0) -> FALSE | T13: =AND(NOT(S13),OR(NOT(Q13),R13=1)) -> TRUE | U13: {=AND(T13,OR(O13-N13>1,P13>1,ISERROR(A13:P13)))} -> FALSE | W13: =MATCH(K13&$W$2,Taostats_CSV!$X$3:$X$1167,0) -> #N/A | X13: =VALUE(D13) -> #VALUE! | Y13: =VALUE(F13) -> 0.11019781 | Z13: =VALUE(H13) -> #VALUE! | AB13: =SUMIF(Taostats_CSV!$E:$E,AA13,Taostats_CSV!G:G) -> 0 | AC13: =SUMIF(Taostats_CSV!$E:$E,AA13,Taostats_CSV!H:H) -> 0 | AD13: =SUMIF(Taostats_CSV!$E:$E,AA13,Taostats_CSV!R:R) -> 0 | AE13: =SUMIFS($X:$X,$C:$C,$AA13,$T:$T,TRUE) -> 0 | AF13: =SUMIFS($Y:$Y,$E:$E,$AA13,$T:$T,TRUE) -> 0 | AG13: =SUMIFS($H:$H,$G:$G,$AA13,$T:$T,TRUE) -> 0 | AH13: =AE13+AG13-AB13 -> 0 | AI13: =AF13-AD13-AC13 -> 0
A14: =MID(Taostats_CSV!C14,6,2)&"/"&MID(Taostats_CSV!C14,9,2)&"/"&LEFT(Taostats_CSV!C14,4)&" "&MID(Taostats_CSV!C14,12,8) -> 01/11/2025 23:59:48 | C14: =IF(Q14,OFFSET(Taostats_CSV!$E$1,MATCH(K14&D$1,Taostats_CSV!$X:$X,0)-1,0),IF(Taostats_CSV!F14="fee",IF(VALUE(Taostats_CSV!G14)>0,Taostats_CSV!E14,""),"")) | D14: =IF(Q14,OFFSET(Taostats_CSV!$G$1,MATCH(K14&D$1,Taostats_CSV!$X:$X,0)-1,0),IF(Taostats_CSV!F14="fee",IF(VALUE(Taostats_CSV!G14)>0,Taostats_CSV!G14,""),"")) | E14: =IF(AND(Q14,P14>0),OFFSET(Taostats_CSV!$E$1,MATCH(K14&F$1,Taostats_CSV!$X:$X,0)-1,0),IF(LEN(F14)>0,Taostats_CSV!E14,"")) -> TAO | F14: =TRIM(IF(AND(Q14,P14>0),OFFSET(Taostats_CSV!$H$1,MATCH(K14&F$1,Taostats_CSV!$X:$X,0)-1,0),IF(LEN(Taostats_CSV!H14)>0,Taostats_CSV!H14,Taostats_CSV!R14))) -> 0.112062363 | G14: =IF(AND(Q14,N14=1),OFFSET(Taostats_CSV!$E$1,MATCH(K14&H$1,Taostats_CSV!$X:$X,0)-1,0),"") | H14: =IF(AND(Q14,N14=1),OFFSET(Taostats_CSV!$G$1,MATCH(K14&H$1,Taostats_CSV!$X:$X,0)-1,0),"") | I14: =IF(AND(LEN(K14)=0,LEN(F14)>0),"Income",IF(AND(O14>0,P14>0,C14<>E14),"Trade",IF(AND(NOT(Q14),Taostats_CSV!F14="fee"),'READ ME'!$C$5,""))) -> Income | J14: =SUBSTITUTE(IF(LEN(I14)=0,Taostats_CSV!F14&" "&Taostats_CSV!J14,IF(I14="Cost","Extrinsic fee","")),"_"," ") | K14: =TRIM(IF(LEN(Taostats_CSV!I14)>0,Taostats_CSV!I14,"")) | L14: =IF(Taostats_CSV!E14<>"TAO",IF(LEN(F14)>0,F14,IF(LEN(D14)>0,D14,0))*Taostats_CSV!P14,"") | M14: =IF(LEN(L14)>0,"USD","") | N14: =COUNTIF(Taostats_CSV!$X:$X,Taostats_CSV!$I14&N$1) -> 0 | O14: =COUNTIF(Taostats_CSV!$X:$X,Taostats_CSV!$I14&O$1) -> 0 | P14: =COUNTIF(Taostats_CSV!$X:$X,Taostats_CSV!$I14&P$1) -> 0 | Q14: =AND(O14<=1,N14<=1,P14<=1,O14+N14+P14>=2) -> FALSE | R14: =IF(LEN(K14)>0,COUNTIF($K$3:K14,K14),FALSE) -> FALSE | S14: =IF(Taostats_CSV!A14=Taostats_CSV!$A$2,TRUE,Taostats_CSV!G14+Taostats_CSV!H14+Taostats_CSV!R14=0) -> FALSE | T14: =AND(NOT(S14),OR(NOT(Q14),R14=1)) -> TRUE | U14: {=AND(T14,OR(O14-N14>1,P14>1,ISERROR(A14:P14)))} -> FALSE | W14: =MATCH(K14&$W$2,Taostats_CSV!$X$3:$X$1167,0) -> #N/A | X14: =VALUE(D14) -> #VALUE! | Y14: =VALUE(F14) -> 0.11206236 | Z14: =VALUE(H14) -> #VALUE! | AB14: =SUMIF(Taostats_CSV!$E:$E,AA14,Taostats_CSV!G:G) -> 0 | AC14: =SUMIF(Taostats_CSV!$E:$E,AA14,Taostats_CSV!H:H) -> 0 | AD14: =SUMIF(Taostats_CSV!$E:$E,AA14,Taostats_CSV!R:R) -> 0 | AE14: =SUMIFS($X:$X,$C:$C,$AA14,$T:$T,TRUE) -> 0 | AF14: =SUMIFS($Y:$Y,$E:$E,$AA14,$T:$T,TRUE) -> 0 | AG14: =SUMIFS($H:$H,$G:$G,$AA14,$T:$T,TRUE) -> 0 | AH14: =AE14+AG14-AB14 -> 0 | AI14: =AF14-AD14-AC14 -> 0
A15: =MID(Taostats_CSV!C15,6,2)&"/"&MID(Taostats_CSV!C15,9,2)&"/"&LEFT(Taostats_CSV!C15,4)&" "&MID(Taostats_CSV!C15,12,8) -> 01/12/2025 23:59:48 | C15: =IF(Q15,OFFSET(Taostats_CSV!$E$1,MATCH(K15&D$1,Taostats_CSV!$X:$X,0)-1,0),IF(Taostats_CSV!F15="fee",IF(VALUE(Taostats_CSV!G15)>0,Taostats_CSV!E15,""),"")) | D15: =IF(Q15,OFFSET(Taostats_CSV!$G$1,MATCH(K15&D$1,Taostats_CSV!$X:$X,0)-1,0),IF(Taostats_CSV!F15="fee",IF(VALUE(Taostats_CSV!G15)>0,Taostats_CSV!G15,""),"")) | E15: =IF(AND(Q15,P15>0),OFFSET(Taostats_CSV!$E$1,MATCH(K15&F$1,Taostats_CSV!$X:$X,0)-1,0),IF(LEN(F15)>0,Taostats_CSV!E15,"")) -> TAO | F15: =TRIM(IF(AND(Q15,P15>0),OFFSET(Taostats_CSV!$H$1,MATCH(K15&F$1,Taostats_CSV!$X:$X,0)-1,0),IF(LEN(Taostats_CSV!H15)>0,Taostats_CSV!H15,Taostats_CSV!R15))) -> 0.111740714 | G15: =IF(AND(Q15,N15=1),OFFSET(Taostats_CSV!$E$1,MATCH(K15&H$1,Taostats_CSV!$X:$X,0)-1,0),"") | H15: =IF(AND(Q15,N15=1),OFFSET(Taostats_CSV!$G$1,MATCH(K15&H$1,Taostats_CSV!$X:$X,0)-1,0),"") | I15: =IF(AND(LEN(K15)=0,LEN(F15)>0),"Income",IF(AND(O15>0,P15>0,C15<>E15),"Trade",IF(AND(NOT(Q15),Taostats_CSV!F15="fee"),'READ ME'!$C$5,""))) -> Income | J15: =SUBSTITUTE(IF(LEN(I15)=0,Taostats_CSV!F15&" "&Taostats_CSV!J15,IF(I15="Cost","Extrinsic fee","")),"_"," ") | K15: =TRIM(IF(LEN(Taostats_CSV!I15)>0,Taostats_CSV!I15,"")) | L15: =IF(Taostats_CSV!E15<>"TAO",IF(LEN(F15)>0,F15,IF(LEN(D15)>0,D15,0))*Taostats_CSV!P15,"") | M15: =IF(LEN(L15)>0,"USD","") | N15: =COUNTIF(Taostats_CSV!$X:$X,Taostats_CSV!$I15&N$1) -> 0 | O15: =COUNTIF(Taostats_CSV!$X:$X,Taostats_CSV!$I15&O$1) -> 0 | P15: =COUNTIF(Taostats_CSV!$X:$X,Taostats_CSV!$I15&P$1) -> 0 | Q15: =AND(O15<=1,N15<=1,P15<=1,O15+N15+P15>=2) -> FALSE | R15: =IF(LEN(K15)>0,COUNTIF($K$3:K15,K15),FALSE) -> FALSE | S15: =IF(Taostats_CSV!A15=Taostats_CSV!$A$2,TRUE,Taostats_CSV!G15+Taostats_CSV!H15+Taostats_CSV!R15=0) -> FALSE | T15: =AND(NOT(S15),OR(NOT(Q15),R15=1)) -> TRUE | U15: {=AND(T15,OR(O15-N15>1,P15>1,ISERROR(A15:P15)))} -> FALSE | W15: =MATCH(K15&$W$2,Taostats_CSV!$X$3:$X$1167,0) -> #N/A | X15: =VALUE(D15) -> #VALUE! | Y15: =VALUE(F15) -> 0.11174071 | Z15: =VALUE(H15) -> #VALUE! | AB15: =SUMIF(Taostats_CSV!$E:$E,AA15,Taostats_CSV!G:G) -> 0 | AC15: =SUMIF(Taostats_CSV!$E:$E,AA15,Taostats_CSV!H:H) -> 0 | AD15: =SUMIF(Taostats_CSV!$E:$E,AA15,Taostats_CSV!R:R) -> 0 | AE15: =SUMIFS($X:$X,$C:$C,$AA15,$T:$T,TRUE) -> 0 | AF15: =SUMIFS($Y:$Y,$E:$E,$AA15,$T:$T,TRUE) -> 0 | AG15: =SUMIFS($H:$H,$G:$G,$AA15,$T:$T,TRUE) -> 0 | AH15: =AE15+AG15-AB15 -> 0 | AI15: =AF15-AD15-AC15 -> 0
A16: =MID(Taostats_CSV!C16,6,2)&"/"&MID(Taostats_CSV!C16,9,2)&"/"&LEFT(Taostats_CSV!C16,4)&" "&MID(Taostats_CSV!C16,12,8) -> 01/13/2025 23:59:48 | C16: =IF(Q16,OFFSET(Taostats_CSV!$E$1,MATCH(K16&D$1,Taostats_CSV!$X:$X,0)-1,0),IF(Taostats_CSV!F16="fee",IF(VALUE(Taostats_CSV!G16)>0,Taostats_CSV!E16,""),"")) | D16: =IF(Q16,OFFSET(Taostats_CSV!$G$1,MATCH(K16&D$1,Taostats_CSV!$X:$X,0)-1,0),IF(Taostats_CSV!F16="fee",IF(VALUE(Taostats_CSV!G16)>0,Taostats_CSV!G16,""),"")) | E16: =IF(AND(Q16,P16>0),OFFSET(Taostats_CSV!$E$1,MATCH(K16&F$1,Taostats_CSV!$X:$X,0)-1,0),IF(LEN(F16)>0,Taostats_CSV!E16,"")) -> TAO | F16: =TRIM(IF(AND(Q16,P16>0),OFFSET(Taostats_CSV!$H$1,MATCH(K16&F$1,Taostats_CSV!$X:$X,0)-1,0),IF(LEN(Taostats_CSV!H16)>0,Taostats_CSV!H16,Taostats_CSV!R16))) -> 0.110391721 | G16: =IF(AND(Q16,N16=1),OFFSET(Taostats_CSV!$E$1,MATCH(K16&H$1,Taostats_CSV!$X:$X,0)-1,0),"") | H16: =IF(AND(Q16,N16=1),OFFSET(Taostats_CSV!$G$1,MATCH(K16&H$1,Taostats_CSV!$X:$X,0)-1,0),"") | I16: =IF(AND(LEN(K16)=0,LEN(F16)>0),"Income",IF(AND(O16>0,P16>0,C16<>E16),"Trade",IF(AND(NOT(Q16),Taostats_CSV!F16="fee"),'READ ME'!$C$5,""))) -> Income | J16: =SUBSTITUTE(IF(LEN(I16)=0,Taostats_CSV!F16&" "&Taostats_CSV!J16,IF(I16="Cost","Extrinsic fee","")),"_"," ") | K16: =TRIM(IF(LEN(Taostats_CSV!I16)>0,Taostats_CSV!I16,"")) | L16: =IF(Taostats_CSV!E16<>"TAO",IF(LEN(F16)>0,F16,IF(LEN(D16)>0,D16,0))*Taostats_CSV!P16,"") | M16: =IF(LEN(L16)>0,"USD","") | N16: =COUNTIF(Taostats_CSV!$X:$X,Taostats_CSV!$I16&N$1) -> 0 | O16: =COUNTIF(Taostats_CSV!$X:$X,Taostats_CSV!$I16&O$1) -> 0 | P16: =COUNTIF(Taostats_CSV!$X:$X,Taostats_CSV!$I16&P$1) -> 0 | Q16: =AND(O16<=1,N16<=1,P16<=1,O16+N16+P16>=2) -> FALSE | R16: =IF(LEN(K16)>0,COUNTIF($K$3:K16,K16),FALSE) -> FALSE | S16: =IF(Taostats_CSV!A16=Taostats_CSV!$A$2,TRUE,Taostats_CSV!G16+Taostats_CSV!H16+Taostats_CSV!R16=0) -> FALSE | T16: =AND(NOT(S16),OR(NOT(Q16),R16=1)) -> TRUE | U16: {=AND(T16,OR(O16-N16>1,P16>1,ISERROR(A16:P16)))} -> FALSE | W16: =MATCH(K16&$W$2,Taostats_CSV!$X$3:$X$1167,0) -> #N/A | X16: =VALUE(D16) -> #VALUE! | Y16: =VALUE(F16) -> 0.11039172 | Z16: =VALUE(H16) -> #VALUE! | AB16: =SUMIF(Taostats_CSV!$E:$E,AA16,Taostats_CSV!G:G) -> 0 | AC16: =SUMIF(Taostats_CSV!$E:$E,AA16,Taostats_CSV!H:H) -> 0 | AD16: =SUMIF(Taostats_CSV!$E:$E,AA16,Taostats_CSV!R:R) -> 0 | AE16: =SUMIFS($X:$X,$C:$C,$AA16,$T:$T,TRUE) -> 0 | AF16: =SUMIFS($Y:$Y,$E:$E,$AA16,$T:$T,TRUE) -> 0 | AG16: =SUMIFS($H:$H,$G:$G,$AA16,$T:$T,TRUE) -> 0 | AH16: =AE16+AG16-AB16 -> 0 | AI16: =AF16-AD16-AC16 -> 0
A17: =MID(Taostats_CSV!C17,6,2)&"/"&MID(Taostats_CSV!C17,9,2)&"/"&LEFT(Taostats_CSV!C17,4)&" "&MID(Taostats_CSV!C17,12,8) -> 01/14/2025 23:59:48 | C17: =IF(Q17,OFFSET(Taostats_CSV!$E$1,MATCH(K17&D$1,Taostats_CSV!$X:$X,0)-1,0),IF(Taostats_CSV!F17="fee",IF(VALUE(Taostats_CSV!G17)>0,Taostats_CSV!E17,""),"")) | D17: =IF(Q17,OFFSET(Taostats_CSV!$G$1,MATCH(K17&D$1,Taostats_CSV!$X:$X,0)-1,0),IF(Taostats_CSV!F17="fee",IF(VALUE(Taostats_CSV!G17)>0,Taostats_CSV!G17,""),"")) | E17: =IF(AND(Q17,P17>0),OFFSET(Taostats_CSV!$E$1,MATCH(K17&F$1,Taostats_CSV!$X:$X,0)-1,0),IF(LEN(F17)>0,Taostats_CSV!E17,"")) -> TAO | F17: =TRIM(IF(AND(Q17,P17>0),OFFSET(Taostats_CSV!$H$1,MATCH(K17&F$1,Taostats_CSV!$X:$X,0)-1,0),IF(LEN(Taostats_CSV!H17)>0,Taostats_CSV!H17,Taostats_CSV!R17))) -> 0.108992796 | G17: =IF(AND(Q17,N17=1),OFFSET(Taostats_CSV!$E$1,MATCH(K17&H$1,Taostats_CSV!$X:$X,0)-1,0),"") | H17: =IF(AND(Q17,N17=1),OFFSET(Taostats_CSV!$G$1,MATCH(K17&H$1,Taostats_CSV!$X:$X,0)-1,0),"") | I17: =IF(AND(LEN(K17)=0,LEN(F17)>0),"Income",IF(AND(O17>0,P17>0,C17<>E17),"Trade",IF(AND(NOT(Q17),Taostats_CSV!F17="fee"),'READ ME'!$C$5,""))) -> Income | J17: =SUBSTITUTE(IF(LEN(I17)=0,Taostats_CSV!F17&" "&Taostats_CSV!J17,IF(I17="Cost","Extrinsic fee","")),"_"," ") | K17: =TRIM(IF(LEN(Taostats_CSV!I17)>0,Taostats_CSV!I17,"")) | L17: =IF(Taostats_CSV!E17<>"TAO",IF(LEN(F17)>0,F17,IF(LEN(D17)>0,D17,0))*Taostats_CSV!P17,"") | M17: =IF(LEN(L17)>0,"USD","") | N17: =COUNTIF(Taostats_CSV!$X:$X,Taostats_CSV!$I17&N$1) -> 0 | O17: =COUNTIF(Taostats_CSV!$X:$X,Taostats_CSV!$I17&O$1) -> 0 | P17: =COUNTIF(Taostats_CSV!$X:$X,Taostats_CSV!$I17&P$1) -> 0 | Q17: =AND(O17<=1,N17<=1,P17<=1,O17+N17+P17>=2) -> FALSE | R17: =IF(LEN(K17)>0,COUNTIF($K$3:K17,K17),FALSE) -> FALSE | S17: =IF(Taostats_CSV!A17=Taostats_CSV!$A$2,TRUE,Taostats_CSV!G17+Taostats_CSV!H17+Taostats_CSV!R17=0) -> FALSE | T17: =AND(NOT(S17),OR(NOT(Q17),R17=1)) -> TRUE | U17: {=AND(T17,OR(O17-N17>1,P17>1,ISERROR(A17:P17)))} -> FALSE | W17: =MATCH(K17&$W$2,Taostats_CSV!$X$3:$X$1167,0) -> #N/A | X17: =VALUE(D17) -> #VALUE! | Y17: =VALUE(F17) -> 0.1089928 | Z17: =VALUE(H17) -> #VALUE! | AB17: =SUMIF(Taostats_CSV!$E:$E,AA17,Taostats_CSV!G:G) -> 0 | AC17: =SUMIF(Taostats_CSV!$E:$E,AA17,Taostats_CSV!H:H) -> 0 | AD17: =SUMIF(Taostats_CSV!$E:$E,AA17,Taostats_CSV!R:R) -> 0 | AE17: =SUMIFS($X:$X,$C:$C,$AA17,$T:$T,TRUE) -> 0 | AF17: =SUMIFS($Y:$Y,$E:$E,$AA17,$T:$T,TRUE) -> 0 | AG17: =SUMIFS($H:$H,$G:$G,$AA17,$T:$T,TRUE) -> 0 | AH17: =AE17+AG17-AB17 -> 0 | AI17: =AF17-AD17-AC17 -> 0
A18: =MID(Taostats_CSV!C18,6,2)&"/"&MID(Taostats_CSV!C18,9,2)&"/"&LEFT(Taostats_CSV!C18,4)&" "&MID(Taostats_CSV!C18,12,8) -> 01/15/2025 23:59:48 | C18: =IF(Q18,OFFSET(Taostats_CSV!$E$1,MATCH(K18&D$1,Taostats_CSV!$X:$X,0)-1,0),IF(Taostats_CSV!F18="fee",IF(VALUE(Taostats_CSV!G18)>0,Taostats_CSV!E18,""),"")) | D18: =IF(Q18,OFFSET(Taostats_CSV!$G$1,MATCH(K18&D$1,Taostats_CSV!$X:$X,0)-1,0),IF(Taostats_CSV!F18="fee",IF(VALUE(Taostats_CSV!G18)>0,Taostats_CSV!G18,""),"")) | E18: =IF(AND(Q18,P18>0),OFFSET(Taostats_CSV!$E$1,MATCH(K18&F$1,Taostats_CSV!$X:$X,0)-1,0),IF(LEN(F18)>0,Taostats_CSV!E18,"")) -> TAO | F18: =TRIM(IF(AND(Q18,P18>0),OFFSET(Taostats_CSV!$H$1,MATCH(K18&F$1,Taostats_CSV!$X:$X,0)-1,0),IF(LEN(Taostats_CSV!H18)>0,Taostats_CSV!H18,Taostats_CSV!R18))) -> 0.108729499 | G18: =IF(AND(Q18,N18=1),OFFSET(Taostats_CSV!$E$1,MATCH(K18&H$1,Taostats_CSV!$X:$X,0)-1,0),"") | H18: =IF(AND(Q18,N18=1),OFFSET(Taostats_CSV!$G$1,MATCH(K18&H$1,Taostats_CSV!$X:$X,0)-1,0),"") | I18: =IF(AND(LEN(K18)=0,LEN(F18)>0),"Income",IF(AND(O18>0,P18>0,C18<>E18),"Trade",IF(AND(NOT(Q18),Taostats_CSV!F18="fee"),'READ ME'!$C$5,""))) -> Income | J18: =SUBSTITUTE(IF(LEN(I18)=0,Taostats_CSV!F18&" "&Taostats_CSV!J18,IF(I18="Cost","Extrinsic fee","")),"_"," ") | K18: =TRIM(IF(LEN(Taostats_CSV!I18)>0,Taostats_CSV!I18,"")) | L18: =IF(Taostats_CSV!E18<>"TAO",IF(LEN(F18)>0,F18,IF(LEN(D18)>0,D18,0))*Taostats_CSV!P18,"") | M18: =IF(LEN(L18)>0,"USD","") | N18: =COUNTIF(Taostats_CSV!$X:$X,Taostats_CSV!$I18&N$1) -> 0 | O18: =COUNTIF(Taostats_CSV!$X:$X,Taostats_CSV!$I18&O$1) -> 0 | P18: =COUNTIF(Taostats_CSV!$X:$X,Taostats_CSV!$I18&P$1) -> 0 | Q18: =AND(O18<=1,N18<=1,P18<=1,O18+N18+P18>=2) -> FALSE | R18: =IF(LEN(K18)>0,COUNTIF($K$3:K18,K18),FALSE) -> FALSE | S18: =IF(Taostats_CSV!A18=Taostats_CSV!$A$2,TRUE,Taostats_CSV!G18+Taostats_CSV!H18+Taostats_CSV!R18=0) -> FALSE | T18: =AND(NOT(S18),OR(NOT(Q18),R18=1)) -> TRUE | U18: {=AND(T18,OR(O18-N18>1,P18>1,ISERROR(A18:P18)))} -> FALSE | W18: =MATCH(K18&$W$2,Taostats_CSV!$X$3:$X$1167,0) -> #N/A | X18: =VALUE(D18) -> #VALUE! | Y18: =VALUE(F18) -> 0.1087295 | Z18: =VALUE(H18) -> #VALUE! | AB18: =SUMIF(Taostats_CSV!$E:$E,AA18,Taostats_CSV!G:G) -> 0 | AC18: =SUMIF(Taostats_CSV!$E:$E,AA18,Taostats_CSV!H:H) -> 0 | AD18: =SUMIF(Taostats_CSV!$E:$E,AA18,Taostats_CSV!R:R) -> 0 | AE18: =SUMIFS($X:$X,$C:$C,$AA18,$T:$T,TRUE) -> 0 | AF18: =SUMIFS($Y:$Y,$E:$E,$AA18,$T:$T,TRUE) -> 0 | AG18: =SUMIFS($H:$H,$G:$G,$AA18,$T:$T,TRUE) -> 0 | AH18: =AE18+AG18-AB18 -> 0 | AI18: =AF18-AD18-AC18 -> 0
A19: =MID(Taostats_CSV!C19,6,2)&"/"&MID(Taostats_CSV!C19,9,2)&"/"&LEFT(Taostats_CSV!C19,4)&" "&MID(Taostats_CSV!C19,12,8) -> 01/16/2025 23:59:48 | C19: =IF(Q19,OFFSET(Taostats_CSV!$E$1,MATCH(K19&D$1,Taostats_CSV!$X:$X,0)-1,0),IF(Taostats_CSV!F19="fee",IF(VALUE(Taostats_CSV!G19)>0,Taostats_CSV!E19,""),"")) | D19: =IF(Q19,OFFSET(Taostats_CSV!$G$1,MATCH(K19&D$1,Taostats_CSV!$X:$X,0)-1,0),IF(Taostats_CSV!F19="fee",IF(VALUE(Taostats_CSV!G19)>0,Taostats_CSV!G19,""),"")) | E19: =IF(AND(Q19,P19>0),OFFSET(Taostats_CSV!$E$1,MATCH(K19&F$1,Taostats_CSV!$X:$X,0)-1,0),IF(LEN(F19)>0,Taostats_CSV!E19,"")) -> TAO | F19: =TRIM(IF(AND(Q19,P19>0),OFFSET(Taostats_CSV!$H$1,MATCH(K19&F$1,Taostats_CSV!$X:$X,0)-1,0),IF(LEN(Taostats_CSV!H19)>0,Taostats_CSV!H19,Taostats_CSV!R19))) -> 0.108907057 | G19: =IF(AND(Q19,N19=1),OFFSET(Taostats_CSV!$E$1,MATCH(K19&H$1,Taostats_CSV!$X:$X,0)-1,0),"") | H19: =IF(AND(Q19,N19=1),OFFSET(Taostats_CSV!$G$1,MATCH(K19&H$1,Taostats_CSV!$X:$X,0)-1,0),"") | I19: =IF(AND(LEN(K19)=0,LEN(F19)>0),"Income",IF(AND(O19>0,P19>0,C19<>E19),"Trade",IF(AND(NOT(Q19),Taostats_CSV!F19="fee"),'READ ME'!$C$5,""))) -> Income | J19: =SUBSTITUTE(IF(LEN(I19)=0,Taostats_CSV!F19&" "&Taostats_CSV!J19,IF(I19="Cost","Extrinsic fee","")),"_"," ") | K19: =TRIM(IF(LEN(Taostats_CSV!I19)>0,Taostats_CSV!I19,"")) | L19: =IF(Taostats_CSV!E19<>"TAO",IF(LEN(F19)>0,F19,IF(LEN(D19)>0,D19,0))*Taostats_CSV!P19,"") | M19: =IF(LEN(L19)>0,"USD","") | N19: =COUNTIF(Taostats_CSV!$X:$X,Taostats_CSV!$I19&N$1) -> 0 | O19: =COUNTIF(Taostats_CSV!$X:$X,Taostats_CSV!$I19&O$1) -> 0 | P19: =COUNTIF(Taostats_CSV!$X:$X,Taostats_CSV!$I19&P$1) -> 0 | Q19: =AND(O19<=1,N19<=1,P19<=1,O19+N19+P19>=2) -> FALSE | R19: =IF(LEN(K19)>0,COUNTIF($K$3:K19,K19),FALSE) -> FALSE | S19: =IF(Taostats_CSV!A19=Taostats_CSV!$A$2,TRUE,Taostats_CSV!G19+Taostats_CSV!H19+Taostats_CSV!R19=0) -> FALSE | T19: =AND(NOT(S19),OR(NOT(Q19),R19=1)) -> TRUE | U19: {=AND(T19,OR(O19-N19>1,P19>1,ISERROR(A19:P19)))} -> FALSE | W19: =MATCH(K19&$W$2,Taostats_CSV!$X$3:$X$1167,0) -> #N/A | X19: =VALUE(D19) -> #VALUE! | Y19: =VALUE(F19) -> 0.10890706 | Z19: =VALUE(H19) -> #VALUE! | AB19: =SUMIF(Taostats_CSV!$E:$E,AA19,Taostats_CSV!G:G) -> 0 | AC19: =SUMIF(Taostats_CSV!$E:$E,AA19,Taostats_CSV!H:H) -> 0 | AD19: =SUMIF(Taostats_CSV!$E:$E,AA19,Taostats_CSV!R:R) -> 0 | AE19: =SUMIFS($X:$X,$C:$C,$AA19,$T:$T,TRUE) -> 0 | AF19: =SUMIFS($Y:$Y,$E:$E,$AA19,$T:$T,TRUE) -> 0 | AG19: =SUMIFS($H:$H,$G:$G,$AA19,$T:$T,TRUE) -> 0 | AH19: =AE19+AG19-AB19 -> 0 | AI19: =AF19-AD19-AC19 -> 0
A20: =MID(Taostats_CSV!C20,6,2)&"/"&MID(Taostats_CSV!C20,9,2)&"/"&LEFT(Taostats_CSV!C20,4)&" "&MID(Taostats_CSV!C20,12,8) -> 01/17/2025 23:59:48 | C20: =IF(Q20,OFFSET(Taostats_CSV!$E$1,MATCH(K20&D$1,Taostats_CSV!$X:$X,0)-1,0),IF(Taostats_CSV!F20="fee",IF(VALUE(Taostats_CSV!G20)>0,Taostats_CSV!E20,""),"")) | D20: =IF(Q20,OFFSET(Taostats_CSV!$G$1,MATCH(K20&D$1,Taostats_CSV!$X:$X,0)-1,0),IF(Taostats_CSV!F20="fee",IF(VALUE(Taostats_CSV!G20)>0,Taostats_CSV!G20,""),"")) | E20: =IF(AND(Q20,P20>0),OFFSET(Taostats_CSV!$E$1,MATCH(K20&F$1,Taostats_CSV!$X:$X,0)-1,0),IF(LEN(F20)>0,Taostats_CSV!E20,"")) -> TAO | F20: =TRIM(IF(AND(Q20,P20>0),OFFSET(Taostats_CSV!$H$1,MATCH(K20&F$1,Taostats_CSV!$X:$X,0)-1,0),IF(LEN(Taostats_CSV!H20)>0,Taostats_CSV!H20,Taostats_CSV!R20))) -> 0.11169907 | G20: =IF(AND(Q20,N20=1),OFFSET(Taostats_CSV!$E$1,MATCH(K20&H$1,Taostats_CSV!$X:$X,0)-1,0),"") | H20: =IF(AND(Q20,N20=1),OFFSET(Taostats_CSV!$G$1,MATCH(K20&H$1,Taostats_CSV!$X:$X,0)-1,0),"") | I20: =IF(AND(LEN(K20)=0,LEN(F20)>0),"Income",IF(AND(O20>0,P20>0,C20<>E20),"Trade",IF(AND(NOT(Q20),Taostats_CSV!F20="fee"),'READ ME'!$C$5,""))) -> Income | J20: =SUBSTITUTE(IF(LEN(I20)=0,Taostats_CSV!F20&" "&Taostats_CSV!J20,IF(I20="Cost","Extrinsic fee","")),"_"," ") | K20: =TRIM(IF(LEN(Taostats_CSV!I20)>0,Taostats_CSV!I20,"")) | L20: =IF(Taostats_CSV!E20<>"TAO",IF(LEN(F20)>0,F20,IF(LEN(D20)>0,D20,0))*Taostats_CSV!P20,"") | M20: =IF(LEN(L20)>0,"USD","") | N20: =COUNTIF(Taostats_CSV!$X:$X,Taostats_CSV!$I20&N$1) -> 0 | O20: =COUNTIF(Taostats_CSV!$X:$X,Taostats_CSV!$I20&O$1) -> 0 | P20: =COUNTIF(Taostats_CSV!$X:$X,Taostats_CSV!$I20&P$1) -> 0 | Q20: =AND(O20<=1,N20<=1,P20<=1,O20+N20+P20>=2) -> FALSE | R20: =IF(LEN(K20)>0,COUNTIF($K$3:K20,K20),FALSE) -> FALSE | S20: =IF(Taostats_CSV!A20=Taostats_CSV!$A$2,TRUE,Taostats_CSV!G20+Taostats_CSV!H20+Taostats_CSV!R20=0) -> FALSE | T20: =AND(NOT(S20),OR(NOT(Q20),R20=1)) -> TRUE | U20: {=AND(T20,OR(O20-N20>1,P20>1,ISERROR(A20:P20)))} -> FALSE | W20: =MATCH(K20&$W$2,Taostats_CSV!$X$3:$X$1167,0) -> #N/A | X20: =VALUE(D20) -> #VALUE! | Y20: =VALUE(F20) -> 0.11169907 | Z20: =VALUE(H20) -> #VALUE! | AB20: =SUMIF(Taostats_CSV!$E:$E,AA20,Taostats_CSV!G:G) -> 0 | AC20: =SUMIF(Taostats_CSV!$E:$E,AA20,Taostats_CSV!H:H) -> 0 | AD20: =SUMIF(Taostats_CSV!$E:$E,AA20,Taostats_CSV!R:R) -> 0 | AE20: =SUMIFS($X:$X,$C:$C,$AA20,$T:$T,TRUE) -> 0 | AF20: =SUMIFS($Y:$Y,$E:$E,$AA20,$T:$T,TRUE) -> 0 | AG20: =SUMIFS($H:$H,$G:$G,$AA20,$T:$T,TRUE) -> 0 | AH20: =AE20+AG20-AB20 -> 0 | AI20: =AF20-AD20-AC20 -> 0
A21: =MID(Taostats_CSV!C21,6,2)&"/"&MID(Taostats_CSV!C21,9,2)&"/"&LEFT(Taostats_CSV!C21,4)&" "&MID(Taostats_CSV!C21,12,8) -> 01/18/2025 23:59:48 | C21: =IF(Q21,OFFSET(Taostats_CSV!$E$1,MATCH(K21&D$1,Taostats_CSV!$X:$X,0)-1,0),IF(Taostats_CSV!F21="fee",IF(VALUE(Taostats_CSV!G21)>0,Taostats_CSV!E21,""),"")) | D21: =IF(Q21,OFFSET(Taostats_CSV!$G$1,MATCH(K21&D$1,Taostats_CSV!$X:$X,0)-1,0),IF(Taostats_CSV!F21="fee",IF(VALUE(Taostats_CSV!G21)>0,Taostats_CSV!G21,""),"")) | E21: =IF(AND(Q21,P21>0),OFFSET(Taostats_CSV!$E$1,MATCH(K21&F$1,Taostats_CSV!$X:$X,0)-1,0),IF(LEN(F21)>0,Taostats_CSV!E21,"")) -> TAO | F21: =TRIM(IF(AND(Q21,P21>0),OFFSET(Taostats_CSV!$H$1,MATCH(K21&F$1,Taostats_CSV!$X:$X,0)-1,0),IF(LEN(Taostats_CSV!H21)>0,Taostats_CSV!H21,Taostats_CSV!R21))) -> 0.115134308 | G21: =IF(AND(Q21,N21=1),OFFSET(Taostats_CSV!$E$1,MATCH(K21&H$1,Taostats_CSV!$X:$X,0)-1,0),"") | H21: =IF(AND(Q21,N21=1),OFFSET(Taostats_CSV!$G$1,MATCH(K21&H$1,Taostats_CSV!$X:$X,0)-1,0),"") | I21: =IF(AND(LEN(K21)=0,LEN(F21)>0),"Income",IF(AND(O21>0,P21>0,C21<>E21),"Trade",IF(AND(NOT(Q21),Taostats_CSV!F21="fee"),'READ ME'!$C$5,""))) -> Income | J21: =SUBSTITUTE(IF(LEN(I21)=0,Taostats_CSV!F21&" "&Taostats_CSV!J21,IF(I21="Cost","Extrinsic fee","")),"_"," ") | K21: =TRIM(IF(LEN(Taostats_CSV!I21)>0,Taostats_CSV!I21,"")) | L21: =IF(Taostats_CSV!E21<>"TAO",IF(LEN(F21)>0,F21,IF(LEN(D21)>0,D21,0))*Taostats_CSV!P21,"") | M21: =IF(LEN(L21)>0,"USD","") | N21: =COUNTIF(Taostats_CSV!$X:$X,Taostats_CSV!$I21&N$1) -> 0 | O21: =COUNTIF(Taostats_CSV!$X:$X,Taostats_CSV!$I21&O$1) -> 0 | P21: =COUNTIF(Taostats_CSV!$X:$X,Taostats_CSV!$I21&P$1) -> 0 | Q21: =AND(O21<=1,N21<=1,P21<=1,O21+N21+P21>=2) -> FALSE | R21: =IF(LEN(K21)>0,COUNTIF($K$3:K21,K21),FALSE) -> FALSE | S21: =IF(Taostats_CSV!A21=Taostats_CSV!$A$2,TRUE,Taostats_CSV!G21+Taostats_CSV!H21+Taostats_CSV!R21=0) -> FALSE | T21: =AND(NOT(S21),OR(NOT(Q21),R21=1)) -> TRUE | U21: {=AND(T21,OR(O21-N21>1,P21>1,ISERROR(A21:P21)))} -> FALSE | W21: =MATCH(K21&$W$2,Taostats_CSV!$X$3:$X$1167,0) -> #N/A | X21: =VALUE(D21) -> #VALUE! | Y21: =VALUE(F21) -> 0.11513431 | Z21: =VALUE(H21) -> #VALUE! | AB21: =SUMIF(Taostats_CSV!$E:$E,AA21,Taostats_CSV!G:G) -> 0 | AC21: =SUMIF(Taostats_CSV!$E:$E,AA21,Taostats_CSV!H:H) -> 0 | AD21: =SUMIF(Taostats_CSV!$E:$E,AA21,Taostats_CSV!R:R) -> 0 | AE21: =SUMIFS($X:$X,$C:$C,$AA21,$T:$T,TRUE) -> 0 | AF21: =SUMIFS($Y:$Y,$E:$E,$AA21,$T:$T,TRUE) -> 0 | AG21: =SUMIFS($H:$H,$G:$G,$AA21,$T:$T,TRUE) -> 0 | AH21: =AE21+AG21-AB21 -> 0 | AI21: =AF21-AD21-AC21 -> 0
A22: =MID(Taostats_CSV!C22,6,2)&"/"&MID(Taostats_CSV!C22,9,2)&"/"&LEFT(Taostats_CSV!C22,4)&" "&MID(Taostats_CSV!C22,12,8) -> 01/19/2025 23:59:48 | C22: =IF(Q22,OFFSET(Taostats_CSV!$E$1,MATCH(K22&D$1,Taostats_CSV!$X:$X,0)-1,0),IF(Taostats_CSV!F22="fee",IF(VALUE(Taostats_CSV!G22)>0,Taostats_CSV!E22,""),"")) | D22: =IF(Q22,OFFSET(Taostats_CSV!$G$1,MATCH(K22&D$1,Taostats_CSV!$X:$X,0)-1,0),IF(Taostats_CSV!F22="fee",IF(VALUE(Taostats_CSV!G22)>0,Taostats_CSV!G22,""),"")) | E22: =IF(AND(Q22,P22>0),OFFSET(Taostats_CSV!$E$1,MATCH(K22&F$1,Taostats_CSV!$X:$X,0)-1,0),IF(LEN(F22)>0,Taostats_CSV!E22,"")) -> TAO | F22: =TRIM(IF(AND(Q22,P22>0),OFFSET(Taostats_CSV!$H$1,MATCH(K22&F$1,Taostats_CSV!$X:$X,0)-1,0),IF(LEN(Taostats_CSV!H22)>0,Taostats_CSV!H22,Taostats_CSV!R22))) -> 0.114470059 | G22: =IF(AND(Q22,N22=1),OFFSET(Taostats_CSV!$E$1,MATCH(K22&H$1,Taostats_CSV!$X:$X,0)-1,0),"") | H22: =IF(AND(Q22,N22=1),OFFSET(Taostats_CSV!$G$1,MATCH(K22&H$1,Taostats_CSV!$X:$X,0)-1,0),"") | I22: =IF(AND(LEN(K22)=0,LEN(F22)>0),"Income",IF(AND(O22>0,P22>0,C22<>E22),"Trade",IF(AND(NOT(Q22),Taostats_CSV!F22="fee"),'READ ME'!$C$5,""))) -> Income | J22: =SUBSTITUTE(IF(LEN(I22)=0,Taostats_CSV!F22&" "&Taostats_CSV!J22,IF(I22="Cost","Extrinsic fee","")),"_"," ") | K22: =TRIM(IF(LEN(Taostats_CSV!I22)>0,Taostats_CSV!I22,"")) | L22: =IF(Taostats_CSV!E22<>"TAO",IF(LEN(F22)>0,F22,IF(LEN(D22)>0,D22,0))*Taostats_CSV!P22,"") | M22: =IF(LEN(L22)>0,"USD","") | N22: =COUNTIF(Taostats_CSV!$X:$X,Taostats_CSV!$I22&N$1) -> 0 | O22: =COUNTIF(Taostats_CSV!$X:$X,Taostats_CSV!$I22&O$1) -> 0 | P22: =COUNTIF(Taostats_CSV!$X:$X,Taostats_CSV!$I22&P$1) -> 0 | Q22: =AND(O22<=1,N22<=1,P22<=1,O22+N22+P22>=2) -> FALSE | R22: =IF(LEN(K22)>0,COUNTIF($K$3:K22,K22),FALSE) -> FALSE | S22: =IF(Taostats_CSV!A22=Taostats_CSV!$A$2,TRUE,Taostats_CSV!G22+Taostats_CSV!H22+Taostats_CSV!R22=0) -> FALSE | T22: =AND(NOT(S22),OR(NOT(Q22),R22=1)) -> TRUE | U22: {=AND(T22,OR(O22-N22>1,P22>1,ISERROR(A22:P22)))} -> FALSE | W22: =MATCH(K22&$W$2,Taostats_CSV!$X$3:$X$1167,0) -> #N/A | X22: =VALUE(D22) -> #VALUE! | Y22: =VALUE(F22) -> 0.11447006 | Z22: =VALUE(H22) -> #VALUE! | AB22: =SUMIF(Taostats_CSV!$E:$E,AA22,Taostats_CSV!G:G) -> 0 | AC22: =SUMIF(Taostats_CSV!$E:$E,AA22,Taostats_CSV!H:H) -> 0 | AD22: =SUMIF(Taostats_CSV!$E:$E,AA22,Taostats_CSV!R:R) -> 0 | AE22: =SUMIFS($X:$X,$C:$C,$AA22,$T:$T,TRUE) -> 0 | AF22: =SUMIFS($Y:$Y,$E:$E,$AA22,$T:$T,TRUE) -> 0 | AG22: =SUMIFS($H:$H,$G:$G,$AA22,$T:$T,TRUE) -> 0 | AH22: =AE22+AG22-AB22 -> 0 | AI22: =AF22-AD22-AC22 -> 0
... A53: =MID(Taostats_CSV!C53,6,2)&"/"&MID(Taostats_CSV!C53,9,2)&"/"&LEFT(Taostats_CSV!C53,4)&" "&MID(Taostats_CSV!C53,12,8) -> 02/19/2025 23:59:48 | C53: =IF(Q53,OFFSET(Taostats_CSV!$E$1,MATCH(K53&D$1,Taostats_CSV!$X:$X,0)-1,0),IF(Taostats_CSV!F53="fee",IF(VALUE(Taostats_CSV!G53)>0,Taostats_CSV!E53,""),"")) | D53: =IF(Q53,OFFSET(Taostats_CSV!$G$1,MATCH(K53&D$1,Taostats_CSV!$X:$X,0)-1,0),IF(Taostats_CSV!F53="fee",IF(VALUE(Taostats_CSV!G53)>0,Taostats_CSV!G53,""),"")) | E53: =IF(AND(Q53,P53>0),OFFSET(Taostats_CSV!$E$1,MATCH(K53&F$1,Taostats_CSV!$X:$X,0)-1,0),IF(LEN(F53)>0,Taostats_CSV!E53,"")) -> TAO | F53: =TRIM(IF(AND(Q53,P53>0),OFFSET(Taostats_CSV!$H$1,MATCH(K53&F$1,Taostats_CSV!$X:$X,0)-1,0),IF(LEN(Taostats_CSV!H53)>0,Taostats_CSV!H53,Taostats_CSV!R53))) -> 0.336360716 | G53: =IF(AND(Q53,N53=1),OFFSET(Taostats_CSV!$E$1,MATCH(K53&H$1,Taostats_CSV!$X:$X,0)-1,0),"") | H53: =IF(AND(Q53,N53=1),OFFSET(Taostats_CSV!$G$1,MATCH(K53&H$1,Taostats_CSV!$X:$X,0)-1,0),"") | I53: =IF(AND(LEN(K53)=0,LEN(F53)>0),"Income",IF(AND(O53>0,P53>0,C53<>E53),"Trade",IF(AND(NOT(Q53),Taostats_CSV!F53="fee"),'READ ME'!$C$5,""))) -> Income | J53: =SUBSTITUTE(IF(LEN(I53)=0,Taostats_CSV!F53&" "&Taostats_CSV!J53,IF(I53="Cost","Extrinsic fee","")),"_"," ") | K53: =TRIM(IF(LEN(Taostats_CSV!I53)>0,Taostats_CSV!I53,"")) | L53: =IF(Taostats_CSV!E53<>"TAO",IF(LEN(F53)>0,F53,IF(LEN(D53)>0,D53,0))*Taostats_CSV!P53,"") | M53: =IF(LEN(L53)>0,"USD","") | N53: =COUNTIF(Taostats_CSV!$X:$X,Taostats_CSV!$I53&N$1) -> 0 | O53: =COUNTIF(Taostats_CSV!$X:$X,Taostats_CSV!$I53&O$1) -> 0 | P53: =COUNTIF(Taostats_CSV!$X:$X,Taostats_CSV!$I53&P$1) -> 0 | Q53: =AND(O53<=1,N53<=1,P53<=1,O53+N53+P53>=2) -> FALSE | R53: =IF(LEN(K53)>0,COUNTIF($K$3:K53,K53),FALSE) -> FALSE | S53: =IF(Taostats_CSV!A53=Taostats_CSV!$A$2,TRUE,Taostats_CSV!G53+Taostats_CSV!H53+Taostats_CSV!R53=0) -> FALSE | T53: =AND(NOT(S53),OR(NOT(Q53),R53=1)) -> TRUE | U53: {=AND(T53,OR(O53-N53>1,P53>1,ISERROR(A53:P53)))} -> FALSE | W53: =MATCH(K53&$W$2,Taostats_CSV!$X$3:$X$1167,0) -> #N/A | X53: =VALUE(D53) -> #VALUE! | Y53: =VALUE(F53) -> 0.33636072 | Z53: =VALUE(H53) -> #VALUE! | AB53: =SUMIF(Taostats_CSV!$E:$E,AA53,Taostats_CSV!G:G) -> 0 | AC53: =SUMIF(Taostats_CSV!$E:$E,AA53,Taostats_CSV!H:H) -> 0 | AD53: =SUMIF(Taostats_CSV!$E:$E,AA53,Taostats_CSV!R:R) -> 0 | AE53: =SUMIFS($X:$X,$C:$C,$AA53,$T:$T,TRUE) -> 0 | AF53: =SUMIFS($Y:$Y,$E:$E,$AA53,$T:$T,TRUE) -> 0 | AG53: =SUMIFS($H:$H,$G:$G,$AA53,$T:$T,TRUE) -> 0 | AH53: =AE53+AG53-AB53 -> 0 | AI53: =AF53-AD53-AC53 -> 0
A54: =MID(Taostats_CSV!C54,6,2)&"/"&MID(Taostats_CSV!C54,9,2)&"/"&LEFT(Taostats_CSV!C54,4)&" "&MID(Taostats_CSV!C54,12,8) -> 02/20/2025 23:59:48 | C54: =IF(Q54,OFFSET(Taostats_CSV!$E$1,MATCH(K54&D$1,Taostats_CSV!$X:$X,0)-1,0),IF(Taostats_CSV!F54="fee",IF(VALUE(Taostats_CSV!G54)>0,Taostats_CSV!E54,""),"")) | D54: =IF(Q54,OFFSET(Taostats_CSV!$G$1,MATCH(K54&D$1,Taostats_CSV!$X:$X,0)-1,0),IF(Taostats_CSV!F54="fee",IF(VALUE(Taostats_CSV!G54)>0,Taostats_CSV!G54,""),"")) | E54: =IF(AND(Q54,P54>0),OFFSET(Taostats_CSV!$E$1,MATCH(K54&F$1,Taostats_CSV!$X:$X,0)-1,0),IF(LEN(F54)>0,Taostats_CSV!E54,"")) -> TAO | F54: =TRIM(IF(AND(Q54,P54>0),OFFSET(Taostats_CSV!$H$1,MATCH(K54&F$1,Taostats_CSV!$X:$X,0)-1,0),IF(LEN(Taostats_CSV!H54)>0,Taostats_CSV!H54,Taostats_CSV!R54))) -> 0.225686011 | G54: =IF(AND(Q54,N54=1),OFFSET(Taostats_CSV!$E$1,MATCH(K54&H$1,Taostats_CSV!$X:$X,0)-1,0),"") | H54: =IF(AND(Q54,N54=1),OFFSET(Taostats_CSV!$G$1,MATCH(K54&H$1,Taostats_CSV!$X:$X,0)-1,0),"") | I54: =IF(AND(LEN(K54)=0,LEN(F54)>0),"Income",IF(AND(O54>0,P54>0,C54<>E54),"Trade",IF(AND(NOT(Q54),Taostats_CSV!F54="fee"),'READ ME'!$C$5,""))) -> Income | J54: =SUBSTITUTE(IF(LEN(I54)=0,Taostats_CSV!F54&" "&Taostats_CSV!J54,IF(I54="Cost","Extrinsic fee","")),"_"," ") | K54: =TRIM(IF(LEN(Taostats_CSV!I54)>0,Taostats_CSV!I54,"")) | L54: =IF(Taostats_CSV!E54<>"TAO",IF(LEN(F54)>0,F54,IF(LEN(D54)>0,D54,0))*Taostats_CSV!P54,"") | M54: =IF(LEN(L54)>0,"USD","") | N54: =COUNTIF(Taostats_CSV!$X:$X,Taostats_CSV!$I54&N$1) -> 0 | O54: =COUNTIF(Taostats_CSV!$X:$X,Taostats_CSV!$I54&O$1) -> 0 | P54: =COUNTIF(Taostats_CSV!$X:$X,Taostats_CSV!$I54&P$1) -> 0 | Q54: =AND(O54<=1,N54<=1,P54<=1,O54+N54+P54>=2) -> FALSE | R54: =IF(LEN(K54)>0,COUNTIF($K$3:K54,K54),FALSE) -> FALSE | S54: =IF(Taostats_CSV!A54=Taostats_CSV!$A$2,TRUE,Taostats_CSV!G54+Taostats_CSV!H54+Taostats_CSV!R54=0) -> FALSE | T54: =AND(NOT(S54),OR(NOT(Q54),R54=1)) -> TRUE | U54: {=AND(T54,OR(O54-N54>1,P54>1,ISERROR(A54:P54)))} -> FALSE | W54: =MATCH(K54&$W$2,Taostats_CSV!$X$3:$X$1167,0) -> #N/A | X54: =VALUE(D54) -> #VALUE! | Y54: =VALUE(F54) -> 0.22568601 | Z54: =VALUE(H54) -> #VALUE!
A55: =MID(Taostats_CSV!C55,6,2)&"/"&MID(Taostats_CSV!C55,9,2)&"/"&LEFT(Taostats_CSV!C55,4)&" "&MID(Taostats_CSV!C55,12,8) -> 02/21/2025 23:59:48 | C55: =IF(Q55,OFFSET(Taostats_CSV!$E$1,MATCH(K55&D$1,Taostats_CSV!$X:$X,0)-1,0),IF(Taostats_CSV!F55="fee",IF(VALUE(Taostats_CSV!G55)>0,Taostats_CSV!E55,""),"")) | D55: =IF(Q55,OFFSET(Taostats_CSV!$G$1,MATCH(K55&D$1,Taostats_CSV!$X:$X,0)-1,0),IF(Taostats_CSV!F55="fee",IF(VALUE(Taostats_CSV!G55)>0,Taostats_CSV!G55,""),"")) | E55: =IF(AND(Q55,P55>0),OFFSET(Taostats_CSV!$E$1,MATCH(K55&F$1,Taostats_CSV!$X:$X,0)-1,0),IF(LEN(F55)>0,Taostats_CSV!E55,"")) -> TAO | F55: =TRIM(IF(AND(Q55,P55>0),OFFSET(Taostats_CSV!$H$1,MATCH(K55&F$1,Taostats_CSV!$X:$X,0)-1,0),IF(LEN(Taostats_CSV!H55)>0,Taostats_CSV!H55,Taostats_CSV!R55))) -> 0.230621099 | G55: =IF(AND(Q55,N55=1),OFFSET(Taostats_CSV!$E$1,MATCH(K55&H$1,Taostats_CSV!$X:$X,0)-1,0),"") | H55: =IF(AND(Q55,N55=1),OFFSET(Taostats_CSV!$G$1,MATCH(K55&H$1,Taostats_CSV!$X:$X,0)-1,0),"") | I55: =IF(AND(LEN(K55)=0,LEN(F55)>0),"Income",IF(AND(O55>0,P55>0,C55<>E55),"Trade",IF(AND(NOT(Q55),Taostats_CSV!F55="fee"),'READ ME'!$C$5,""))) -> Income | J55: =SUBSTITUTE(IF(LEN(I55)=0,Taostats_CSV!F55&" "&Taostats_CSV!J55,IF(I55="Cost","Extrinsic fee","")),"_"," ") | K55: =TRIM(IF(LEN(Taostats_CSV!I55)>0,Taostats_CSV!I55,"")) | L55: =IF(Taostats_CSV!E55<>"TAO",IF(LEN(F55)>0,F55,IF(LEN(D55)>0,D55,0))*Taostats_CSV!P55,"") | M55: =IF(LEN(L55)>0,"USD","") | N55: =COUNTIF(Taostats_CSV!$X:$X,Taostats_CSV!$I55&N$1) -> 0 | O55: =COUNTIF(Taostats_CSV!$X:$X,Taostats_CSV!$I55&O$1) -> 0 | P55: =COUNTIF(Taostats_CSV!$X:$X,Taostats_CSV!$I55&P$1) -> 0 | Q55: =AND(O55<=1,N55<=1,P55<=1,O55+N55+P55>=2) -> FALSE | R55: =IF(LEN(K55)>0,COUNTIF($K$3:K55,K55),FALSE) -> FALSE | S55: =IF(Taostats_CSV!A55=Taostats_CSV!$A$2,TRUE,Taostats_CSV!G55+Taostats_CSV!H55+Taostats_CSV!R55=0) -> FALSE | T55: =AND(NOT(S55),OR(NOT(Q55),R55=1)) -> TRUE | U55: {=AND(T55,OR(O55-N55>1,P55>1,ISERROR(A55:P55)))} -> FALSE | W55: =MATCH(K55&$W$2,Taostats_CSV!$X$3:$X$1167,0) -> #N/A | X55: =VALUE(D55) -> #VALUE! | Y55: =VALUE(F55) -> 0.2306211 | Z55: =VALUE(H55) -> #VALUE!
A56: =MID(Taostats_CSV!C56,6,2)&"/"&MID(Taostats_CSV!C56,9,2)&"/"&LEFT(Taostats_CSV!C56,4)&" "&MID(Taostats_CSV!C56,12,8) -> 02/22/2025 23:59:48 | C56: =IF(Q56,OFFSET(Taostats_CSV!$E$1,MATCH(K56&D$1,Taostats_CSV!$X:$X,0)-1,0),IF(Taostats_CSV!F56="fee",IF(VALUE(Taostats_CSV!G56)>0,Taostats_CSV!E56,""),"")) | D56: =IF(Q56,OFFSET(Taostats_CSV!$G$1,MATCH(K56&D$1,Taostats_CSV!$X:$X,0)-1,0),IF(Taostats_CSV!F56="fee",IF(VALUE(Taostats_CSV!G56)>0,Taostats_CSV!G56,""),"")) | E56: =IF(AND(Q56,P56>0),OFFSET(Taostats_CSV!$E$1,MATCH(K56&F$1,Taostats_CSV!$X:$X,0)-1,0),IF(LEN(F56)>0,Taostats_CSV!E56,"")) -> TAO | F56: =TRIM(IF(AND(Q56,P56>0),OFFSET(Taostats_CSV!$H$1,MATCH(K56&F$1,Taostats_CSV!$X:$X,0)-1,0),IF(LEN(Taostats_CSV!H56)>0,Taostats_CSV!H56,Taostats_CSV!R56))) -> 0.225027386 | G56: =IF(AND(Q56,N56=1),OFFSET(Taostats_CSV!$E$1,MATCH(K56&H$1,Taostats_CSV!$X:$X,0)-1,0),"") | H56: =IF(AND(Q56,N56=1),OFFSET(Taostats_CSV!$G$1,MATCH(K56&H$1,Taostats_CSV!$X:$X,0)-1,0),"") | I56: =IF(AND(LEN(K56)=0,LEN(F56)>0),"Income",IF(AND(O56>0,P56>0,C56<>E56),"Trade",IF(AND(NOT(Q56),Taostats_CSV!F56="fee"),'READ ME'!$C$5,""))) -> Income | J56: =SUBSTITUTE(IF(LEN(I56)=0,Taostats_CSV!F56&" "&Taostats_CSV!J56,IF(I56="Cost","Extrinsic fee","")),"_"," ") | K56: =TRIM(IF(LEN(Taostats_CSV!I56)>0,Taostats_CSV!I56,"")) | L56: =IF(Taostats_CSV!E56<>"TAO",IF(LEN(F56)>0,F56,IF(LEN(D56)>0,D56,0))*Taostats_CSV!P56,"") | M56: =IF(LEN(L56)>0,"USD","") | N56: =COUNTIF(Taostats_CSV!$X:$X,Taostats_CSV!$I56&N$1) -> 0 | O56: =COUNTIF(Taostats_CSV!$X:$X,Taostats_CSV!$I56&O$1) -> 0 | P56: =COUNTIF(Taostats_CSV!$X:$X,Taostats_CSV!$I56&P$1) -> 0 | Q56: =AND(O56<=1,N56<=1,P56<=1,O56+N56+P56>=2) -> FALSE | R56: =IF(LEN(K56)>0,COUNTIF($K$3:K56,K56),FALSE) -> FALSE | S56: =IF(Taostats_CSV!A56=Taostats_CSV!$A$2,TRUE,Taostats_CSV!G56+Taostats_CSV!H56+Taostats_CSV!R56=0) -> FALSE | T56: =AND(NOT(S56),OR(NOT(Q56),R56=1)) -> TRUE | U56: {=AND(T56,OR(O56-N56>1,P56>1,ISERROR(A56:P56)))} -> FALSE | W56: =MATCH(K56&$W$2,Taostats_CSV!$X$3:$X$1167,0) -> #N/A | X56: =VALUE(D56) -> #VALUE! | Y56: =VALUE(F56) -> 0.22502739 | Z56: =VALUE(H56) -> #VALUE!
A57: =MID(Taostats_CSV!C57,6,2)&"/"&MID(Taostats_CSV!C57,9,2)&"/"&LEFT(Taostats_CSV!C57,4)&" "&MID(Taostats_CSV!C57,12,8) -> 02/23/2025 23:59:48 | C57: =IF(Q57,OFFSET(Taostats_CSV!$E$1,MATCH(K57&D$1,Taostats_CSV!$X:$X,0)-1,0),IF(Taostats_CSV!F57="fee",IF(VALUE(Taostats_CSV!G57)>0,Taostats_CSV!E57,""),"")) | D57: =IF(Q57,OFFSET(Taostats_CSV!$G$1,MATCH(K57&D$1,Taostats_CSV!$X:$X,0)-1,0),IF(Taostats_CSV!F57="fee",IF(VALUE(Taostats_CSV!G57)>0,Taostats_CSV!G57,""),"")) | E57: =IF(AND(Q57,P57>0),OFFSET(Taostats_CSV!$E$1,MATCH(K57&F$1,Taostats_CSV!$X:$X,0)-1,0),IF(LEN(F57)>0,Taostats_CSV!E57,"")) -> TAO | F57: =TRIM(IF(AND(Q57,P57>0),OFFSET(Taostats_CSV!$H$1,MATCH(K57&F$1,Taostats_CSV!$X:$X,0)-1,0),IF(LEN(Taostats_CSV!H57)>0,Taostats_CSV!H57,Taostats_CSV!R57))) -> 0.206899526 | G57: =IF(AND(Q57,N57=1),OFFSET(Taostats_CSV!$E$1,MATCH(K57&H$1,Taostats_CSV!$X:$X,0)-1,0),"") | H57: =IF(AND(Q57,N57=1),OFFSET(Taostats_CSV!$G$1,MATCH(K57&H$1,Taostats_CSV!$X:$X,0)-1,0),"") | I57: =IF(AND(LEN(K57)=0,LEN(F57)>0),"Income",IF(AND(O57>0,P57>0,C57<>E57),"Trade",IF(AND(NOT(Q57),Taostats_CSV!F57="fee"),'READ ME'!$C$5,""))) -> Income | J57: =SUBSTITUTE(IF(LEN(I57)=0,Taostats_CSV!F57&" "&Taostats_CSV!J57,IF(I57="Cost","Extrinsic fee","")),"_"," ") | K57: =TRIM(IF(LEN(Taostats_CSV!I57)>0,Taostats_CSV!I57,"")) | L57: =IF(Taostats_CSV!E57<>"TAO",IF(LEN(F57)>0,F57,IF(LEN(D57)>0,D57,0))*Taostats_CSV!P57,"") | M57: =IF(LEN(L57)>0,"USD","") | N57: =COUNTIF(Taostats_CSV!$X:$X,Taostats_CSV!$I57&N$1) -> 0 | O57: =COUNTIF(Taostats_CSV!$X:$X,Taostats_CSV!$I57&O$1) -> 0 | P57: =COUNTIF(Taostats_CSV!$X:$X,Taostats_CSV!$I57&P$1) -> 0 | Q57: =AND(O57<=1,N57<=1,P57<=1,O57+N57+P57>=2) -> FALSE | R57: =IF(LEN(K57)>0,COUNTIF($K$3:K57,K57),FALSE) -> FALSE | S57: =IF(Taostats_CSV!A57=Taostats_CSV!$A$2,TRUE,Taostats_CSV!G57+Taostats_CSV!H57+Taostats_CSV!R57=0) -> FALSE | T57: =AND(NOT(S57),OR(NOT(Q57),R57=1)) -> TRUE | U57: {=AND(T57,OR(O57-N57>1,P57>1,ISERROR(A57:P57)))} -> FALSE | W57: =MATCH(K57&$W$2,Taostats_CSV!$X$3:$X$1167,0) -> #N/A | X57: =VALUE(D57) -> #VALUE! | Y57: =VALUE(F57) -> 0.20689953 | Z57: =VALUE(H57) -> #VALUE!
A58: =MID(Taostats_CSV!C58,6,2)&"/"&MID(Taostats_CSV!C58,9,2)&"/"&LEFT(Taostats_CSV!C58,4)&" "&MID(Taostats_CSV!C58,12,8) -> 02/24/2025 23:59:48 | C58: =IF(Q58,OFFSET(Taostats_CSV!$E$1,MATCH(K58&D$1,Taostats_CSV!$X:$X,0)-1,0),IF(Taostats_CSV!F58="fee",IF(VALUE(Taostats_CSV!G58)>0,Taostats_CSV!E58,""),"")) | D58: =IF(Q58,OFFSET(Taostats_CSV!$G$1,MATCH(K58&D$1,Taostats_CSV!$X:$X,0)-1,0),IF(Taostats_CSV!F58="fee",IF(VALUE(Taostats_CSV!G58)>0,Taostats_CSV!G58,""),"")) | E58: =IF(AND(Q58,P58>0),OFFSET(Taostats_CSV!$E$1,MATCH(K58&F$1,Taostats_CSV!$X:$X,0)-1,0),IF(LEN(F58)>0,Taostats_CSV!E58,"")) -> TAO | F58: =TRIM(IF(AND(Q58,P58>0),OFFSET(Taostats_CSV!$H$1,MATCH(K58&F$1,Taostats_CSV!$X:$X,0)-1,0),IF(LEN(Taostats_CSV!H58)>0,Taostats_CSV!H58,Taostats_CSV!R58))) -> 0.171833937 | G58: =IF(AND(Q58,N58=1),OFFSET(Taostats_CSV!$E$1,MATCH(K58&H$1,Taostats_CSV!$X:$X,0)-1,0),"") | H58: =IF(AND(Q58,N58=1),OFFSET(Taostats_CSV!$G$1,MATCH(K58&H$1,Taostats_CSV!$X:$X,0)-1,0),"") | I58: =IF(AND(LEN(K58)=0,LEN(F58)>0),"Income",IF(AND(O58>0,P58>0,C58<>E58),"Trade",IF(AND(NOT(Q58),Taostats_CSV!F58="fee"),'READ ME'!$C$5,""))) -> Income | J58: =SUBSTITUTE(IF(LEN(I58)=0,Taostats_CSV!F58&" "&Taostats_CSV!J58,IF(I58="Cost","Extrinsic fee","")),"_"," ") | K58: =TRIM(IF(LEN(Taostats_CSV!I58)>0,Taostats_CSV!I58,"")) | L58: =IF(Taostats_CSV!E58<>"TAO",IF(LEN(F58)>0,F58,IF(LEN(D58)>0,D58,0))*Taostats_CSV!P58,"") | M58: =IF(LEN(L58)>0,"USD","") | N58: =COUNTIF(Taostats_CSV!$X:$X,Taostats_CSV!$I58&N$1) -> 0 | O58: =COUNTIF(Taostats_CSV!$X:$X,Taostats_CSV!$I58&O$1) -> 0 | P58: =COUNTIF(Taostats_CSV!$X:$X,Taostats_CSV!$I58&P$1) -> 0 | Q58: =AND(O58<=1,N58<=1,P58<=1,O58+N58+P58>=2) -> FALSE | R58: =IF(LEN(K58)>0,COUNTIF($K$3:K58,K58),FALSE) -> FALSE | S58: =IF(Taostats_CSV!A58=Taostats_CSV!$A$2,TRUE,Taostats_CSV!G58+Taostats_CSV!H58+Taostats_CSV!R58=0) -> FALSE | T58: =AND(NOT(S58),OR(NOT(Q58),R58=1)) -> TRUE | U58: {=AND(T58,OR(O58-N58>1,P58>1,ISERROR(A58:P58)))} -> FALSE | W58: =MATCH(K58&$W$2,Taostats_CSV!$X$3:$X$1167,0) -> #N/A | X58: =VALUE(D58) -> #VALUE! | Y58: =VALUE(F58) -> 0.17183394 | Z58: =VALUE(H58) -> #VALUE!
A59: =MID(Taostats_CSV!C59,6,2)&"/"&MID(Taostats_CSV!C59,9,2)&"/"&LEFT(Taostats_CSV!C59,4)&" "&MID(Taostats_CSV!C59,12,8) -> 02/25/2025 23:59:48 | C59: =IF(Q59,OFFSET(Taostats_CSV!$E$1,MATCH(K59&D$1,Taostats_CSV!$X:$X,0)-1,0),IF(Taostats_CSV!F59="fee",IF(VALUE(Taostats_CSV!G59)>0,Taostats_CSV!E59,""),"")) | D59: =IF(Q59,OFFSET(Taostats_CSV!$G$1,MATCH(K59&D$1,Taostats_CSV!$X:$X,0)-1,0),IF(Taostats_CSV!F59="fee",IF(VALUE(Taostats_CSV!G59)>0,Taostats_CSV!G59,""),"")) | E59: =IF(AND(Q59,P59>0),OFFSET(Taostats_CSV!$E$1,MATCH(K59&F$1,Taostats_CSV!$X:$X,0)-1,0),IF(LEN(F59)>0,Taostats_CSV!E59,"")) -> TAO | F59: =TRIM(IF(AND(Q59,P59>0),OFFSET(Taostats_CSV!$H$1,MATCH(K59&F$1,Taostats_CSV!$X:$X,0)-1,0),IF(LEN(Taostats_CSV!H59)>0,Taostats_CSV!H59,Taostats_CSV!R59))) -> 0.15202322 | G59: =IF(AND(Q59,N59=1),OFFSET(Taostats_CSV!$E$1,MATCH(K59&H$1,Taostats_CSV!$X:$X,0)-1,0),"") | H59: =IF(AND(Q59,N59=1),OFFSET(Taostats_CSV!$G$1,MATCH(K59&H$1,Taostats_CSV!$X:$X,0)-1,0),"") | I59: =IF(AND(LEN(K59)=0,LEN(F59)>0),"Income",IF(AND(O59>0,P59>0,C59<>E59),"Trade",IF(AND(NOT(Q59),Taostats_CSV!F59="fee"),'READ ME'!$C$5,""))) -> Income | J59: =SUBSTITUTE(IF(LEN(I59)=0,Taostats_CSV!F59&" "&Taostats_CSV!J59,IF(I59="Cost","Extrinsic fee","")),"_"," ") | K59: =TRIM(IF(LEN(Taostats_CSV!I59)>0,Taostats_CSV!I59,"")) | L59: =IF(Taostats_CSV!E59<>"TAO",IF(LEN(F59)>0,F59,IF(LEN(D59)>0,D59,0))*Taostats_CSV!P59,"") | M59: =IF(LEN(L59)>0,"USD","") | N59: =COUNTIF(Taostats_CSV!$X:$X,Taostats_CSV!$I59&N$1) -> 0 | O59: =COUNTIF(Taostats_CSV!$X:$X,Taostats_CSV!$I59&O$1) -> 0 | P59: =COUNTIF(Taostats_CSV!$X:$X,Taostats_CSV!$I59&P$1) -> 0 | Q59: =AND(O59<=1,N59<=1,P59<=1,O59+N59+P59>=2) -> FALSE | R59: =IF(LEN(K59)>0,COUNTIF($K$3:K59,K59),FALSE) -> FALSE | S59: =IF(Taostats_CSV!A59=Taostats_CSV!$A$2,TRUE,Taostats_CSV!G59+Taostats_CSV!H59+Taostats_CSV!R59=0) -> FALSE | T59: =AND(NOT(S59),OR(NOT(Q59),R59=1)) -> TRUE | U59: {=AND(T59,OR(O59-N59>1,P59>1,ISERROR(A59:P59)))} -> FALSE | W59: =MATCH(K59&$W$2,Taostats_CSV!$X$3:$X$1167,0) -> #N/A | X59: =VALUE(D59) -> #VALUE! | Y59: =VALUE(F59) -> 0.15202322 | Z59: =VALUE(H59) -> #VALUE!
A60: =MID(Taostats_CSV!C60,6,2)&"/"&MID(Taostats_CSV!C60,9,2)&"/"&LEFT(Taostats_CSV!C60,4)&" "&MID(Taostats_CSV!C60,12,8) -> 02/26/2025 14:09:12 | C60: =IF(Q60,OFFSET(Taostats_CSV!$E$1,MATCH(K60&D$1,Taostats_CSV!$X:$X,0)-1,0),IF(Taostats_CSV!F60="fee",IF(VALUE(Taostats_CSV!G60)>0,Taostats_CSV!E60,""),"")) -> TAO | D60: =IF(Q60,OFFSET(Taostats_CSV!$G$1,MATCH(K60&D$1,Taostats_CSV!$X:$X,0)-1,0),IF(Taostats_CSV!F60="fee",IF(VALUE(Taostats_CSV!G60)>0,Taostats_CSV!G60,""),"")) -> 1 | E60: =IF(AND(Q60,P60>0),OFFSET(Taostats_CSV!$E$1,MATCH(K60&F$1,Taostats_CSV!$X:$X,0)-1,0),IF(LEN(F60)>0,Taostats_CSV!E60,"")) | F60: =TRIM(IF(AND(Q60,P60>0),OFFSET(Taostats_CSV!$H$1,MATCH(K60&F$1,Taostats_CSV!$X:$X,0)-1,0),IF(LEN(Taostats_CSV!H60)>0,Taostats_CSV!H60,Taostats_CSV!R60))) | G60: =IF(AND(Q60,N60=1),OFFSET(Taostats_CSV!$E$1,MATCH(K60&H$1,Taostats_CSV!$X:$X,0)-1,0),"") -> TAO | H60: =IF(AND(Q60,N60=1),OFFSET(Taostats_CSV!$G$1,MATCH(K60&H$1,Taostats_CSV!$X:$X,0)-1,0),"") -> 0.000135261 | I60: =IF(AND(LEN(K60)=0,LEN(F60)>0),"Income",IF(AND(O60>0,P60>0,C60<>E60),"Trade",IF(AND(NOT(Q60),Taostats_CSV!F60="fee"),'READ ME'!$C$5,""))) | J60: =SUBSTITUTE(IF(LEN(I60)=0,Taostats_CSV!F60&" "&Taostats_CSV!J60,IF(I60="Cost","Extrinsic fee","")),"_"," ") -> fee Balances.transfer keep alive | K60: =TRIM(IF(LEN(Taostats_CSV!I60)>0,Taostats_CSV!I60,"")) -> 5011678-0003 | L60: =IF(Taostats_CSV!E60<>"TAO",IF(LEN(F60)>0,F60,IF(LEN(D60)>0,D60,0))*Taostats_CSV!P60,"") | M60: =IF(LEN(L60)>0,"USD","") | N60: =COUNTIF(Taostats_CSV!$X:$X,Taostats_CSV!$I60&N$1) -> 1 | O60: =COUNTIF(Taostats_CSV!$X:$X,Taostats_CSV!$I60&O$1) -> 1 | P60: =COUNTIF(Taostats_CSV!$X:$X,Taostats_CSV!$I60&P$1) -> 0 | Q60: =AND(O60<=1,N60<=1,P60<=1,O60+N60+P60>=2) -> TRUE | R60: =IF(LEN(K60)>0,COUNTIF($K$3:K60,K60),FALSE) -> 1 | S60: =IF(Taostats_CSV!A60=Taostats_CSV!$A$2,TRUE,Taostats_CSV!G60+Taostats_CSV!H60+Taostats_CSV!R60=0) -> FALSE | T60: =AND(NOT(S60),OR(NOT(Q60),R60=1)) -> TRUE | U60: {=AND(T60,OR(O60-N60>1,P60>1,ISERROR(A60:P60)))} -> FALSE | W60: =MATCH(K60&F$1,Taostats_CSV!$X:$X,0)-1 -> #N/A | X60: =VALUE(D60) -> 1 | Y60: =VALUE(F60) -> #VALUE! | Z60: =VALUE(H60) -> 0.000135261
A61: =MID(Taostats_CSV!C61,6,2)&"/"&MID(Taostats_CSV!C61,9,2)&"/"&LEFT(Taostats_CSV!C61,4)&" "&MID(Taostats_CSV!C61,12,8) -> 02/26/2025 14:09:12 | C61: =IF(Q61,OFFSET(Taostats_CSV!$E$1,MATCH(K61&D$1,Taostats_CSV!$X:$X,0)-1,0),IF(Taostats_CSV!F61="fee","",IF(VALUE(Taostats_CSV!G61)>0,Taostats_CSV!E61,""))) -> TAO | D61: =IF(Q61,OFFSET(Taostats_CSV!$G$1,MATCH(K61&D$1,Taostats_CSV!$X:$X,0)-1,0),IF(Taostats_CSV!F61="fee","",IF(VALUE(Taostats_CSV!G61)>0,Taostats_CSV!G61,""))) -> 1 | E61: =IF(AND(Q61,P61>0),OFFSET(Taostats_CSV!$E$1,MATCH(K61&F$1,Taostats_CSV!$X:$X,0)-1,0),IF(LEN(F61)>0,Taostats_CSV!E61,"")) | F61: =TRIM(IF(AND(Q61,P61>0),OFFSET(Taostats_CSV!$H$1,MATCH(K61&F$1,Taostats_CSV!$X:$X,0)-1,0),IF(LEN(Taostats_CSV!H61)>0,Taostats_CSV!H61,Taostats_CSV!R61))) | G61: =IF(AND(Q61,N61=1),OFFSET(Taostats_CSV!$E$1,MATCH(K61&H$1,Taostats_CSV!$X:$X,0)-1,0),IF(Taostats_CSV!F61="fee",Taostats_CSV!E61,"")) -> TAO | H61: =IF(AND(Q61,N61=1),OFFSET(Taostats_CSV!$G$1,MATCH(K61&H$1,Taostats_CSV!$X:$X,0)-1,0),IF(Taostats_CSV!F61="fee",Taostats_CSV!G61,"")) -> 0.000135261 | I61: =IF(AND(LEN(K61)=0,LEN(F61)>0),"Income",IF(AND(O61>0,P61>0,C61<>E61),"Trade",IF(AND(NOT(Q61),Taostats_CSV!F61="fee"),'READ ME'!$C$5,""))) | J61: =SUBSTITUTE(IF(LEN(I61)=0,Taostats_CSV!F61&" "&Taostats_CSV!J61,IF(I61="Cost","Extrinsic fee","")),"_"," ") -> transfer out 5HbnKZMzGk3GT3mpWZgKuQHq3CC8LeW2tbNq1FkBLQhzUX6L | K61: =TRIM(IF(LEN(Taostats_CSV!I61)>0,Taostats_CSV!I61,"")) -> 5011678-0003 | L61: =IF(Taostats_CSV!E61<>"TAO",IF(LEN(F61)>0,F61,IF(LEN(D61)>0,D61,0))*Taostats_CSV!P61,"") | M61: =IF(LEN(L61)>0,"USD","") | N61: =COUNTIF(Taostats_CSV!$X:$X,Taostats_CSV!$I61&N$1) -> 1 | O61: =COUNTIF(Taostats_CSV!$X:$X,Taostats_CSV!$I61&O$1) -> 1 | P61: =COUNTIF(Taostats_CSV!$X:$X,Taostats_CSV!$I61&P$1) -> 0 | Q61: =AND(O61<=1,N61<=1,P61<=1,O61+N61+P61>=2) -> TRUE | R61: =IF(LEN(K61)>0,COUNTIF($K$3:K61,K61),FALSE) -> 2 | S61: =IF(Taostats_CSV!A61=Taostats_CSV!$A$2,TRUE,Taostats_CSV!G61+Taostats_CSV!H61+Taostats_CSV!R61=0) -> FALSE | T61: =AND(NOT(S61),OR(NOT(Q61),R61=1)) -> FALSE | U61: {=AND(T61,OR(O61-N61>1,P61>1,ISERROR(A61:P61)))} -> FALSE | W61: =MATCH(K61&$W$2,Taostats_CSV!$X$3:$X$1167,0) -> 58 | X61: =VALUE(D61) -> 1 | Y61: =VALUE(F61) -> #VALUE! | Z61: =VALUE(H61) -> 0.000135261
A62: =MID(Taostats_CSV!C62,6,2)&"/"&MID(Taostats_CSV!C62,9,2)&"/"&LEFT(Taostats_CSV!C62,4)&" "&MID(Taostats_CSV!C62,12,8) -> 02/26/2025 14:32:12 | C62: =IF(Q62,OFFSET(Taostats_CSV!$E$1,MATCH(K62&D$1,Taostats_CSV!$X:$X,0)-1,0),IF(Taostats_CSV!F62="fee",IF(VALUE(Taostats_CSV!G62)>0,Taostats_CSV!E62,""),"")) -> TAO | D62: =IF(Q62,OFFSET(Taostats_CSV!$G$1,MATCH(K62&D$1,Taostats_CSV!$X:$X,0)-1,0),IF(Taostats_CSV!F62="fee",IF(VALUE(Taostats_CSV!G62)>0,Taostats_CSV!G62,""),"")) -> 5e-05 | E62: =IF(AND(Q62,P62>0),OFFSET(Taostats_CSV!$E$1,MATCH(K62&F$1,Taostats_CSV!$X:$X,0)-1,0),IF(LEN(F62)>0,Taostats_CSV!E62,"")) | F62: =TRIM(IF(AND(Q62,P62>0),OFFSET(Taostats_CSV!$H$1,MATCH(K62&F$1,Taostats_CSV!$X:$X,0)-1,0),IF(LEN(Taostats_CSV!H62)>0,Taostats_CSV!H62,Taostats_CSV!R62))) | G62: =IF(AND(Q62,N62=1),OFFSET(Taostats_CSV!$E$1,MATCH(K62&H$1,Taostats_CSV!$X:$X,0)-1,0),"") | H62: =IF(AND(Q62,N62=1),OFFSET(Taostats_CSV!$G$1,MATCH(K62&H$1,Taostats_CSV!$X:$X,0)-1,0),"") | I62: =IF(AND(LEN(K62)=0,LEN(F62)>0),"Income",IF(AND(O62>0,P62>0,C62<>E62),"Trade",IF(AND(NOT(Q62),Taostats_CSV!F62="fee"),'READ ME'!$C$5,""))) -> Merchant Payment | J62: =SUBSTITUTE(IF(LEN(I62)=0,Taostats_CSV!F62&" "&Taostats_CSV!J62,IF(I62="Cost","Extrinsic fee","")),"_"," ") | K62: =TRIM(IF(LEN(Taostats_CSV!I62)>0,Taostats_CSV!I62,"")) -> 5011793-0005 | L62: =IF(Taostats_CSV!E62<>"TAO",IF(LEN(F62)>0,F62,IF(LEN(D62)>0,D62,0))*Taostats_CSV!P62,"") | M62: =IF(LEN(L62)>0,"USD","") | N62: =COUNTIF(Taostats_CSV!$X:$X,Taostats_CSV!$I62&N$1) -> 1 | O62: =COUNTIF(Taostats_CSV!$X:$X,Taostats_CSV!$I62&O$1) -> 0 | P62: =COUNTIF(Taostats_CSV!$X:$X,Taostats_CSV!$I62&P$1) -> 0 | Q62: =AND(O62<=1,N62<=1,P62<=1,O62+N62+P62>=2) -> FALSE | R62: =IF(LEN(K62)>0,COUNTIF($K$3:K62,K62),FALSE) -> 1 | S62: =IF(Taostats_CSV!A62=Taostats_CSV!$A$2,TRUE,Taostats_CSV!G62+Taostats_CSV!H62+Taostats_CSV!R62=0) -> FALSE | T62: =AND(NOT(S62),OR(NOT(Q62),R62=1)) -> TRUE | U62: {=AND(T62,OR(O62-N62>1,P62>1,ISERROR(A62:P62)))} -> FALSE | W62: =MATCH(K62&$W$2,Taostats_CSV!$X$3:$X$1167,0) -> 60 | X62: =VALUE(D62) -> 5e-05 | Y62: =VALUE(F62) -> #VALUE! | Z62: =VALUE(H62) -> #VALUE!
A63: =MID(Taostats_CSV!C63,6,2)&"/"&MID(Taostats_CSV!C63,9,2)&"/"&LEFT(Taostats_CSV!C63,4)&" "&MID(Taostats_CSV!C63,12,8) -> 02/26/2025 18:27:24 | C63: =IF(Q63,OFFSET(Taostats_CSV!$E$1,MATCH(K63&D$1,Taostats_CSV!$X:$X,0)-1,0),IF(Taostats_CSV!F63="fee",IF(VALUE(Taostats_CSV!G63)>0,Taostats_CSV!E63,""),"")) -> TAO | D63: =IF(Q63,OFFSET(Taostats_CSV!$G$1,MATCH(K63&D$1,Taostats_CSV!$X:$X,0)-1,0),IF(Taostats_CSV!F63="fee",IF(VALUE(Taostats_CSV!G63)>0,Taostats_CSV!G63,""),"")) -> 5e-05 | E63: =IF(AND(Q63,P63>0),OFFSET(Taostats_CSV!$E$1,MATCH(K63&F$1,Taostats_CSV!$X:$X,0)-1,0),IF(LEN(F63)>0,Taostats_CSV!E63,"")) | F63: =TRIM(IF(AND(Q63,P63>0),OFFSET(Taostats_CSV!$H$1,MATCH(K63&F$1,Taostats_CSV!$X:$X,0)-1,0),IF(LEN(Taostats_CSV!H63)>0,Taostats_CSV!H63,Taostats_CSV!R63))) | G63: =IF(AND(Q63,N63=1),OFFSET(Taostats_CSV!$E$1,MATCH(K63&H$1,Taostats_CSV!$X:$X,0)-1,0),"") | H63: =IF(AND(Q63,N63=1),OFFSET(Taostats_CSV!$G$1,MATCH(K63&H$1,Taostats_CSV!$X:$X,0)-1,0),"") | I63: =IF(AND(LEN(K63)=0,LEN(F63)>0),"Income",IF(AND(O63>0,P63>0,C63<>E63),"Trade",IF(AND(NOT(Q63),Taostats_CSV!F63="fee"),'READ ME'!$C$5,""))) -> Merchant Payment | J63: =SUBSTITUTE(IF(LEN(I63)=0,Taostats_CSV!F63&" "&Taostats_CSV!J63,IF(I63="Cost","Extrinsic fee","")),"_"," ") | K63: =TRIM(IF(LEN(Taostats_CSV!I63)>0,Taostats_CSV!I63,"")) -> 5012969-0007 | L63: =IF(Taostats_CSV!E63<>"TAO",IF(LEN(F63)>0,F63,IF(LEN(D63)>0,D63,0))*Taostats_CSV!P63,"") | M63: =IF(LEN(L63)>0,"USD","") | N63: =COUNTIF(Taostats_CSV!$X:$X,Taostats_CSV!$I63&N$1) -> 1 | O63: =COUNTIF(Taostats_CSV!$X:$X,Taostats_CSV!$I63&O$1) -> 0 | P63: =COUNTIF(Taostats_CSV!$X:$X,Taostats_CSV!$I63&P$1) -> 0 | Q63: =AND(O63<=1,N63<=1,P63<=1,O63+N63+P63>=2) -> FALSE | R63: =IF(LEN(K63)>0,COUNTIF($K$3:K63,K63),FALSE) -> 1 | S63: =IF(Taostats_CSV!A63=Taostats_CSV!$A$2,TRUE,Taostats_CSV!G63+Taostats_CSV!H63+Taostats_CSV!R63=0) -> FALSE | T63: =AND(NOT(S63),OR(NOT(Q63),R63=1)) -> TRUE | U63: {=AND(T63,OR(O63-N63>1,P63>1,ISERROR(A63:P63)))} -> FALSE | W63: =MATCH(K63&$W$2,Taostats_CSV!$X$3:$X$1167,0) -> 61 | X63: =VALUE(D63) -> 5e-05 | Y63: =VALUE(F63) -> #VALUE! | Z63: =VALUE(H63) -> #VALUE!
A64: =MID(Taostats_CSV!C64,6,2)&"/"&MID(Taostats_CSV!C64,9,2)&"/"&LEFT(Taostats_CSV!C64,4)&" "&MID(Taostats_CSV!C64,12,8) -> 02/26/2025 18:28:36 | C64: =IF(Q64,OFFSET(Taostats_CSV!$E$1,MATCH(K64&D$1,Taostats_CSV!$X:$X,0)-1,0),IF(Taostats_CSV!F64="fee",IF(VALUE(Taostats_CSV!G64)>0,Taostats_CSV!E64,""),"")) -> TAO | D64: =IF(Q64,OFFSET(Taostats_CSV!$G$1,MATCH(K64&D$1,Taostats_CSV!$X:$X,0)-1,0),IF(Taostats_CSV!F64="fee",IF(VALUE(Taostats_CSV!G64)>0,Taostats_CSV!G64,""),"")) -> 10 | E64: =IF(AND(Q64,P64>0),OFFSET(Taostats_CSV!$E$1,MATCH(K64&F$1,Taostats_CSV!$X:$X,0)-1,0),IF(LEN(F64)>0,Taostats_CSV!E64,"")) | F64: =TRIM(IF(AND(Q64,P64>0),OFFSET(Taostats_CSV!$H$1,MATCH(K64&F$1,Taostats_CSV!$X:$X,0)-1,0),IF(LEN(Taostats_CSV!H64)>0,Taostats_CSV!H64,Taostats_CSV!R64))) | G64: =IF(AND(Q64,N64=1),OFFSET(Taostats_CSV!$E$1,MATCH(K64&H$1,Taostats_CSV!$X:$X,0)-1,0),"") -> TAO | H64: =IF(AND(Q64,N64=1),OFFSET(Taostats_CSV!$G$1,MATCH(K64&H$1,Taostats_CSV!$X:$X,0)-1,0),"") -> 0.000135263 | I64: =IF(AND(LEN(K64)=0,LEN(F64)>0),"Income",IF(AND(O64>0,P64>0,C64<>E64),"Trade",IF(AND(NOT(Q64),Taostats_CSV!F64="fee"),'READ ME'!$C$5,""))) | J64: =SUBSTITUTE(IF(LEN(I64)=0,Taostats_CSV!F64&" "&Taostats_CSV!J64,IF(I64="Cost","Extrinsic fee","")),"_"," ") -> fee Balances.transfer keep alive | K64: =TRIM(IF(LEN(Taostats_CSV!I64)>0,Taostats_CSV!I64,"")) -> 5012975-0006 | L64: =IF(Taostats_CSV!E64<>"TAO",IF(LEN(F64)>0,F64,IF(LEN(D64)>0,D64,0))*Taostats_CSV!P64,"") | M64: =IF(LEN(L64)>0,"USD","") | N64: =COUNTIF(Taostats_CSV!$X:$X,Taostats_CSV!$I64&N$1) -> 1 | O64: =COUNTIF(Taostats_CSV!$X:$X,Taostats_CSV!$I64&O$1) -> 1 | P64: =COUNTIF(Taostats_CSV!$X:$X,Taostats_CSV!$I64&P$1) -> 0 | Q64: =AND(O64<=1,N64<=1,P64<=1,O64+N64+P64>=2) -> TRUE | R64: =IF(LEN(K64)>0,COUNTIF($K$3:K64,K64),FALSE) -> 1 | S64: =IF(Taostats_CSV!A64=Taostats_CSV!$A$2,TRUE,Taostats_CSV!G64+Taostats_CSV!H64+Taostats_CSV!R64=0) -> FALSE | T64: =AND(NOT(S64),OR(NOT(Q64),R64=1)) -> TRUE | U64: {=AND(T64,OR(O64-N64>1,P64>1,ISERROR(A64:P64)))} -> FALSE | W64: =MATCH(K64&$W$2,Taostats_CSV!$X$3:$X$1167,0) -> 62 | X64: =VALUE(D64) -> 10 | Y64: =VALUE(F64) -> #VALUE! | Z64: =VALUE(H64) -> 0.000135263
A65: =MID(Taostats_CSV!C65,6,2)&"/"&MID(Taostats_CSV!C65,9,2)&"/"&LEFT(Taostats_CSV!C65,4)&" "&MID(Taostats_CSV!C65,12,8) -> 02/26/2025 18:28:36 | C65: =IF(Q65,OFFSET(Taostats_CSV!$E$1,MATCH(K65&D$1,Taostats_CSV!$X:$X,0)-1,0),IF(Taostats_CSV!F65="fee","",IF(VALUE(Taostats_CSV!G65)>0,Taostats_CSV!E65,""))) -> TAO | D65: =IF(Q65,OFFSET(Taostats_CSV!$G$1,MATCH(K65&D$1,Taostats_CSV!$X:$X,0)-1,0),IF(Taostats_CSV!F65="fee","",IF(VALUE(Taostats_CSV!G65)>0,Taostats_CSV!G65,""))) -> 10 | E65: =IF(AND(Q65,P65>0),OFFSET(Taostats_CSV!$E$1,MATCH(K65&F$1,Taostats_CSV!$X:$X,0)-1,0),IF(LEN(F65)>0,Taostats_CSV!E65,"")) | F65: =TRIM(IF(AND(Q65,P65>0),OFFSET(Taostats_CSV!$H$1,MATCH(K65&F$1,Taostats_CSV!$X:$X,0)-1,0),IF(LEN(Taostats_CSV!H65)>0,Taostats_CSV!H65,Taostats_CSV!R65))) | G65: =IF(AND(Q65,N65=1),OFFSET(Taostats_CSV!$E$1,MATCH(K65&H$1,Taostats_CSV!$X:$X,0)-1,0),IF(Taostats_CSV!F65="fee",Taostats_CSV!E65,"")) -> TAO | H65: =IF(AND(Q65,N65=1),OFFSET(Taostats_CSV!$G$1,MATCH(K65&H$1,Taostats_CSV!$X:$X,0)-1,0),IF(Taostats_CSV!F65="fee",Taostats_CSV!G65,"")) -> 0.000135263 | I65: =IF(AND(LEN(K65)=0,LEN(F65)>0),"Income",IF(AND(O65>0,P65>0,C65<>E65),"Trade",IF(AND(NOT(Q65),Taostats_CSV!F65="fee"),'READ ME'!$C$5,""))) | J65: =SUBSTITUTE(IF(LEN(I65)=0,Taostats_CSV!F65&" "&Taostats_CSV!J65,IF(I65="Cost","Extrinsic fee","")),"_"," ") -> transfer out 5HbnKZMzGk3GT3mpWZgKuQHq3CC8LeW2tbNq1FkBLQhzUX6L | K65: =TRIM(IF(LEN(Taostats_CSV!I65)>0,Taostats_CSV!I65,"")) -> 5012975-0006 | L65: =IF(Taostats_CSV!E65<>"TAO",IF(LEN(F65)>0,F65,IF(LEN(D65)>0,D65,0))*Taostats_CSV!P65,"") | M65: =IF(LEN(L65)>0,"USD","") | N65: =COUNTIF(Taostats_CSV!$X:$X,Taostats_CSV!$I65&N$1) -> 1 | O65: =COUNTIF(Taostats_CSV!$X:$X,Taostats_CSV!$I65&O$1) -> 1 | P65: =COUNTIF(Taostats_CSV!$X:$X,Taostats_CSV!$I65&P$1) -> 0 | Q65: =AND(O65<=1,N65<=1,P65<=1,O65+N65+P65>=2) -> TRUE | R65: =IF(LEN(K65)>0,COUNTIF($K$3:K65,K65),FALSE) -> 2 | S65: =IF(Taostats_CSV!A65=Taostats_CSV!$A$2,TRUE,Taostats_CSV!G65+Taostats_CSV!H65+Taostats_CSV!R65=0) -> FALSE | T65: =AND(NOT(S65),OR(NOT(Q65),R65=1)) -> FALSE | U65: {=AND(T65,OR(O65-N65>1,P65>1,ISERROR(A65:P65)))} -> FALSE | W65: =MATCH(K65&$W$2,Taostats_CSV!$X$3:$X$1167,0) -> 62 | X65: =VALUE(D65) -> 10 | Y65: =VALUE(F65) -> #VALUE! | Z65: =VALUE(H65) -> 0.000135263
A66: =MID(Taostats_CSV!C66,6,2)&"/"&MID(Taostats_CSV!C66,9,2)&"/"&LEFT(Taostats_CSV!C66,4)&" "&MID(Taostats_CSV!C66,12,8) -> 02/26/2025 18:30:36 | C66: =IF(Q66,OFFSET(Taostats_CSV!$E$1,MATCH(K66&D$1,Taostats_CSV!$X:$X,0)-1,0),IF(Taostats_CSV!F66="fee",IF(VALUE(Taostats_CSV!G66)>0,Taostats_CSV!E66,""),"")) -> TAO | D66: =IF(Q66,OFFSET(Taostats_CSV!$G$1,MATCH(K66&D$1,Taostats_CSV!$X:$X,0)-1,0),IF(Taostats_CSV!F66="fee",IF(VALUE(Taostats_CSV!G66)>0,Taostats_CSV!G66,""),"")) -> 5e-05 | E66: =IF(AND(Q66,P66>0),OFFSET(Taostats_CSV!$E$1,MATCH(K66&F$1,Taostats_CSV!$X:$X,0)-1,0),IF(LEN(F66)>0,Taostats_CSV!E66,"")) | F66: =TRIM(IF(AND(Q66,P66>0),OFFSET(Taostats_CSV!$H$1,MATCH(K66&F$1,Taostats_CSV!$X:$X,0)-1,0),IF(LEN(Taostats_CSV!H66)>0,Taostats_CSV!H66,Taostats_CSV!R66))) | G66: =IF(AND(Q66,N66=1),OFFSET(Taostats_CSV!$E$1,MATCH(K66&H$1,Taostats_CSV!$X:$X,0)-1,0),"") | H66: =IF(AND(Q66,N66=1),OFFSET(Taostats_CSV!$G$1,MATCH(K66&H$1,Taostats_CSV!$X:$X,0)-1,0),"") | I66: =IF(AND(LEN(K66)=0,LEN(F66)>0),"Income",IF(AND(O66>0,P66>0,C66<>E66),"Trade",IF(AND(NOT(Q66),Taostats_CSV!F66="fee"),'READ ME'!$C$5,""))) -> Merchant Payment | J66: =SUBSTITUTE(IF(LEN(I66)=0,Taostats_CSV!F66&" "&Taostats_CSV!J66,IF(I66="Cost","Extrinsic fee","")),"_"," ") | K66: =TRIM(IF(LEN(Taostats_CSV!I66)>0,Taostats_CSV!I66,"")) -> 5012985-0004 | L66: =IF(Taostats_CSV!E66<>"TAO",IF(LEN(F66)>0,F66,IF(LEN(D66)>0,D66,0))*Taostats_CSV!P66,"") | M66: =IF(LEN(L66)>0,"USD","") | N66: =COUNTIF(Taostats_CSV!$X:$X,Taostats_CSV!$I66&N$1) -> 1 | O66: =COUNTIF(Taostats_CSV!$X:$X,Taostats_CSV!$I66&O$1) -> 0 | P66: =COUNTIF(Taostats_CSV!$X:$X,Taostats_CSV!$I66&P$1) -> 0 | Q66: =AND(O66<=1,N66<=1,P66<=1,O66+N66+P66>=2) -> FALSE | R66: =IF(LEN(K66)>0,COUNTIF($K$3:K66,K66),FALSE) -> 1 | S66: =IF(Taostats_CSV!A66=Taostats_CSV!$A$2,TRUE,Taostats_CSV!G66+Taostats_CSV!H66+Taostats_CSV!R66=0) -> FALSE | T66: =AND(NOT(S66),OR(NOT(Q66),R66=1)) -> TRUE | U66: {=AND(T66,OR(O66-N66>1,P66>1,ISERROR(A66:P66)))} -> FALSE | W66: =MATCH(K66&$W$2,Taostats_CSV!$X$3:$X$1167,0) -> 64 | X66: =VALUE(D66) -> 5e-05 | Y66: =VALUE(F66) -> #VALUE! | Z66: =VALUE(H66) -> #VALUE!
A67: =MID(Taostats_CSV!C67,6,2)&"/"&MID(Taostats_CSV!C67,9,2)&"/"&LEFT(Taostats_CSV!C67,4)&" "&MID(Taostats_CSV!C67,12,8) -> 02/26/2025 18:31:36 | C67: =IF(Q67,OFFSET(Taostats_CSV!$E$1,MATCH(K67&D$1,Taostats_CSV!$X:$X,0)-1,0),IF(Taostats_CSV!F67="fee",IF(VALUE(Taostats_CSV!G67)>0,Taostats_CSV!E67,""),"")) -> TAO | D67: =IF(Q67,OFFSET(Taostats_CSV!$G$1,MATCH(K67&D$1,Taostats_CSV!$X:$X,0)-1,0),IF(Taostats_CSV!F67="fee",IF(VALUE(Taostats_CSV!G67)>0,Taostats_CSV!G67,""),"")) -> 30 | E67: =IF(AND(Q67,P67>0),OFFSET(Taostats_CSV!$E$1,MATCH(K67&F$1,Taostats_CSV!$X:$X,0)-1,0),IF(LEN(F67)>0,Taostats_CSV!E67,"")) | F67: =TRIM(IF(AND(Q67,P67>0),OFFSET(Taostats_CSV!$H$1,MATCH(K67&F$1,Taostats_CSV!$X:$X,0)-1,0),IF(LEN(Taostats_CSV!H67)>0,Taostats_CSV!H67,Taostats_CSV!R67))) | G67: =IF(AND(Q67,N67=1),OFFSET(Taostats_CSV!$E$1,MATCH(K67&H$1,Taostats_CSV!$X:$X,0)-1,0),"") -> TAO | H67: =IF(AND(Q67,N67=1),OFFSET(Taostats_CSV!$G$1,MATCH(K67&H$1,Taostats_CSV!$X:$X,0)-1,0),"") -> 0.000135263 | I67: =IF(AND(LEN(K67)=0,LEN(F67)>0),"Income",IF(AND(O67>0,P67>0,C67<>E67),"Trade",IF(AND(NOT(Q67),Taostats_CSV!F67="fee"),'READ ME'!$C$5,""))) | J67: =SUBSTITUTE(IF(LEN(I67)=0,Taostats_CSV!F67&" "&Taostats_CSV!J67,IF(I67="Cost","Extrinsic fee","")),"_"," ") -> fee Balances.transfer keep alive | K67: =TRIM(IF(LEN(Taostats_CSV!I67)>0,Taostats_CSV!I67,"")) -> 5012990-0005 | L67: =IF(Taostats_CSV!E67<>"TAO",IF(LEN(F67)>0,F67,IF(LEN(D67)>0,D67,0))*Taostats_CSV!P67,"") | M67: =IF(LEN(L67)>0,"USD","") | N67: =COUNTIF(Taostats_CSV!$X:$X,Taostats_CSV!$I67&N$1) -> 1 | O67: =COUNTIF(Taostats_CSV!$X:$X,Taostats_CSV!$I67&O$1) -> 1 | P67: =COUNTIF(Taostats_CSV!$X:$X,Taostats_CSV!$I67&P$1) -> 0 | Q67: =AND(O67<=1,N67<=1,P67<=1,O67+N67+P67>=2) -> TRUE | R67: =IF(LEN(K67)>0,COUNTIF($K$3:K67,K67),FALSE) -> 1 | S67: =IF(Taostats_CSV!A67=Taostats_CSV!$A$2,TRUE,Taostats_CSV!G67+Taostats_CSV!H67+Taostats_CSV!R67=0) -> FALSE | T67: =AND(NOT(S67),OR(NOT(Q67),R67=1)) -> TRUE | U67: {=AND(T67,OR(O67-N67>1,P67>1,ISERROR(A67:P67)))} -> FALSE | W67: =MATCH(K67&$W$2,Taostats_CSV!$X$3:$X$1167,0) -> 65 | X67: =VALUE(D67) -> 30 | Y67: =VALUE(F67) -> #VALUE! | Z67: =VALUE(H67) -> 0.000135263
A68: =MID(Taostats_CSV!C68,6,2)&"/"&MID(Taostats_CSV!C68,9,2)&"/"&LEFT(Taostats_CSV!C68,4)&" "&MID(Taostats_CSV!C68,12,8) -> 02/26/2025 18:31:36 | C68: =IF(Q68,OFFSET(Taostats_CSV!$E$1,MATCH(K68&D$1,Taostats_CSV!$X:$X,0)-1,0),IF(Taostats_CSV!F68="fee","",IF(VALUE(Taostats_CSV!G68)>0,Taostats_CSV!E68,""))) -> TAO | D68: =IF(Q68,OFFSET(Taostats_CSV!$G$1,MATCH(K68&D$1,Taostats_CSV!$X:$X,0)-1,0),IF(Taostats_CSV!F68="fee","",IF(VALUE(Taostats_CSV!G68)>0,Taostats_CSV!G68,""))) -> 30 | E68: =IF(AND(Q68,P68>0),OFFSET(Taostats_CSV!$E$1,MATCH(K68&F$1,Taostats_CSV!$X:$X,0)-1,0),IF(LEN(F68)>0,Taostats_CSV!E68,"")) | F68: =TRIM(IF(AND(Q68,P68>0),OFFSET(Taostats_CSV!$H$1,MATCH(K68&F$1,Taostats_CSV!$X:$X,0)-1,0),IF(LEN(Taostats_CSV!H68)>0,Taostats_CSV!H68,Taostats_CSV!R68))) | G68: =IF(AND(Q68,N68=1),OFFSET(Taostats_CSV!$E$1,MATCH(K68&H$1,Taostats_CSV!$X:$X,0)-1,0),IF(Taostats_CSV!F68="fee",Taostats_CSV!E68,"")) -> TAO | H68: =IF(AND(Q68,N68=1),OFFSET(Taostats_CSV!$G$1,MATCH(K68&H$1,Taostats_CSV!$X:$X,0)-1,0),IF(Taostats_CSV!F68="fee",Taostats_CSV!G68,"")) -> 0.000135263 | I68: =IF(AND(LEN(K68)=0,LEN(F68)>0),"Income",IF(AND(O68>0,P68>0,C68<>E68),"Trade",IF(AND(NOT(Q68),Taostats_CSV!F68="fee"),'READ ME'!$C$5,""))) | J68: =SUBSTITUTE(IF(LEN(I68)=0,Taostats_CSV!F68&" "&Taostats_CSV!J68,IF(I68="Cost","Extrinsic fee","")),"_"," ") -> transfer out 5HbnKZMzGk3GT3mpWZgKuQHq3CC8LeW2tbNq1FkBLQhzUX6L | K68: =TRIM(IF(LEN(Taostats_CSV!I68)>0,Taostats_CSV!I68,"")) -> 5012990-0005 | L68: =IF(Taostats_CSV!E68<>"TAO",IF(LEN(F68)>0,F68,IF(LEN(D68)>0,D68,0))*Taostats_CSV!P68,"") | M68: =IF(LEN(L68)>0,"USD","") | N68: =COUNTIF(Taostats_CSV!$X:$X,Taostats_CSV!$I68&N$1) -> 1 | O68: =COUNTIF(Taostats_CSV!$X:$X,Taostats_CSV!$I68&O$1) -> 1 | P68: =COUNTIF(Taostats_CSV!$X:$X,Taostats_CSV!$I68&P$1) -> 0 | Q68: =AND(O68<=1,N68<=1,P68<=1,O68+N68+P68>=2) -> TRUE | R68: =IF(LEN(K68)>0,COUNTIF($K$3:K68,K68),FALSE) -> 2 | S68: =IF(Taostats_CSV!A68=Taostats_CSV!$A$2,TRUE,Taostats_CSV!G68+Taostats_CSV!H68+Taostats_CSV!R68=0) -> FALSE | T68: =AND(NOT(S68),OR(NOT(Q68),R68=1)) -> FALSE | U68: {=AND(T68,OR(O68-N68>1,P68>1,ISERROR(A68:P68)))} -> FALSE | W68: =MATCH(K68&$W$2,Taostats_CSV!$X$3:$X$1167,0) -> 65 | X68: =VALUE(D68) -> 30 | Y68: =VALUE(F68) -> #VALUE! | Z68: =VALUE(H68) -> 0.000135263
A69: =MID(Taostats_CSV!C69,6,2)&"/"&MID(Taostats_CSV!C69,9,2)&"/"&LEFT(Taostats_CSV!C69,4)&" "&MID(Taostats_CSV!C69,12,8) -> 02/26/2025 18:34:48 | C69: =IF(Q69,OFFSET(Taostats_CSV!$E$1,MATCH(K69&D$1,Taostats_CSV!$X:$X,0)-1,0),IF(Taostats_CSV!F69="fee",IF(VALUE(Taostats_CSV!G69)>0,Taostats_CSV!E69,""),"")) -> TAO | D69: =IF(Q69,OFFSET(Taostats_CSV!$G$1,MATCH(K69&D$1,Taostats_CSV!$X:$X,0)-1,0),IF(Taostats_CSV!F69="fee",IF(VALUE(Taostats_CSV!G69)>0,Taostats_CSV!G69,""),"")) -> 5e-05 | E69: =IF(AND(Q69,P69>0),OFFSET(Taostats_CSV!$E$1,MATCH(K69&F$1,Taostats_CSV!$X:$X,0)-1,0),IF(LEN(F69)>0,Taostats_CSV!E69,"")) | F69: =TRIM(IF(AND(Q69,P69>0),OFFSET(Taostats_CSV!$H$1,MATCH(K69&F$1,Taostats_CSV!$X:$X,0)-1,0),IF(LEN(Taostats_CSV!H69)>0,Taostats_CSV!H69,Taostats_CSV!R69))) | G69: =IF(AND(Q69,N69=1),OFFSET(Taostats_CSV!$E$1,MATCH(K69&H$1,Taostats_CSV!$X:$X,0)-1,0),"") | H69: =IF(AND(Q69,N69=1),OFFSET(Taostats_CSV!$G$1,MATCH(K69&H$1,Taostats_CSV!$X:$X,0)-1,0),"") | I69: =IF(AND(LEN(K69)=0,LEN(F69)>0),"Income",IF(AND(O69>0,P69>0,C69<>E69),"Trade",IF(AND(NOT(Q69),Taostats_CSV!F69="fee"),'READ ME'!$C$5,""))) -> Merchant Payment | J69: =SUBSTITUTE(IF(LEN(I69)=0,Taostats_CSV!F69&" "&Taostats_CSV!J69,IF(I69="Cost","Extrinsic fee","")),"_"," ") | K69: =TRIM(IF(LEN(Taostats_CSV!I69)>0,Taostats_CSV!I69,"")) -> 5013006-0007 | L69: =IF(Taostats_CSV!E69<>"TAO",IF(LEN(F69)>0,F69,IF(LEN(D69)>0,D69,0))*Taostats_CSV!P69,"") | M69: =IF(LEN(L69)>0,"USD","") | N69: =COUNTIF(Taostats_CSV!$X:$X,Taostats_CSV!$I69&N$1) -> 1 | O69: =COUNTIF(Taostats_CSV!$X:$X,Taostats_CSV!$I69&O$1) -> 0 | P69: =COUNTIF(Taostats_CSV!$X:$X,Taostats_CSV!$I69&P$1) -> 0 | Q69: =AND(O69<=1,N69<=1,P69<=1,O69+N69+P69>=2) -> FALSE | R69: =IF(LEN(K69)>0,COUNTIF($K$3:K69,K69),FALSE) -> 1 | S69: =IF(Taostats_CSV!A69=Taostats_CSV!$A$2,TRUE,Taostats_CSV!G69+Taostats_CSV!H69+Taostats_CSV!R69=0) -> FALSE | T69: =AND(NOT(S69),OR(NOT(Q69),R69=1)) -> TRUE | U69: {=AND(T69,OR(O69-N69>1,P69>1,ISERROR(A69:P69)))} -> FALSE | W69: =MATCH(K69&$W$2,Taostats_CSV!$X$3:$X$1167,0) -> 67 | X69: =VALUE(D69) -> 5e-05 | Y69: =VALUE(F69) -> #VALUE! | Z69: =VALUE(H69) -> #VALUE!
A70: =MID(Taostats_CSV!C70,6,2)&"/"&MID(Taostats_CSV!C70,9,2)&"/"&LEFT(Taostats_CSV!C70,4)&" "&MID(Taostats_CSV!C70,12,8) -> 02/26/2025 18:35:24 | C70: =IF(Q70,OFFSET(Taostats_CSV!$E$1,MATCH(K70&D$1,Taostats_CSV!$X:$X,0)-1,0),IF(Taostats_CSV!F70="fee",IF(VALUE(Taostats_CSV!G70)>0,Taostats_CSV!E70,""),"")) -> TAO | D70: =IF(Q70,OFFSET(Taostats_CSV!$G$1,MATCH(K70&D$1,Taostats_CSV!$X:$X,0)-1,0),IF(Taostats_CSV!F70="fee",IF(VALUE(Taostats_CSV!G70)>0,Taostats_CSV!G70,""),"")) -> 22.78 | E70: =IF(AND(Q70,P70>0),OFFSET(Taostats_CSV!$E$1,MATCH(K70&F$1,Taostats_CSV!$X:$X,0)-1,0),IF(LEN(F70)>0,Taostats_CSV!E70,"")) | F70: =TRIM(IF(AND(Q70,P70>0),OFFSET(Taostats_CSV!$H$1,MATCH(K70&F$1,Taostats_CSV!$X:$X,0)-1,0),IF(LEN(Taostats_CSV!H70)>0,Taostats_CSV!H70,Taostats_CSV!R70))) | G70: =IF(AND(Q70,N70=1),OFFSET(Taostats_CSV!$E$1,MATCH(K70&H$1,Taostats_CSV!$X:$X,0)-1,0),"") -> TAO | H70: =IF(AND(Q70,N70=1),OFFSET(Taostats_CSV!$G$1,MATCH(K70&H$1,Taostats_CSV!$X:$X,0)-1,0),"") -> 0.000135263 | I70: =IF(AND(LEN(K70)=0,LEN(F70)>0),"Income",IF(AND(O70>0,P70>0,C70<>E70),"Trade",IF(AND(NOT(Q70),Taostats_CSV!F70="fee"),'READ ME'!$C$5,""))) | J70: =SUBSTITUTE(IF(LEN(I70)=0,Taostats_CSV!F70&" "&Taostats_CSV!J70,IF(I70="Cost","Extrinsic fee","")),"_"," ") -> fee Balances.transfer keep alive | K70: =TRIM(IF(LEN(Taostats_CSV!I70)>0,Taostats_CSV!I70,"")) -> 5013009-0009 | L70: =IF(Taostats_CSV!E70<>"TAO",IF(LEN(F70)>0,F70,IF(LEN(D70)>0,D70,0))*Taostats_CSV!P70,"") | M70: =IF(LEN(L70)>0,"USD","") | N70: =COUNTIF(Taostats_CSV!$X:$X,Taostats_CSV!$I70&N$1) -> 1 | O70: =COUNTIF(Taostats_CSV!$X:$X,Taostats_CSV!$I70&O$1) -> 1 | P70: =COUNTIF(Taostats_CSV!$X:$X,Taostats_CSV!$I70&P$1) -> 0 | Q70: =AND(O70<=1,N70<=1,P70<=1,O70+N70+P70>=2) -> TRUE | R70: =IF(LEN(K70)>0,COUNTIF($K$3:K70,K70),FALSE) -> 1 | S70: =IF(Taostats_CSV!A70=Taostats_CSV!$A$2,TRUE,Taostats_CSV!G70+Taostats_CSV!H70+Taostats_CSV!R70=0) -> FALSE | T70: =AND(NOT(S70),OR(NOT(Q70),R70=1)) -> TRUE | U70: {=AND(T70,OR(O70-N70>1,P70>1,ISERROR(A70:P70)))} -> FALSE | W70: =MATCH(K70&$W$2,Taostats_CSV!$X$3:$X$1167,0) -> 68 | X70: =VALUE(D70) -> 22.78 | Y70: =VALUE(F70) -> #VALUE! | Z70: =VALUE(H70) -> 0.000135263
A71: =MID(Taostats_CSV!C71,6,2)&"/"&MID(Taostats_CSV!C71,9,2)&"/"&LEFT(Taostats_CSV!C71,4)&" "&MID(Taostats_CSV!C71,12,8) -> 02/26/2025 18:35:24 | C71: =IF(Q71,OFFSET(Taostats_CSV!$E$1,MATCH(K71&D$1,Taostats_CSV!$X:$X,0)-1,0),IF(Taostats_CSV!F71="fee","",IF(VALUE(Taostats_CSV!G71)>0,Taostats_CSV!E71,""))) -> TAO | D71: =IF(Q71,OFFSET(Taostats_CSV!$G$1,MATCH(K71&D$1,Taostats_CSV!$X:$X,0)-1,0),IF(Taostats_CSV!F71="fee","",IF(VALUE(Taostats_CSV!G71)>0,Taostats_CSV!G71,""))) -> 22.78 | E71: =IF(AND(Q71,P71>0),OFFSET(Taostats_CSV!$E$1,MATCH(K71&F$1,Taostats_CSV!$X:$X,0)-1,0),IF(LEN(F71)>0,Taostats_CSV!E71,"")) | F71: =TRIM(IF(AND(Q71,P71>0),OFFSET(Taostats_CSV!$H$1,MATCH(K71&F$1,Taostats_CSV!$X:$X,0)-1,0),IF(LEN(Taostats_CSV!H71)>0,Taostats_CSV!H71,Taostats_CSV!R71))) | G71: =IF(AND(Q71,N71=1),OFFSET(Taostats_CSV!$E$1,MATCH(K71&H$1,Taostats_CSV!$X:$X,0)-1,0),IF(Taostats_CSV!F71="fee",Taostats_CSV!E71,"")) -> TAO | H71: =IF(AND(Q71,N71=1),OFFSET(Taostats_CSV!$G$1,MATCH(K71&H$1,Taostats_CSV!$X:$X,0)-1,0),IF(Taostats_CSV!F71="fee",Taostats_CSV!G71,"")) -> 0.000135263 | I71: =IF(AND(LEN(K71)=0,LEN(F71)>0),"Income",IF(AND(O71>0,P71>0,C71<>E71),"Trade",IF(AND(NOT(Q71),Taostats_CSV!F71="fee"),'READ ME'!$C$5,""))) | J71: =SUBSTITUTE(IF(LEN(I71)=0,Taostats_CSV!F71&" "&Taostats_CSV!J71,IF(I71="Cost","Extrinsic fee","")),"_"," ") -> transfer out 5HbnKZMzGk3GT3mpWZgKuQHq3CC8LeW2tbNq1FkBLQhzUX6L | K71: =TRIM(IF(LEN(Taostats_CSV!I71)>0,Taostats_CSV!I71,"")) -> 5013009-0009 | L71: =IF(Taostats_CSV!E71<>"TAO",IF(LEN(F71)>0,F71,IF(LEN(D71)>0,D71,0))*Taostats_CSV!P71,"") | M71: =IF(LEN(L71)>0,"USD","") | N71: =COUNTIF(Taostats_CSV!$X:$X,Taostats_CSV!$I71&N$1) -> 1 | O71: =COUNTIF(Taostats_CSV!$X:$X,Taostats_CSV!$I71&O$1) -> 1 | P71: =COUNTIF(Taostats_CSV!$X:$X,Taostats_CSV!$I71&P$1) -> 0 | Q71: =AND(O71<=1,N71<=1,P71<=1,O71+N71+P71>=2) -> TRUE | R71: =IF(LEN(K71)>0,COUNTIF($K$3:K71,K71),FALSE) -> 2 | S71: =IF(Taostats_CSV!A71=Taostats_CSV!$A$2,TRUE,Taostats_CSV!G71+Taostats_CSV!H71+Taostats_CSV!R71=0) -> FALSE | T71: =AND(NOT(S71),OR(NOT(Q71),R71=1)) -> FALSE | U71: {=AND(T71,OR(O71-N71>1,P71>1,ISERROR(A71:P71)))} -> FALSE | W71: =MATCH(K71&$W$2,Taostats_CSV!$X$3:$X$1167,0) -> 68 | X71: =VALUE(D71) -> 22.78 | Y71: =VALUE(F71) -> #VALUE! | Z71: =VALUE(H71) -> 0.000135263
A72: =MID(Taostats_CSV!C72,6,2)&"/"&MID(Taostats_CSV!C72,9,2)&"/"&LEFT(Taostats_CSV!C72,4)&" "&MID(Taostats_CSV!C72,12,8) -> 02/26/2025 23:59:48 | C72: =IF(Q72,OFFSET(Taostats_CSV!$E$1,MATCH(K72&D$1,Taostats_CSV!$X:$X,0)-1,0),IF(Taostats_CSV!F72="fee",IF(VALUE(Taostats_CSV!G72)>0,Taostats_CSV!E72,""),"")) | D72: =IF(Q72,OFFSET(Taostats_CSV!$G$1,MATCH(K72&D$1,Taostats_CSV!$X:$X,0)-1,0),IF(Taostats_CSV!F72="fee",IF(VALUE(Taostats_CSV!G72)>0,Taostats_CSV!G72,""),"")) | E72: =IF(AND(Q72,P72>0),OFFSET(Taostats_CSV!$E$1,MATCH(K72&F$1,Taostats_CSV!$X:$X,0)-1,0),IF(LEN(F72)>0,Taostats_CSV!E72,"")) -> TAO | F72: =TRIM(IF(AND(Q72,P72>0),OFFSET(Taostats_CSV!$H$1,MATCH(K72&F$1,Taostats_CSV!$X:$X,0)-1,0),IF(LEN(Taostats_CSV!H72)>0,Taostats_CSV!H72,Taostats_CSV!R72))) -> 0.12501014 | G72: =IF(AND(Q72,N72=1),OFFSET(Taostats_CSV!$E$1,MATCH(K72&H$1,Taostats_CSV!$X:$X,0)-1,0),"") | H72: =IF(AND(Q72,N72=1),OFFSET(Taostats_CSV!$G$1,MATCH(K72&H$1,Taostats_CSV!$X:$X,0)-1,0),"") | I72: =IF(AND(LEN(K72)=0,LEN(F72)>0),"Income",IF(AND(O72>0,P72>0,C72<>E72),"Trade",IF(AND(NOT(Q72),Taostats_CSV!F72="fee"),'READ ME'!$C$5,""))) -> Income | J72: =SUBSTITUTE(IF(LEN(I72)=0,Taostats_CSV!F72&" "&Taostats_CSV!J72,IF(I72="Cost","Extrinsic fee","")),"_"," ") | K72: =TRIM(IF(LEN(Taostats_CSV!I72)>0,Taostats_CSV!I72,"")) | L72: =IF(Taostats_CSV!E72<>"TAO",IF(LEN(F72)>0,F72,IF(LEN(D72)>0,D72,0))*Taostats_CSV!P72,"") | M72: =IF(LEN(L72)>0,"USD","") | N72: =COUNTIF(Taostats_CSV!$X:$X,Taostats_CSV!$I72&N$1) -> 0 | O72: =COUNTIF(Taostats_CSV!$X:$X,Taostats_CSV!$I72&O$1) -> 0 | P72: =COUNTIF(Taostats_CSV!$X:$X,Taostats_CSV!$I72&P$1) -> 0 | Q72: =AND(O72<=1,N72<=1,P72<=1,O72+N72+P72>=2) -> FALSE | R72: =IF(LEN(K72)>0,COUNTIF($K$3:K72,K72),FALSE) -> FALSE | S72: =IF(Taostats_CSV!A72=Taostats_CSV!$A$2,TRUE,Taostats_CSV!G72+Taostats_CSV!H72+Taostats_CSV!R72=0) -> FALSE | T72: =AND(NOT(S72),OR(NOT(Q72),R72=1)) -> TRUE | U72: {=AND(T72,OR(O72-N72>1,P72>1,ISERROR(A72:P72)))} -> FALSE | W72: =MATCH(K72&$W$2,Taostats_CSV!$X$3:$X$1167,0) -> #N/A | X72: =VALUE(D72) -> #VALUE! | Y72: =VALUE(F72) -> 0.12501014 | Z72: =VALUE(H72) -> #VALUE!
A73: =MID(Taostats_CSV!C73,6,2)&"/"&MID(Taostats_CSV!C73,9,2)&"/"&LEFT(Taostats_CSV!C73,4)&" "&MID(Taostats_CSV!C73,12,8) -> 02/27/2025 23:59:48 | C73: =IF(Q73,OFFSET(Taostats_CSV!$E$1,MATCH(K73&D$1,Taostats_CSV!$X:$X,0)-1,0),IF(Taostats_CSV!F73="fee",IF(VALUE(Taostats_CSV!G73)>0,Taostats_CSV!E73,""),"")) | D73: =IF(Q73,OFFSET(Taostats_CSV!$G$1,MATCH(K73&D$1,Taostats_CSV!$X:$X,0)-1,0),IF(Taostats_CSV!F73="fee",IF(VALUE(Taostats_CSV!G73)>0,Taostats_CSV!G73,""),"")) | E73: =IF(AND(Q73,P73>0),OFFSET(Taostats_CSV!$E$1,MATCH(K73&F$1,Taostats_CSV!$X:$X,0)-1,0),IF(LEN(F73)>0,Taostats_CSV!E73,"")) -> TAO | F73: =TRIM(IF(AND(Q73,P73>0),OFFSET(Taostats_CSV!$H$1,MATCH(K73&F$1,Taostats_CSV!$X:$X,0)-1,0),IF(LEN(Taostats_CSV!H73)>0,Taostats_CSV!H73,Taostats_CSV!R73))) -> 0.097794089 | G73: =IF(AND(Q73,N73=1),OFFSET(Taostats_CSV!$E$1,MATCH(K73&H$1,Taostats_CSV!$X:$X,0)-1,0),"") | H73: =IF(AND(Q73,N73=1),OFFSET(Taostats_CSV!$G$1,MATCH(K73&H$1,Taostats_CSV!$X:$X,0)-1,0),"") | I73: =IF(AND(LEN(K73)=0,LEN(F73)>0),"Income",IF(AND(O73>0,P73>0,C73<>E73),"Trade",IF(AND(NOT(Q73),Taostats_CSV!F73="fee"),'READ ME'!$C$5,""))) -> Income | J73: =SUBSTITUTE(IF(LEN(I73)=0,Taostats_CSV!F73&" "&Taostats_CSV!J73,IF(I73="Cost","Extrinsic fee","")),"_"," ") | K73: =TRIM(IF(LEN(Taostats_CSV!I73)>0,Taostats_CSV!I73,"")) | L73: =IF(Taostats_CSV!E73<>"TAO",IF(LEN(F73)>0,F73,IF(LEN(D73)>0,D73,0))*Taostats_CSV!P73,"") | M73: =IF(LEN(L73)>0,"USD","") | N73: =COUNTIF(Taostats_CSV!$X:$X,Taostats_CSV!$I73&N$1) -> 0 | O73: =COUNTIF(Taostats_CSV!$X:$X,Taostats_CSV!$I73&O$1) -> 0 | P73: =COUNTIF(Taostats_CSV!$X:$X,Taostats_CSV!$I73&P$1) -> 0 | Q73: =AND(O73<=1,N73<=1,P73<=1,O73+N73+P73>=2) -> FALSE | R73: =IF(LEN(K73)>0,COUNTIF($K$3:K73,K73),FALSE) -> FALSE | S73: =IF(Taostats_CSV!A73=Taostats_CSV!$A$2,TRUE,Taostats_CSV!G73+Taostats_CSV!H73+Taostats_CSV!R73=0) -> FALSE | T73: =AND(NOT(S73),OR(NOT(Q73),R73=1)) -> TRUE | U73: {=AND(T73,OR(O73-N73>1,P73>1,ISERROR(A73:P73)))} -> FALSE | W73: =MATCH(K73&$W$2,Taostats_CSV!$X$3:$X$1167,0) -> #N/A | X73: =VALUE(D73) -> #VALUE! | Y73: =VALUE(F73) -> 0.097794089 | Z73: =VALUE(H73) -> #VALUE!
A74: =MID(Taostats_CSV!C74,6,2)&"/"&MID(Taostats_CSV!C74,9,2)&"/"&LEFT(Taostats_CSV!C74,4)&" "&MID(Taostats_CSV!C74,12,8) -> 02/28/2025 23:59:48 | C74: =IF(Q74,OFFSET(Taostats_CSV!$E$1,MATCH(K74&D$1,Taostats_CSV!$X:$X,0)-1,0),IF(Taostats_CSV!F74="fee",IF(VALUE(Taostats_CSV!G74)>0,Taostats_CSV!E74,""),"")) | D74: =IF(Q74,OFFSET(Taostats_CSV!$G$1,MATCH(K74&D$1,Taostats_CSV!$X:$X,0)-1,0),IF(Taostats_CSV!F74="fee",IF(VALUE(Taostats_CSV!G74)>0,Taostats_CSV!G74,""),"")) | E74: =IF(AND(Q74,P74>0),OFFSET(Taostats_CSV!$E$1,MATCH(K74&F$1,Taostats_CSV!$X:$X,0)-1,0),IF(LEN(F74)>0,Taostats_CSV!E74,"")) -> TAO | F74: =TRIM(IF(AND(Q74,P74>0),OFFSET(Taostats_CSV!$H$1,MATCH(K74&F$1,Taostats_CSV!$X:$X,0)-1,0),IF(LEN(Taostats_CSV!H74)>0,Taostats_CSV!H74,Taostats_CSV!R74))) -> 0.09431049 | G74: =IF(AND(Q74,N74=1),OFFSET(Taostats_CSV!$E$1,MATCH(K74&H$1,Taostats_CSV!$X:$X,0)-1,0),"") | H74: =IF(AND(Q74,N74=1),OFFSET(Taostats_CSV!$G$1,MATCH(K74&H$1,Taostats_CSV!$X:$X,0)-1,0),"") | I74: =IF(AND(LEN(K74)=0,LEN(F74)>0),"Income",IF(AND(O74>0,P74>0,C74<>E74),"Trade",IF(AND(NOT(Q74),Taostats_CSV!F74="fee"),'READ ME'!$C$5,""))) -> Income | J74: =SUBSTITUTE(IF(LEN(I74)=0,Taostats_CSV!F74&" "&Taostats_CSV!J74,IF(I74="Cost","Extrinsic fee","")),"_"," ") | K74: =TRIM(IF(LEN(Taostats_CSV!I74)>0,Taostats_CSV!I74,"")) | L74: =IF(Taostats_CSV!E74<>"TAO",IF(LEN(F74)>0,F74,IF(LEN(D74)>0,D74,0))*Taostats_CSV!P74,"") | M74: =IF(LEN(L74)>0,"USD","") | N74: =COUNTIF(Taostats_CSV!$X:$X,Taostats_CSV!$I74&N$1) -> 0 | O74: =COUNTIF(Taostats_CSV!$X:$X,Taostats_CSV!$I74&O$1) -> 0 | P74: =COUNTIF(Taostats_CSV!$X:$X,Taostats_CSV!$I74&P$1) -> 0 | Q74: =AND(O74<=1,N74<=1,P74<=1,O74+N74+P74>=2) -> FALSE | R74: =IF(LEN(K74)>0,COUNTIF($K$3:K74,K74),FALSE) -> FALSE | S74: =IF(Taostats_CSV!A74=Taostats_CSV!$A$2,TRUE,Taostats_CSV!G74+Taostats_CSV!H74+Taostats_CSV!R74=0) -> FALSE | T74: =AND(NOT(S74),OR(NOT(Q74),R74=1)) -> TRUE | U74: {=AND(T74,OR(O74-N74>1,P74>1,ISERROR(A74:P74)))} -> FALSE | W74: =MATCH(K74&$W$2,Taostats_CSV!$X$3:$X$1167,0) -> #N/A | X74: =VALUE(D74) -> #VALUE! | Y74: =VALUE(F74) -> 0.09431049 | Z74: =VALUE(H74) -> #VALUE!
A75: =MID(Taostats_CSV!C75,6,2)&"/"&MID(Taostats_CSV!C75,9,2)&"/"&LEFT(Taostats_CSV!C75,4)&" "&MID(Taostats_CSV!C75,12,8) -> 03/01/2025 23:59:48 | C75: =IF(Q75,OFFSET(Taostats_CSV!$E$1,MATCH(K75&D$1,Taostats_CSV!$X:$X,0)-1,0),IF(Taostats_CSV!F75="fee",IF(VALUE(Taostats_CSV!G75)>0,Taostats_CSV!E75,""),"")) | D75: =IF(Q75,OFFSET(Taostats_CSV!$G$1,MATCH(K75&D$1,Taostats_CSV!$X:$X,0)-1,0),IF(Taostats_CSV!F75="fee",IF(VALUE(Taostats_CSV!G75)>0,Taostats_CSV!G75,""),"")) | E75: =IF(AND(Q75,P75>0),OFFSET(Taostats_CSV!$E$1,MATCH(K75&F$1,Taostats_CSV!$X:$X,0)-1,0),IF(LEN(F75)>0,Taostats_CSV!E75,"")) -> TAO | F75: =TRIM(IF(AND(Q75,P75>0),OFFSET(Taostats_CSV!$H$1,MATCH(K75&F$1,Taostats_CSV!$X:$X,0)-1,0),IF(LEN(Taostats_CSV!H75)>0,Taostats_CSV!H75,Taostats_CSV!R75))) -> 0.101545834 | G75: =IF(AND(Q75,N75=1),OFFSET(Taostats_CSV!$E$1,MATCH(K75&H$1,Taostats_CSV!$X:$X,0)-1,0),"") | H75: =IF(AND(Q75,N75=1),OFFSET(Taostats_CSV!$G$1,MATCH(K75&H$1,Taostats_CSV!$X:$X,0)-1,0),"") | I75: =IF(AND(LEN(K75)=0,LEN(F75)>0),"Income",IF(AND(O75>0,P75>0,C75<>E75),"Trade",IF(AND(NOT(Q75),Taostats_CSV!F75="fee"),'READ ME'!$C$5,""))) -> Income | J75: =SUBSTITUTE(IF(LEN(I75)=0,Taostats_CSV!F75&" "&Taostats_CSV!J75,IF(I75="Cost","Extrinsic fee","")),"_"," ") | K75: =TRIM(IF(LEN(Taostats_CSV!I75)>0,Taostats_CSV!I75,"")) | L75: =IF(Taostats_CSV!E75<>"TAO",IF(LEN(F75)>0,F75,IF(LEN(D75)>0,D75,0))*Taostats_CSV!P75,"") | M75: =IF(LEN(L75)>0,"USD","") | N75: =COUNTIF(Taostats_CSV!$X:$X,Taostats_CSV!$I75&N$1) -> 0 | O75: =COUNTIF(Taostats_CSV!$X:$X,Taostats_CSV!$I75&O$1) -> 0 | P75: =COUNTIF(Taostats_CSV!$X:$X,Taostats_CSV!$I75&P$1) -> 0 | Q75: =AND(O75<=1,N75<=1,P75<=1,O75+N75+P75>=2) -> FALSE | R75: =IF(LEN(K75)>0,COUNTIF($K$3:K75,K75),FALSE) -> FALSE | S75: =IF(Taostats_CSV!A75=Taostats_CSV!$A$2,TRUE,Taostats_CSV!G75+Taostats_CSV!H75+Taostats_CSV!R75=0) -> FALSE | T75: =AND(NOT(S75),OR(NOT(Q75),R75=1)) -> TRUE | U75: {=AND(T75,OR(O75-N75>1,P75>1,ISERROR(A75:P75)))} -> FALSE | W75: =MATCH(K75&$W$2,Taostats_CSV!$X$3:$X$1167,0) -> #N/A | X75: =VALUE(D75) -> #VALUE! | Y75: =VALUE(F75) -> 0.10154583 | Z75: =VALUE(H75) -> #VALUE!
A76: =MID(Taostats_CSV!C76,6,2)&"/"&MID(Taostats_CSV!C76,9,2)&"/"&LEFT(Taostats_CSV!C76,4)&" "&MID(Taostats_CSV!C76,12,8) -> 03/02/2025 23:59:48 | C76: =IF(Q76,OFFSET(Taostats_CSV!$E$1,MATCH(K76&D$1,Taostats_CSV!$X:$X,0)-1,0),IF(Taostats_CSV!F76="fee",IF(VALUE(Taostats_CSV!G76)>0,Taostats_CSV!E76,""),"")) | D76: =IF(Q76,OFFSET(Taostats_CSV!$G$1,MATCH(K76&D$1,Taostats_CSV!$X:$X,0)-1,0),IF(Taostats_CSV!F76="fee",IF(VALUE(Taostats_CSV!G76)>0,Taostats_CSV!G76,""),"")) | E76: =IF(AND(Q76,P76>0),OFFSET(Taostats_CSV!$E$1,MATCH(K76&F$1,Taostats_CSV!$X:$X,0)-1,0),IF(LEN(F76)>0,Taostats_CSV!E76,"")) -> TAO | F76: =TRIM(IF(AND(Q76,P76>0),OFFSET(Taostats_CSV!$H$1,MATCH(K76&F$1,Taostats_CSV!$X:$X,0)-1,0),IF(LEN(Taostats_CSV!H76)>0,Taostats_CSV!H76,Taostats_CSV!R76))) -> 0.100197688 | G76: =IF(AND(Q76,N76=1),OFFSET(Taostats_CSV!$E$1,MATCH(K76&H$1,Taostats_CSV!$X:$X,0)-1,0),"") | H76: =IF(AND(Q76,N76=1),OFFSET(Taostats_CSV!$G$1,MATCH(K76&H$1,Taostats_CSV!$X:$X,0)-1,0),"") | I76: =IF(AND(LEN(K76)=0,LEN(F76)>0),"Income",IF(AND(O76>0,P76>0,C76<>E76),"Trade",IF(AND(NOT(Q76),Taostats_CSV!F76="fee"),'READ ME'!$C$5,""))) -> Income | J76: =SUBSTITUTE(IF(LEN(I76)=0,Taostats_CSV!F76&" "&Taostats_CSV!J76,IF(I76="Cost","Extrinsic fee","")),"_"," ") | K76: =TRIM(IF(LEN(Taostats_CSV!I76)>0,Taostats_CSV!I76,"")) | L76: =IF(Taostats_CSV!E76<>"TAO",IF(LEN(F76)>0,F76,IF(LEN(D76)>0,D76,0))*Taostats_CSV!P76,"") | M76: =IF(LEN(L76)>0,"USD","") | N76: =COUNTIF(Taostats_CSV!$X:$X,Taostats_CSV!$I76&N$1) -> 0 | O76: =COUNTIF(Taostats_CSV!$X:$X,Taostats_CSV!$I76&O$1) -> 0 | P76: =COUNTIF(Taostats_CSV!$X:$X,Taostats_CSV!$I76&P$1) -> 0 | Q76: =AND(O76<=1,N76<=1,P76<=1,O76+N76+P76>=2) -> FALSE | R76: =IF(LEN(K76)>0,COUNTIF($K$3:K76,K76),FALSE) -> FALSE | S76: =IF(Taostats_CSV!A76=Taostats_CSV!$A$2,TRUE,Taostats_CSV!G76+Taostats_CSV!H76+Taostats_CSV!R76=0) -> FALSE | T76: =AND(NOT(S76),OR(NOT(Q76),R76=1)) -> TRUE | U76: {=AND(T76,OR(O76-N76>1,P76>1,ISERROR(A76:P76)))} -> FALSE | W76: =MATCH(K76&$W$2,Taostats_CSV!$X$3:$X$1167,0) -> #N/A | X76: =VALUE(D76) -> #VALUE! | Y76: =VALUE(F76) -> 0.10019769 | Z76: =VALUE(H76) -> #VALUE!
A77: =MID(Taostats_CSV!C77,6,2)&"/"&MID(Taostats_CSV!C77,9,2)&"/"&LEFT(Taostats_CSV!C77,4)&" "&MID(Taostats_CSV!C77,12,8) -> 03/03/2025 23:59:48 | C77: =IF(Q77,OFFSET(Taostats_CSV!$E$1,MATCH(K77&D$1,Taostats_CSV!$X:$X,0)-1,0),IF(Taostats_CSV!F77="fee",IF(VALUE(Taostats_CSV!G77)>0,Taostats_CSV!E77,""),"")) | D77: =IF(Q77,OFFSET(Taostats_CSV!$G$1,MATCH(K77&D$1,Taostats_CSV!$X:$X,0)-1,0),IF(Taostats_CSV!F77="fee",IF(VALUE(Taostats_CSV!G77)>0,Taostats_CSV!G77,""),"")) | E77: =IF(AND(Q77,P77>0),OFFSET(Taostats_CSV!$E$1,MATCH(K77&F$1,Taostats_CSV!$X:$X,0)-1,0),IF(LEN(F77)>0,Taostats_CSV!E77,"")) -> TAO | F77: =TRIM(IF(AND(Q77,P77>0),OFFSET(Taostats_CSV!$H$1,MATCH(K77&F$1,Taostats_CSV!$X:$X,0)-1,0),IF(LEN(Taostats_CSV!H77)>0,Taostats_CSV!H77,Taostats_CSV!R77))) -> 0.107518346 | G77: =IF(AND(Q77,N77=1),OFFSET(Taostats_CSV!$E$1,MATCH(K77&H$1,Taostats_CSV!$X:$X,0)-1,0),"") | H77: =IF(AND(Q77,N77=1),OFFSET(Taostats_CSV!$G$1,MATCH(K77&H$1,Taostats_CSV!$X:$X,0)-1,0),"") | I77: =IF(AND(LEN(K77)=0,LEN(F77)>0),"Income",IF(AND(O77>0,P77>0,C77<>E77),"Trade",IF(AND(NOT(Q77),Taostats_CSV!F77="fee"),'READ ME'!$C$5,""))) -> Income | J77: =SUBSTITUTE(IF(LEN(I77)=0,Taostats_CSV!F77&" "&Taostats_CSV!J77,IF(I77="Cost","Extrinsic fee","")),"_"," ") | K77: =TRIM(IF(LEN(Taostats_CSV!I77)>0,Taostats_CSV!I77,"")) | L77: =IF(Taostats_CSV!E77<>"TAO",IF(LEN(F77)>0,F77,IF(LEN(D77)>0,D77,0))*Taostats_CSV!P77,"") | M77: =IF(LEN(L77)>0,"USD","") | N77: =COUNTIF(Taostats_CSV!$X:$X,Taostats_CSV!$I77&N$1) -> 0 | O77: =COUNTIF(Taostats_CSV!$X:$X,Taostats_CSV!$I77&O$1) -> 0 | P77: =COUNTIF(Taostats_CSV!$X:$X,Taostats_CSV!$I77&P$1) -> 0 | Q77: =AND(O77<=1,N77<=1,P77<=1,O77+N77+P77>=2) -> FALSE | R77: =IF(LEN(K77)>0,COUNTIF($K$3:K77,K77),FALSE) -> FALSE | S77: =IF(Taostats_CSV!A77=Taostats_CSV!$A$2,TRUE,Taostats_CSV!G77+Taostats_CSV!H77+Taostats_CSV!R77=0) -> FALSE | T77: =AND(NOT(S77),OR(NOT(Q77),R77=1)) -> TRUE | U77: {=AND(T77,OR(O77-N77>1,P77>1,ISERROR(A77:P77)))} -> FALSE | W77: =MATCH(K77&$W$2,Taostats_CSV!$X$3:$X$1167,0) -> #N/A | X77: =VALUE(D77) -> #VALUE! | Y77: =VALUE(F77) -> 0.10751835 | Z77: =VALUE(H77) -> #VALUE!
A78: =MID(Taostats_CSV!C78,6,2)&"/"&MID(Taostats_CSV!C78,9,2)&"/"&LEFT(Taostats_CSV!C78,4)&" "&MID(Taostats_CSV!C78,12,8) -> 03/04/2025 16:46:36 | C78: =IF(Q78,OFFSET(Taostats_CSV!$E$1,MATCH(K78&D$1,Taostats_CSV!$X:$X,0)-1,0),IF(Taostats_CSV!F78="fee",IF(VALUE(Taostats_CSV!G78)>0,Taostats_CSV!E78,""),"")) -> TAO | D78: =IF(Q78,OFFSET(Taostats_CSV!$G$1,MATCH(K78&D$1,Taostats_CSV!$X:$X,0)-1,0),IF(Taostats_CSV!F78="fee",IF(VALUE(Taostats_CSV!G78)>0,Taostats_CSV!G78,""),"")) -> 5e-05 | E78: =IF(AND(Q78,P78>0),OFFSET(Taostats_CSV!$E$1,MATCH(K78&F$1,Taostats_CSV!$X:$X,0)-1,0),IF(LEN(F78)>0,Taostats_CSV!E78,"")) | F78: =TRIM(IF(AND(Q78,P78>0),OFFSET(Taostats_CSV!$H$1,MATCH(K78&F$1,Taostats_CSV!$X:$X,0)-1,0),IF(LEN(Taostats_CSV!H78)>0,Taostats_CSV!H78,Taostats_CSV!R78))) | G78: =IF(AND(Q78,N78=1),OFFSET(Taostats_CSV!$E$1,MATCH(K78&H$1,Taostats_CSV!$X:$X,0)-1,0),"") | H78: =IF(AND(Q78,N78=1),OFFSET(Taostats_CSV!$G$1,MATCH(K78&H$1,Taostats_CSV!$X:$X,0)-1,0),"") | I78: =IF(AND(LEN(K78)=0,LEN(F78)>0),"Income",IF(AND(O78>0,P78>0,C78<>E78),"Trade",IF(AND(NOT(Q78),Taostats_CSV!F78="fee"),'READ ME'!$C$5,""))) -> Merchant Payment | J78: =SUBSTITUTE(IF(LEN(I78)=0,Taostats_CSV!F78&" "&Taostats_CSV!J78,IF(I78="Cost","Extrinsic fee","")),"_"," ") | K78: =TRIM(IF(LEN(Taostats_CSV!I78)>0,Taostats_CSV!I78,"")) -> 5055665-0003 | L78: =IF(Taostats_CSV!E78<>"TAO",IF(LEN(F78)>0,F78,IF(LEN(D78)>0,D78,0))*Taostats_CSV!P78,"") | M78: =IF(LEN(L78)>0,"USD","") | N78: =COUNTIF(Taostats_CSV!$X:$X,Taostats_CSV!$I78&N$1) -> 1 | O78: =COUNTIF(Taostats_CSV!$X:$X,Taostats_CSV!$I78&O$1) -> 0 | P78: =COUNTIF(Taostats_CSV!$X:$X,Taostats_CSV!$I78&P$1) -> 0 | Q78: =AND(O78<=1,N78<=1,P78<=1,O78+N78+P78>=2) -> FALSE | R78: =IF(LEN(K78)>0,COUNTIF($K$3:K78,K78),FALSE) -> 1 | S78: =IF(Taostats_CSV!A78=Taostats_CSV!$A$2,TRUE,Taostats_CSV!G78+Taostats_CSV!H78+Taostats_CSV!R78=0) -> FALSE | T78: =AND(NOT(S78),OR(NOT(Q78),R78=1)) -> TRUE | U78: {=AND(T78,OR(O78-N78>1,P78>1,ISERROR(A78:P78)))} -> FALSE | W78: =MATCH(K78&$W$2,Taostats_CSV!$X$3:$X$1167,0) -> 76 | X78: =VALUE(D78) -> 5e-05 | Y78: =VALUE(F78) -> #VALUE! | Z78: =VALUE(H78) -> #VALUE!
A79: =MID(Taostats_CSV!C79,6,2)&"/"&MID(Taostats_CSV!C79,9,2)&"/"&LEFT(Taostats_CSV!C79,4)&" "&MID(Taostats_CSV!C79,12,8) -> 03/04/2025 16:47:36 | C79: =IF(Q79,OFFSET(Taostats_CSV!$E$1,MATCH(K79&D$1,Taostats_CSV!$X:$X,0)-1,0),IF(Taostats_CSV!F79="fee",IF(VALUE(Taostats_CSV!G79)>0,Taostats_CSV!E79,""),"")) -> TAO | D79: =IF(Q79,OFFSET(Taostats_CSV!$G$1,MATCH(K79&D$1,Taostats_CSV!$X:$X,0)-1,0),IF(Taostats_CSV!F79="fee",IF(VALUE(Taostats_CSV!G79)>0,Taostats_CSV!G79,""),"")) -> 50 | E79: =IF(AND(Q79,P79>0),OFFSET(Taostats_CSV!$E$1,MATCH(K79&F$1,Taostats_CSV!$X:$X,0)-1,0),IF(LEN(F79)>0,Taostats_CSV!E79,"")) | F79: =TRIM(IF(AND(Q79,P79>0),OFFSET(Taostats_CSV!$H$1,MATCH(K79&F$1,Taostats_CSV!$X:$X,0)-1,0),IF(LEN(Taostats_CSV!H79)>0,Taostats_CSV!H79,Taostats_CSV!R79))) | G79: =IF(AND(Q79,N79=1),OFFSET(Taostats_CSV!$E$1,MATCH(K79&H$1,Taostats_CSV!$X:$X,0)-1,0),"") -> TAO | H79: =IF(AND(Q79,N79=1),OFFSET(Taostats_CSV!$G$1,MATCH(K79&H$1,Taostats_CSV!$X:$X,0)-1,0),"") -> 0.000135263 | I79: =IF(AND(LEN(K79)=0,LEN(F79)>0),"Income",IF(AND(O79>0,P79>0,C79<>E79),"Trade",IF(AND(NOT(Q79),Taostats_CSV!F79="fee"),'READ ME'!$C$5,""))) | J79: =SUBSTITUTE(IF(LEN(I79)=0,Taostats_CSV!F79&" "&Taostats_CSV!J79,IF(I79="Cost","Extrinsic fee","")),"_"," ") -> fee Balances.transfer keep alive | K79: =TRIM(IF(LEN(Taostats_CSV!I79)>0,Taostats_CSV!I79,"")) -> 5055670-0007 | L79: =IF(Taostats_CSV!E79<>"TAO",IF(LEN(F79)>0,F79,IF(LEN(D79)>0,D79,0))*Taostats_CSV!P79,"") | M79: =IF(LEN(L79)>0,"USD","") | N79: =COUNTIF(Taostats_CSV!$X:$X,Taostats_CSV!$I79&N$1) -> 1 | O79: =COUNTIF(Taostats_CSV!$X:$X,Taostats_CSV!$I79&O$1) -> 1 | P79: =COUNTIF(Taostats_CSV!$X:$X,Taostats_CSV!$I79&P$1) -> 0 | Q79: =AND(O79<=1,N79<=1,P79<=1,O79+N79+P79>=2) -> TRUE | R79: =IF(LEN(K79)>0,COUNTIF($K$3:K79,K79),FALSE) -> 1 | S79: =IF(Taostats_CSV!A79=Taostats_CSV!$A$2,TRUE,Taostats_CSV!G79+Taostats_CSV!H79+Taostats_CSV!R79=0) -> FALSE | T79: =AND(NOT(S79),OR(NOT(Q79),R79=1)) -> TRUE | U79: {=AND(T79,OR(O79-N79>1,P79>1,ISERROR(A79:P79)))} -> FALSE | W79: =MATCH(K79&$W$2,Taostats_CSV!$X$3:$X$1167,0) -> 77 | X79: =VALUE(D79) -> 50 | Y79: =VALUE(F79) -> #VALUE! | Z79: =VALUE(H79) -> 0.000135263
A80: =MID(Taostats_CSV!C80,6,2)&"/"&MID(Taostats_CSV!C80,9,2)&"/"&LEFT(Taostats_CSV!C80,4)&" "&MID(Taostats_CSV!C80,12,8) -> 03/04/2025 16:47:36 | C80: =IF(Q80,OFFSET(Taostats_CSV!$E$1,MATCH(K80&D$1,Taostats_CSV!$X:$X,0)-1,0),IF(Taostats_CSV!F80="fee","",IF(VALUE(Taostats_CSV!G80)>0,Taostats_CSV!E80,""))) -> TAO | D80: =IF(Q80,OFFSET(Taostats_CSV!$G$1,MATCH(K80&D$1,Taostats_CSV!$X:$X,0)-1,0),IF(Taostats_CSV!F80="fee","",IF(VALUE(Taostats_CSV!G80)>0,Taostats_CSV!G80,""))) -> 50 | E80: =IF(AND(Q80,P80>0),OFFSET(Taostats_CSV!$E$1,MATCH(K80&F$1,Taostats_CSV!$X:$X,0)-1,0),IF(LEN(F80)>0,Taostats_CSV!E80,"")) | F80: =TRIM(IF(AND(Q80,P80>0),OFFSET(Taostats_CSV!$H$1,MATCH(K80&F$1,Taostats_CSV!$X:$X,0)-1,0),IF(LEN(Taostats_CSV!H80)>0,Taostats_CSV!H80,Taostats_CSV!R80))) | G80: =IF(AND(Q80,N80=1),OFFSET(Taostats_CSV!$E$1,MATCH(K80&H$1,Taostats_CSV!$X:$X,0)-1,0),IF(Taostats_CSV!F80="fee",Taostats_CSV!E80,"")) -> TAO | H80: =IF(AND(Q80,N80=1),OFFSET(Taostats_CSV!$G$1,MATCH(K80&H$1,Taostats_CSV!$X:$X,0)-1,0),IF(Taostats_CSV!F80="fee",Taostats_CSV!G80,"")) -> 0.000135263 | I80: =IF(AND(LEN(K80)=0,LEN(F80)>0),"Income",IF(AND(O80>0,P80>0,C80<>E80),"Trade",IF(AND(NOT(Q80),Taostats_CSV!F80="fee"),'READ ME'!$C$5,""))) | J80: =SUBSTITUTE(IF(LEN(I80)=0,Taostats_CSV!F80&" "&Taostats_CSV!J80,IF(I80="Cost","Extrinsic fee","")),"_"," ") -> transfer out 5HbnKZMzGk3GT3mpWZgKuQHq3CC8LeW2tbNq1FkBLQhzUX6L | K80: =TRIM(IF(LEN(Taostats_CSV!I80)>0,Taostats_CSV!I80,"")) -> 5055670-0007 | L80: =IF(Taostats_CSV!E80<>"TAO",IF(LEN(F80)>0,F80,IF(LEN(D80)>0,D80,0))*Taostats_CSV!P80,"") | M80: =IF(LEN(L80)>0,"USD","") | N80: =COUNTIF(Taostats_CSV!$X:$X,Taostats_CSV!$I80&N$1) -> 1 | O80: =COUNTIF(Taostats_CSV!$X:$X,Taostats_CSV!$I80&O$1) -> 1 | P80: =COUNTIF(Taostats_CSV!$X:$X,Taostats_CSV!$I80&P$1) -> 0 | Q80: =AND(O80<=1,N80<=1,P80<=1,O80+N80+P80>=2) -> TRUE | R80: =IF(LEN(K80)>0,COUNTIF($K$3:K80,K80),FALSE) -> 2 | S80: =IF(Taostats_CSV!A80=Taostats_CSV!$A$2,TRUE,Taostats_CSV!G80+Taostats_CSV!H80+Taostats_CSV!R80=0) -> FALSE | T80: =AND(NOT(S80),OR(NOT(Q80),R80=1)) -> FALSE | U80: {=AND(T80,OR(O80-N80>1,P80>1,ISERROR(A80:P80)))} -> FALSE | W80: =MATCH(K80&$W$2,Taostats_CSV!$X$3:$X$1167,0) -> 77 | X80: =VALUE(D80) -> 50 | Y80: =VALUE(F80) -> #VALUE! | Z80: =VALUE(H80) -> 0.000135263
A81: =MID(Taostats_CSV!C81,6,2)&"/"&MID(Taostats_CSV!C81,9,2)&"/"&LEFT(Taostats_CSV!C81,4)&" "&MID(Taostats_CSV!C81,12,8) -> 03/04/2025 16:57:12 | C81: =IF(Q81,OFFSET(Taostats_CSV!$E$1,MATCH(K81&D$1,Taostats_CSV!$X:$X,0)-1,0),IF(Taostats_CSV!F81="fee",IF(VALUE(Taostats_CSV!G81)>0,Taostats_CSV!E81,""),"")) -> TAO | D81: =IF(Q81,OFFSET(Taostats_CSV!$G$1,MATCH(K81&D$1,Taostats_CSV!$X:$X,0)-1,0),IF(Taostats_CSV!F81="fee",IF(VALUE(Taostats_CSV!G81)>0,Taostats_CSV!G81,""),"")) -> 50 | E81: =IF(AND(Q81,P81>0),OFFSET(Taostats_CSV!$E$1,MATCH(K81&F$1,Taostats_CSV!$X:$X,0)-1,0),IF(LEN(F81)>0,Taostats_CSV!E81,"")) | F81: =TRIM(IF(AND(Q81,P81>0),OFFSET(Taostats_CSV!$H$1,MATCH(K81&F$1,Taostats_CSV!$X:$X,0)-1,0),IF(LEN(Taostats_CSV!H81)>0,Taostats_CSV!H81,Taostats_CSV!R81))) | G81: =IF(AND(Q81,N81=1),OFFSET(Taostats_CSV!$E$1,MATCH(K81&H$1,Taostats_CSV!$X:$X,0)-1,0),"") -> TAO | H81: =IF(AND(Q81,N81=1),OFFSET(Taostats_CSV!$G$1,MATCH(K81&H$1,Taostats_CSV!$X:$X,0)-1,0),"") -> 0.000135263 | I81: =IF(AND(LEN(K81)=0,LEN(F81)>0),"Income",IF(AND(O81>0,P81>0,C81<>E81),"Trade",IF(AND(NOT(Q81),Taostats_CSV!F81="fee"),'READ ME'!$C$5,""))) | J81: =SUBSTITUTE(IF(LEN(I81)=0,Taostats_CSV!F81&" "&Taostats_CSV!J81,IF(I81="Cost","Extrinsic fee","")),"_"," ") -> fee Balances.transfer keep alive | K81: =TRIM(IF(LEN(Taostats_CSV!I81)>0,Taostats_CSV!I81,"")) -> 5055718-0007 | L81: =IF(Taostats_CSV!E81<>"TAO",IF(LEN(F81)>0,F81,IF(LEN(D81)>0,D81,0))*Taostats_CSV!P81,"") | M81: =IF(LEN(L81)>0,"USD","") | N81: =COUNTIF(Taostats_CSV!$X:$X,Taostats_CSV!$I81&N$1) -> 1 | O81: =COUNTIF(Taostats_CSV!$X:$X,Taostats_CSV!$I81&O$1) -> 1 | P81: =COUNTIF(Taostats_CSV!$X:$X,Taostats_CSV!$I81&P$1) -> 0 | Q81: =AND(O81<=1,N81<=1,P81<=1,O81+N81+P81>=2) -> TRUE | R81: =IF(LEN(K81)>0,COUNTIF($K$3:K81,K81),FALSE) -> 1 | S81: =IF(Taostats_CSV!A81=Taostats_CSV!$A$2,TRUE,Taostats_CSV!G81+Taostats_CSV!H81+Taostats_CSV!R81=0) -> FALSE | T81: =AND(NOT(S81),OR(NOT(Q81),R81=1)) -> TRUE | U81: {=AND(T81,OR(O81-N81>1,P81>1,ISERROR(A81:P81)))} -> FALSE | W81: =MATCH(K81&$W$2,Taostats_CSV!$X$3:$X$1167,0) -> 79 | X81: =VALUE(D81) -> 50 | Y81: =VALUE(F81) -> #VALUE! | Z81: =VALUE(H81) -> 0.000135263
A82: =MID(Taostats_CSV!C82,6,2)&"/"&MID(Taostats_CSV!C82,9,2)&"/"&LEFT(Taostats_CSV!C82,4)&" "&MID(Taostats_CSV!C82,12,8) -> 03/04/2025 16:57:12 | C82: =IF(Q82,OFFSET(Taostats_CSV!$E$1,MATCH(K82&D$1,Taostats_CSV!$X:$X,0)-1,0),IF(Taostats_CSV!F82="fee","",IF(VALUE(Taostats_CSV!G82)>0,Taostats_CSV!E82,""))) -> TAO | D82: =IF(Q82,OFFSET(Taostats_CSV!$G$1,MATCH(K82&D$1,Taostats_CSV!$X:$X,0)-1,0),IF(Taostats_CSV!F82="fee","",IF(VALUE(Taostats_CSV!G82)>0,Taostats_CSV!G82,""))) -> 50 | E82: =IF(AND(Q82,P82>0),OFFSET(Taostats_CSV!$E$1,MATCH(K82&F$1,Taostats_CSV!$X:$X,0)-1,0),IF(LEN(F82)>0,Taostats_CSV!E82,"")) | F82: =TRIM(IF(AND(Q82,P82>0),OFFSET(Taostats_CSV!$H$1,MATCH(K82&F$1,Taostats_CSV!$X:$X,0)-1,0),IF(LEN(Taostats_CSV!H82)>0,Taostats_CSV!H82,Taostats_CSV!R82))) | G82: =IF(AND(Q82,N82=1),OFFSET(Taostats_CSV!$E$1,MATCH(K82&H$1,Taostats_CSV!$X:$X,0)-1,0),IF(Taostats_CSV!F82="fee",Taostats_CSV!E82,"")) -> TAO | H82: =IF(AND(Q82,N82=1),OFFSET(Taostats_CSV!$G$1,MATCH(K82&H$1,Taostats_CSV!$X:$X,0)-1,0),IF(Taostats_CSV!F82="fee",Taostats_CSV!G82,"")) -> 0.000135263 | I82: =IF(AND(LEN(K82)=0,LEN(F82)>0),"Income",IF(AND(O82>0,P82>0,C82<>E82),"Trade",IF(AND(NOT(Q82),Taostats_CSV!F82="fee"),'READ ME'!$C$5,""))) | J82: =SUBSTITUTE(IF(LEN(I82)=0,Taostats_CSV!F82&" "&Taostats_CSV!J82,IF(I82="Cost","Extrinsic fee","")),"_"," ") -> transfer out 5HbnKZMzGk3GT3mpWZgKuQHq3CC8LeW2tbNq1FkBLQhzUX6L | K82: =TRIM(IF(LEN(Taostats_CSV!I82)>0,Taostats_CSV!I82,"")) -> 5055718-0007 | L82: =IF(Taostats_CSV!E82<>"TAO",IF(LEN(F82)>0,F82,IF(LEN(D82)>0,D82,0))*Taostats_CSV!P82,"") | M82: =IF(LEN(L82)>0,"USD","") | N82: =COUNTIF(Taostats_CSV!$X:$X,Taostats_CSV!$I82&N$1) -> 1 | O82: =COUNTIF(Taostats_CSV!$X:$X,Taostats_CSV!$I82&O$1) -> 1 | P82: =COUNTIF(Taostats_CSV!$X:$X,Taostats_CSV!$I82&P$1) -> 0 | Q82: =AND(O82<=1,N82<=1,P82<=1,O82+N82+P82>=2) -> TRUE | R82: =IF(LEN(K82)>0,COUNTIF($K$3:K82,K82),FALSE) -> 2 | S82: =IF(Taostats_CSV!A82=Taostats_CSV!$A$2,TRUE,Taostats_CSV!G82+Taostats_CSV!H82+Taostats_CSV!R82=0) -> FALSE | T82: =AND(NOT(S82),OR(NOT(Q82),R82=1)) -> FALSE | U82: {=AND(T82,OR(O82-N82>1,P82>1,ISERROR(A82:P82)))} -> FALSE | W82: =MATCH(K82&$W$2,Taostats_CSV!$X$3:$X$1167,0) -> 79 | X82: =VALUE(D82) -> 50 | Y82: =VALUE(F82) -> #VALUE! | Z82: =VALUE(H82) -> 0.000135263
A83: =MID(Taostats_CSV!C83,6,2)&"/"&MID(Taostats_CSV!C83,9,2)&"/"&LEFT(Taostats_CSV!C83,4)&" "&MID(Taostats_CSV!C83,12,8) -> 03/04/2025 23:59:48 | C83: =IF(Q83,OFFSET(Taostats_CSV!$E$1,MATCH(K83&D$1,Taostats_CSV!$X:$X,0)-1,0),IF(Taostats_CSV!F83="fee",IF(VALUE(Taostats_CSV!G83)>0,Taostats_CSV!E83,""),"")) | D83: =IF(Q83,OFFSET(Taostats_CSV!$G$1,MATCH(K83&D$1,Taostats_CSV!$X:$X,0)-1,0),IF(Taostats_CSV!F83="fee",IF(VALUE(Taostats_CSV!G83)>0,Taostats_CSV!G83,""),"")) | E83: =IF(AND(Q83,P83>0),OFFSET(Taostats_CSV!$E$1,MATCH(K83&F$1,Taostats_CSV!$X:$X,0)-1,0),IF(LEN(F83)>0,Taostats_CSV!E83,"")) -> TAO | F83: =TRIM(IF(AND(Q83,P83>0),OFFSET(Taostats_CSV!$H$1,MATCH(K83&F$1,Taostats_CSV!$X:$X,0)-1,0),IF(LEN(Taostats_CSV!H83)>0,Taostats_CSV!H83,Taostats_CSV!R83))) -> 0.101763446 | G83: =IF(AND(Q83,N83=1),OFFSET(Taostats_CSV!$E$1,MATCH(K83&H$1,Taostats_CSV!$X:$X,0)-1,0),"") | H83: =IF(AND(Q83,N83=1),OFFSET(Taostats_CSV!$G$1,MATCH(K83&H$1,Taostats_CSV!$X:$X,0)-1,0),"") | I83: =IF(AND(LEN(K83)=0,LEN(F83)>0),"Income",IF(AND(O83>0,P83>0,C83<>E83),"Trade",IF(AND(NOT(Q83),Taostats_CSV!F83="fee"),'READ ME'!$C$5,""))) -> Income | J83: =SUBSTITUTE(IF(LEN(I83)=0,Taostats_CSV!F83&" "&Taostats_CSV!J83,IF(I83="Cost","Extrinsic fee","")),"_"," ") | K83: =TRIM(IF(LEN(Taostats_CSV!I83)>0,Taostats_CSV!I83,"")) | L83: =IF(Taostats_CSV!E83<>"TAO",IF(LEN(F83)>0,F83,IF(LEN(D83)>0,D83,0))*Taostats_CSV!P83,"") | M83: =IF(LEN(L83)>0,"USD","") | N83: =COUNTIF(Taostats_CSV!$X:$X,Taostats_CSV!$I83&N$1) -> 0 | O83: =COUNTIF(Taostats_CSV!$X:$X,Taostats_CSV!$I83&O$1) -> 0 | P83: =COUNTIF(Taostats_CSV!$X:$X,Taostats_CSV!$I83&P$1) -> 0 | Q83: =AND(O83<=1,N83<=1,P83<=1,O83+N83+P83>=2) -> FALSE | R83: =IF(LEN(K83)>0,COUNTIF($K$3:K83,K83),FALSE) -> FALSE | S83: =IF(Taostats_CSV!A83=Taostats_CSV!$A$2,TRUE,Taostats_CSV!G83+Taostats_CSV!H83+Taostats_CSV!R83=0) -> FALSE | T83: =AND(NOT(S83),OR(NOT(Q83),R83=1)) -> TRUE | U83: {=AND(T83,OR(O83-N83>1,P83>1,ISERROR(A83:P83)))} -> FALSE | W83: =MATCH(K83&$W$2,Taostats_CSV!$X$3:$X$1167,0) -> #N/A | X83: =VALUE(D83) -> #VALUE! | Y83: =VALUE(F83) -> 0.10176345 | Z83: =VALUE(H83) -> #VALUE!
A84: =MID(Taostats_CSV!C84,6,2)&"/"&MID(Taostats_CSV!C84,9,2)&"/"&LEFT(Taostats_CSV!C84,4)&" "&MID(Taostats_CSV!C84,12,8) -> 03/05/2025 23:59:48 | C84: =IF(Q84,OFFSET(Taostats_CSV!$E$1,MATCH(K84&D$1,Taostats_CSV!$X:$X,0)-1,0),IF(Taostats_CSV!F84="fee",IF(VALUE(Taostats_CSV!G84)>0,Taostats_CSV!E84,""),"")) | D84: =IF(Q84,OFFSET(Taostats_CSV!$G$1,MATCH(K84&D$1,Taostats_CSV!$X:$X,0)-1,0),IF(Taostats_CSV!F84="fee",IF(VALUE(Taostats_CSV!G84)>0,Taostats_CSV!G84,""),"")) | E84: =IF(AND(Q84,P84>0),OFFSET(Taostats_CSV!$E$1,MATCH(K84&F$1,Taostats_CSV!$X:$X,0)-1,0),IF(LEN(F84)>0,Taostats_CSV!E84,"")) -> TAO | F84: =TRIM(IF(AND(Q84,P84>0),OFFSET(Taostats_CSV!$H$1,MATCH(K84&F$1,Taostats_CSV!$X:$X,0)-1,0),IF(LEN(Taostats_CSV!H84)>0,Taostats_CSV!H84,Taostats_CSV!R84))) -> 0.063845141 | G84: =IF(AND(Q84,N84=1),OFFSET(Taostats_CSV!$E$1,MATCH(K84&H$1,Taostats_CSV!$X:$X,0)-1,0),"") | H84: =IF(AND(Q84,N84=1),OFFSET(Taostats_CSV!$G$1,MATCH(K84&H$1,Taostats_CSV!$X:$X,0)-1,0),"") | I84: =IF(AND(LEN(K84)=0,LEN(F84)>0),"Income",IF(AND(O84>0,P84>0,C84<>E84),"Trade",IF(AND(NOT(Q84),Taostats_CSV!F84="fee"),'READ ME'!$C$5,""))) -> Income | J84: =SUBSTITUTE(IF(LEN(I84)=0,Taostats_CSV!F84&" "&Taostats_CSV!J84,IF(I84="Cost","Extrinsic fee","")),"_"," ") | K84: =TRIM(IF(LEN(Taostats_CSV!I84)>0,Taostats_CSV!I84,"")) | L84: =IF(Taostats_CSV!E84<>"TAO",IF(LEN(F84)>0,F84,IF(LEN(D84)>0,D84,0))*Taostats_CSV!P84,"") | M84: =IF(LEN(L84)>0,"USD","") | N84: =COUNTIF(Taostats_CSV!$X:$X,Taostats_CSV!$I84&N$1) -> 0 | O84: =COUNTIF(Taostats_CSV!$X:$X,Taostats_CSV!$I84&O$1) -> 0 | P84: =COUNTIF(Taostats_CSV!$X:$X,Taostats_CSV!$I84&P$1) -> 0 | Q84: =AND(O84<=1,N84<=1,P84<=1,O84+N84+P84>=2) -> FALSE | R84: =IF(LEN(K84)>0,COUNTIF($K$3:K84,K84),FALSE) -> FALSE | S84: =IF(Taostats_CSV!A84=Taostats_CSV!$A$2,TRUE,Taostats_CSV!G84+Taostats_CSV!H84+Taostats_CSV!R84=0) -> FALSE | T84: =AND(NOT(S84),OR(NOT(Q84),R84=1)) -> TRUE | U84: {=AND(T84,OR(O84-N84>1,P84>1,ISERROR(A84:P84)))} -> FALSE | W84: =MATCH(K84&$W$2,Taostats_CSV!$X$3:$X$1167,0) -> #N/A | X84: =VALUE(D84) -> #VALUE! | Y84: =VALUE(F84) -> 0.063845141 | Z84: =VALUE(H84) -> #VALUE!
A85: =MID(Taostats_CSV!C85,6,2)&"/"&MID(Taostats_CSV!C85,9,2)&"/"&LEFT(Taostats_CSV!C85,4)&" "&MID(Taostats_CSV!C85,12,8) -> 03/06/2025 23:59:48 | C85: =IF(Q85,OFFSET(Taostats_CSV!$E$1,MATCH(K85&D$1,Taostats_CSV!$X:$X,0)-1,0),IF(Taostats_CSV!F85="fee",IF(VALUE(Taostats_CSV!G85)>0,Taostats_CSV!E85,""),"")) | D85: =IF(Q85,OFFSET(Taostats_CSV!$G$1,MATCH(K85&D$1,Taostats_CSV!$X:$X,0)-1,0),IF(Taostats_CSV!F85="fee",IF(VALUE(Taostats_CSV!G85)>0,Taostats_CSV!G85,""),"")) | E85: =IF(AND(Q85,P85>0),OFFSET(Taostats_CSV!$E$1,MATCH(K85&F$1,Taostats_CSV!$X:$X,0)-1,0),IF(LEN(F85)>0,Taostats_CSV!E85,"")) -> TAO | F85: =TRIM(IF(AND(Q85,P85>0),OFFSET(Taostats_CSV!$H$1,MATCH(K85&F$1,Taostats_CSV!$X:$X,0)-1,0),IF(LEN(Taostats_CSV!H85)>0,Taostats_CSV!H85,Taostats_CSV!R85))) -> 0.062255145 | G85: =IF(AND(Q85,N85=1),OFFSET(Taostats_CSV!$E$1,MATCH(K85&H$1,Taostats_CSV!$X:$X,0)-1,0),"") | H85: =IF(AND(Q85,N85=1),OFFSET(Taostats_CSV!$G$1,MATCH(K85&H$1,Taostats_CSV!$X:$X,0)-1,0),"") | I85: =IF(AND(LEN(K85)=0,LEN(F85)>0),"Income",IF(AND(O85>0,P85>0,C85<>E85),"Trade",IF(AND(NOT(Q85),Taostats_CSV!F85="fee"),'READ ME'!$C$5,""))) -> Income | J85: =SUBSTITUTE(IF(LEN(I85)=0,Taostats_CSV!F85&" "&Taostats_CSV!J85,IF(I85="Cost","Extrinsic fee","")),"_"," ") | K85: =TRIM(IF(LEN(Taostats_CSV!I85)>0,Taostats_CSV!I85,"")) | L85: =IF(Taostats_CSV!E85<>"TAO",IF(LEN(F85)>0,F85,IF(LEN(D85)>0,D85,0))*Taostats_CSV!P85,"") | M85: =IF(LEN(L85)>0,"USD","") | N85: =COUNTIF(Taostats_CSV!$X:$X,Taostats_CSV!$I85&N$1) -> 0 | O85: =COUNTIF(Taostats_CSV!$X:$X,Taostats_CSV!$I85&O$1) -> 0 | P85: =COUNTIF(Taostats_CSV!$X:$X,Taostats_CSV!$I85&P$1) -> 0 | Q85: =AND(O85<=1,N85<=1,P85<=1,O85+N85+P85>=2) -> FALSE | R85: =IF(LEN(K85)>0,COUNTIF($K$3:K85,K85),FALSE) -> FALSE | S85: =IF(Taostats_CSV!A85=Taostats_CSV!$A$2,TRUE,Taostats_CSV!G85+Taostats_CSV!H85+Taostats_CSV!R85=0) -> FALSE | T85: =AND(NOT(S85),OR(NOT(Q85),R85=1)) -> TRUE | U85: {=AND(T85,OR(O85-N85>1,P85>1,ISERROR(A85:P85)))} -> FALSE | W85: =MATCH(K85&$W$2,Taostats_CSV!$X$3:$X$1167,0) -> #N/A | X85: =VALUE(D85) -> #VALUE! | Y85: =VALUE(F85) -> 0.062255145 | Z85: =VALUE(H85) -> #VALUE!
A86: =MID(Taostats_CSV!C86,6,2)&"/"&MID(Taostats_CSV!C86,9,2)&"/"&LEFT(Taostats_CSV!C86,4)&" "&MID(Taostats_CSV!C86,12,8) -> 03/07/2025 23:59:48 | C86: =IF(Q86,OFFSET(Taostats_CSV!$E$1,MATCH(K86&D$1,Taostats_CSV!$X:$X,0)-1,0),IF(Taostats_CSV!F86="fee",IF(VALUE(Taostats_CSV!G86)>0,Taostats_CSV!E86,""),"")) | D86: =IF(Q86,OFFSET(Taostats_CSV!$G$1,MATCH(K86&D$1,Taostats_CSV!$X:$X,0)-1,0),IF(Taostats_CSV!F86="fee",IF(VALUE(Taostats_CSV!G86)>0,Taostats_CSV!G86,""),"")) | E86: =IF(AND(Q86,P86>0),OFFSET(Taostats_CSV!$E$1,MATCH(K86&F$1,Taostats_CSV!$X:$X,0)-1,0),IF(LEN(F86)>0,Taostats_CSV!E86,"")) -> TAO | F86: =TRIM(IF(AND(Q86,P86>0),OFFSET(Taostats_CSV!$H$1,MATCH(K86&F$1,Taostats_CSV!$X:$X,0)-1,0),IF(LEN(Taostats_CSV!H86)>0,Taostats_CSV!H86,Taostats_CSV!R86))) -> 0.06197379 | G86: =IF(AND(Q86,N86=1),OFFSET(Taostats_CSV!$E$1,MATCH(K86&H$1,Taostats_CSV!$X:$X,0)-1,0),"") | H86: =IF(AND(Q86,N86=1),OFFSET(Taostats_CSV!$G$1,MATCH(K86&H$1,Taostats_CSV!$X:$X,0)-1,0),"") | I86: =IF(AND(LEN(K86)=0,LEN(F86)>0),"Income",IF(AND(O86>0,P86>0,C86<>E86),"Trade",IF(AND(NOT(Q86),Taostats_CSV!F86="fee"),'READ ME'!$C$5,""))) -> Income | J86: =SUBSTITUTE(IF(LEN(I86)=0,Taostats_CSV!F86&" "&Taostats_CSV!J86,IF(I86="Cost","Extrinsic fee","")),"_"," ") | K86: =TRIM(IF(LEN(Taostats_CSV!I86)>0,Taostats_CSV!I86,"")) | L86: =IF(Taostats_CSV!E86<>"TAO",IF(LEN(F86)>0,F86,IF(LEN(D86)>0,D86,0))*Taostats_CSV!P86,"") | M86: =IF(LEN(L86)>0,"USD","") | N86: =COUNTIF(Taostats_CSV!$X:$X,Taostats_CSV!$I86&N$1) -> 0 | O86: =COUNTIF(Taostats_CSV!$X:$X,Taostats_CSV!$I86&O$1) -> 0 | P86: =COUNTIF(Taostats_CSV!$X:$X,Taostats_CSV!$I86&P$1) -> 0 | Q86: =AND(O86<=1,N86<=1,P86<=1,O86+N86+P86>=2) -> FALSE | R86: =IF(LEN(K86)>0,COUNTIF($K$3:K86,K86),FALSE) -> FALSE | S86: =IF(Taostats_CSV!A86=Taostats_CSV!$A$2,TRUE,Taostats_CSV!G86+Taostats_CSV!H86+Taostats_CSV!R86=0) -> FALSE | T86: =AND(NOT(S86),OR(NOT(Q86),R86=1)) -> TRUE | U86: {=AND(T86,OR(O86-N86>1,P86>1,ISERROR(A86:P86)))} -> FALSE | W86: =MATCH(K86&$W$2,Taostats_CSV!$X$3:$X$1167,0) -> #N/A | X86: =VALUE(D86) -> #VALUE! | Y86: =VALUE(F86) -> 0.06197379 | Z86: =VALUE(H86) -> #VALUE!
A87: =MID(Taostats_CSV!C87,6,2)&"/"&MID(Taostats_CSV!C87,9,2)&"/"&LEFT(Taostats_CSV!C87,4)&" "&MID(Taostats_CSV!C87,12,8) -> 03/08/2025 23:59:48 | C87: =IF(Q87,OFFSET(Taostats_CSV!$E$1,MATCH(K87&D$1,Taostats_CSV!$X:$X,0)-1,0),IF(Taostats_CSV!F87="fee",IF(VALUE(Taostats_CSV!G87)>0,Taostats_CSV!E87,""),"")) | D87: =IF(Q87,OFFSET(Taostats_CSV!$G$1,MATCH(K87&D$1,Taostats_CSV!$X:$X,0)-1,0),IF(Taostats_CSV!F87="fee",IF(VALUE(Taostats_CSV!G87)>0,Taostats_CSV!G87,""),"")) | E87: =IF(AND(Q87,P87>0),OFFSET(Taostats_CSV!$E$1,MATCH(K87&F$1,Taostats_CSV!$X:$X,0)-1,0),IF(LEN(F87)>0,Taostats_CSV!E87,"")) -> TAO | F87: =TRIM(IF(AND(Q87,P87>0),OFFSET(Taostats_CSV!$H$1,MATCH(K87&F$1,Taostats_CSV!$X:$X,0)-1,0),IF(LEN(Taostats_CSV!H87)>0,Taostats_CSV!H87,Taostats_CSV!R87))) -> 0.061367857 | G87: =IF(AND(Q87,N87=1),OFFSET(Taostats_CSV!$E$1,MATCH(K87&H$1,Taostats_CSV!$X:$X,0)-1,0),"") | H87: =IF(AND(Q87,N87=1),OFFSET(Taostats_CSV!$G$1,MATCH(K87&H$1,Taostats_CSV!$X:$X,0)-1,0),"") | I87: =IF(AND(LEN(K87)=0,LEN(F87)>0),"Income",IF(AND(O87>0,P87>0,C87<>E87),"Trade",IF(AND(NOT(Q87),Taostats_CSV!F87="fee"),'READ ME'!$C$5,""))) -> Income | J87: =SUBSTITUTE(IF(LEN(I87)=0,Taostats_CSV!F87&" "&Taostats_CSV!J87,IF(I87="Cost","Extrinsic fee","")),"_"," ") | K87: =TRIM(IF(LEN(Taostats_CSV!I87)>0,Taostats_CSV!I87,"")) | L87: =IF(Taostats_CSV!E87<>"TAO",IF(LEN(F87)>0,F87,IF(LEN(D87)>0,D87,0))*Taostats_CSV!P87,"") | M87: =IF(LEN(L87)>0,"USD","") | N87: =COUNTIF(Taostats_CSV!$X:$X,Taostats_CSV!$I87&N$1) -> 0 | O87: =COUNTIF(Taostats_CSV!$X:$X,Taostats_CSV!$I87&O$1) -> 0 | P87: =COUNTIF(Taostats_CSV!$X:$X,Taostats_CSV!$I87&P$1) -> 0 | Q87: =AND(O87<=1,N87<=1,P87<=1,O87+N87+P87>=2) -> FALSE | R87: =IF(LEN(K87)>0,COUNTIF($K$3:K87,K87),FALSE) -> FALSE | S87: =IF(Taostats_CSV!A87=Taostats_CSV!$A$2,TRUE,Taostats_CSV!G87+Taostats_CSV!H87+Taostats_CSV!R87=0) -> FALSE | T87: =AND(NOT(S87),OR(NOT(Q87),R87=1)) -> TRUE | U87: {=AND(T87,OR(O87-N87>1,P87>1,ISERROR(A87:P87)))} -> FALSE | W87: =MATCH(K87&$W$2,Taostats_CSV!$X$3:$X$1167,0) -> #N/A | X87: =VALUE(D87) -> #VALUE! | Y87: =VALUE(F87) -> 0.061367857 | Z87: =VALUE(H87) -> #VALUE!
A88: =MID(Taostats_CSV!C88,6,2)&"/"&MID(Taostats_CSV!C88,9,2)&"/"&LEFT(Taostats_CSV!C88,4)&" "&MID(Taostats_CSV!C88,12,8) -> 03/09/2025 23:59:48 | C88: =IF(Q88,OFFSET(Taostats_CSV!$E$1,MATCH(K88&D$1,Taostats_CSV!$X:$X,0)-1,0),IF(Taostats_CSV!F88="fee",IF(VALUE(Taostats_CSV!G88)>0,Taostats_CSV!E88,""),"")) | D88: =IF(Q88,OFFSET(Taostats_CSV!$G$1,MATCH(K88&D$1,Taostats_CSV!$X:$X,0)-1,0),IF(Taostats_CSV!F88="fee",IF(VALUE(Taostats_CSV!G88)>0,Taostats_CSV!G88,""),"")) | E88: =IF(AND(Q88,P88>0),OFFSET(Taostats_CSV!$E$1,MATCH(K88&F$1,Taostats_CSV!$X:$X,0)-1,0),IF(LEN(F88)>0,Taostats_CSV!E88,"")) -> TAO | F88: =TRIM(IF(AND(Q88,P88>0),OFFSET(Taostats_CSV!$H$1,MATCH(K88&F$1,Taostats_CSV!$X:$X,0)-1,0),IF(LEN(Taostats_CSV!H88)>0,Taostats_CSV!H88,Taostats_CSV!R88))) -> 0.061593839 | G88: =IF(AND(Q88,N88=1),OFFSET(Taostats_CSV!$E$1,MATCH(K88&H$1,Taostats_CSV!$X:$X,0)-1,0),"") | H88: =IF(AND(Q88,N88=1),OFFSET(Taostats_CSV!$G$1,MATCH(K88&H$1,Taostats_CSV!$X:$X,0)-1,0),"") | I88: =IF(AND(LEN(K88)=0,LEN(F88)>0),"Income",IF(AND(O88>0,P88>0,C88<>E88),"Trade",IF(AND(NOT(Q88),Taostats_CSV!F88="fee"),'READ ME'!$C$5,""))) -> Income | J88: =SUBSTITUTE(IF(LEN(I88)=0,Taostats_CSV!F88&" "&Taostats_CSV!J88,IF(I88="Cost","Extrinsic fee","")),"_"," ") | K88: =TRIM(IF(LEN(Taostats_CSV!I88)>0,Taostats_CSV!I88,"")) | L88: =IF(Taostats_CSV!E88<>"TAO",IF(LEN(F88)>0,F88,IF(LEN(D88)>0,D88,0))*Taostats_CSV!P88,"") | M88: =IF(LEN(L88)>0,"USD","") | N88: =COUNTIF(Taostats_CSV!$X:$X,Taostats_CSV!$I88&N$1) -> 0 | O88: =COUNTIF(Taostats_CSV!$X:$X,Taostats_CSV!$I88&O$1) -> 0 | P88: =COUNTIF(Taostats_CSV!$X:$X,Taostats_CSV!$I88&P$1) -> 0 | Q88: =AND(O88<=1,N88<=1,P88<=1,O88+N88+P88>=2) -> FALSE | R88: =IF(LEN(K88)>0,COUNTIF($K$3:K88,K88),FALSE) -> FALSE | S88: =IF(Taostats_CSV!A88=Taostats_CSV!$A$2,TRUE,Taostats_CSV!G88+Taostats_CSV!H88+Taostats_CSV!R88=0) -> FALSE | T88: =AND(NOT(S88),OR(NOT(Q88),R88=1)) -> TRUE | U88: {=AND(T88,OR(O88-N88>1,P88>1,ISERROR(A88:P88)))} -> FALSE | W88: =MATCH(K88&$W$2,Taostats_CSV!$X$3:$X$1167,0) -> #N/A | X88: =VALUE(D88) -> #VALUE! | Y88: =VALUE(F88) -> 0.061593839 | Z88: =VALUE(H88) -> #VALUE!
A89: =MID(Taostats_CSV!C89,6,2)&"/"&MID(Taostats_CSV!C89,9,2)&"/"&LEFT(Taostats_CSV!C89,4)&" "&MID(Taostats_CSV!C89,12,8) -> 03/10/2025 23:59:48 | C89: =IF(Q89,OFFSET(Taostats_CSV!$E$1,MATCH(K89&D$1,Taostats_CSV!$X:$X,0)-1,0),IF(Taostats_CSV!F89="fee",IF(VALUE(Taostats_CSV!G89)>0,Taostats_CSV!E89,""),"")) | D89: =IF(Q89,OFFSET(Taostats_CSV!$G$1,MATCH(K89&D$1,Taostats_CSV!$X:$X,0)-1,0),IF(Taostats_CSV!F89="fee",IF(VALUE(Taostats_CSV!G89)>0,Taostats_CSV!G89,""),"")) | E89: =IF(AND(Q89,P89>0),OFFSET(Taostats_CSV!$E$1,MATCH(K89&F$1,Taostats_CSV!$X:$X,0)-1,0),IF(LEN(F89)>0,Taostats_CSV!E89,"")) -> TAO | F89: =TRIM(IF(AND(Q89,P89>0),OFFSET(Taostats_CSV!$H$1,MATCH(K89&F$1,Taostats_CSV!$X:$X,0)-1,0),IF(LEN(Taostats_CSV!H89)>0,Taostats_CSV!H89,Taostats_CSV!R89))) -> 0.057860691 | G89: =IF(AND(Q89,N89=1),OFFSET(Taostats_CSV!$E$1,MATCH(K89&H$1,Taostats_CSV!$X:$X,0)-1,0),"") | H89: =IF(AND(Q89,N89=1),OFFSET(Taostats_CSV!$G$1,MATCH(K89&H$1,Taostats_CSV!$X:$X,0)-1,0),"") | I89: =IF(AND(LEN(K89)=0,LEN(F89)>0),"Income",IF(AND(O89>0,P89>0,C89<>E89),"Trade",IF(AND(NOT(Q89),Taostats_CSV!F89="fee"),'READ ME'!$C$5,""))) -> Income | J89: =SUBSTITUTE(IF(LEN(I89)=0,Taostats_CSV!F89&" "&Taostats_CSV!J89,IF(I89="Cost","Extrinsic fee","")),"_"," ") | K89: =TRIM(IF(LEN(Taostats_CSV!I89)>0,Taostats_CSV!I89,"")) | L89: =IF(Taostats_CSV!E89<>"TAO",IF(LEN(F89)>0,F89,IF(LEN(D89)>0,D89,0))*Taostats_CSV!P89,"") | M89: =IF(LEN(L89)>0,"USD","") | N89: =COUNTIF(Taostats_CSV!$X:$X,Taostats_CSV!$I89&N$1) -> 0 | O89: =COUNTIF(Taostats_CSV!$X:$X,Taostats_CSV!$I89&O$1) -> 0 | P89: =COUNTIF(Taostats_CSV!$X:$X,Taostats_CSV!$I89&P$1) -> 0 | Q89: =AND(O89<=1,N89<=1,P89<=1,O89+N89+P89>=2) -> FALSE | R89: =IF(LEN(K89)>0,COUNTIF($K$3:K89,K89),FALSE) -> FALSE | S89: =IF(Taostats_CSV!A89=Taostats_CSV!$A$2,TRUE,Taostats_CSV!G89+Taostats_CSV!H89+Taostats_CSV!R89=0) -> FALSE | T89: =AND(NOT(S89),OR(NOT(Q89),R89=1)) -> TRUE | U89: {=AND(T89,OR(O89-N89>1,P89>1,ISERROR(A89:P89)))} -> FALSE | W89: =MATCH(K89&$W$2,Taostats_CSV!$X$3:$X$1167,0) -> #N/A | X89: =VALUE(D89) -> #VALUE! | Y89: =VALUE(F89) -> 0.057860691 | Z89: =VALUE(H89) -> #VALUE!
A90: =MID(Taostats_CSV!C90,6,2)&"/"&MID(Taostats_CSV!C90,9,2)&"/"&LEFT(Taostats_CSV!C90,4)&" "&MID(Taostats_CSV!C90,12,8) -> 03/11/2025 23:59:48 | C90: =IF(Q90,OFFSET(Taostats_CSV!$E$1,MATCH(K90&D$1,Taostats_CSV!$X:$X,0)-1,0),IF(Taostats_CSV!F90="fee",IF(VALUE(Taostats_CSV!G90)>0,Taostats_CSV!E90,""),"")) | D90: =IF(Q90,OFFSET(Taostats_CSV!$G$1,MATCH(K90&D$1,Taostats_CSV!$X:$X,0)-1,0),IF(Taostats_CSV!F90="fee",IF(VALUE(Taostats_CSV!G90)>0,Taostats_CSV!G90,""),"")) | E90: =IF(AND(Q90,P90>0),OFFSET(Taostats_CSV!$E$1,MATCH(K90&F$1,Taostats_CSV!$X:$X,0)-1,0),IF(LEN(F90)>0,Taostats_CSV!E90,"")) -> TAO | F90: =TRIM(IF(AND(Q90,P90>0),OFFSET(Taostats_CSV!$H$1,MATCH(K90&F$1,Taostats_CSV!$X:$X,0)-1,0),IF(LEN(Taostats_CSV!H90)>0,Taostats_CSV!H90,Taostats_CSV!R90))) -> 0.052396977 | G90: =IF(AND(Q90,N90=1),OFFSET(Taostats_CSV!$E$1,MATCH(K90&H$1,Taostats_CSV!$X:$X,0)-1,0),"") | H90: =IF(AND(Q90,N90=1),OFFSET(Taostats_CSV!$G$1,MATCH(K90&H$1,Taostats_CSV!$X:$X,0)-1,0),"") | I90: =IF(AND(LEN(K90)=0,LEN(F90)>0),"Income",IF(AND(O90>0,P90>0,C90<>E90),"Trade",IF(AND(NOT(Q90),Taostats_CSV!F90="fee"),'READ ME'!$C$5,""))) -> Income | J90: =SUBSTITUTE(IF(LEN(I90)=0,Taostats_CSV!F90&" "&Taostats_CSV!J90,IF(I90="Cost","Extrinsic fee","")),"_"," ") | K90: =TRIM(IF(LEN(Taostats_CSV!I90)>0,Taostats_CSV!I90,"")) | L90: =IF(Taostats_CSV!E90<>"TAO",IF(LEN(F90)>0,F90,IF(LEN(D90)>0,D90,0))*Taostats_CSV!P90,"") | M90: =IF(LEN(L90)>0,"USD","") | N90: =COUNTIF(Taostats_CSV!$X:$X,Taostats_CSV!$I90&N$1) -> 0 | O90: =COUNTIF(Taostats_CSV!$X:$X,Taostats_CSV!$I90&O$1) -> 0 | P90: =COUNTIF(Taostats_CSV!$X:$X,Taostats_CSV!$I90&P$1) -> 0 | Q90: =AND(O90<=1,N90<=1,P90<=1,O90+N90+P90>=2) -> FALSE | R90: =IF(LEN(K90)>0,COUNTIF($K$3:K90,K90),FALSE) -> FALSE | S90: =IF(Taostats_CSV!A90=Taostats_CSV!$A$2,TRUE,Taostats_CSV!G90+Taostats_CSV!H90+Taostats_CSV!R90=0) -> FALSE | T90: =AND(NOT(S90),OR(NOT(Q90),R90=1)) -> TRUE | U90: {=AND(T90,OR(O90-N90>1,P90>1,ISERROR(A90:P90)))} -> FALSE | W90: =MATCH(K90&$W$2,Taostats_CSV!$X$3:$X$1167,0) -> #N/A | X90: =VALUE(D90) -> #VALUE! | Y90: =VALUE(F90) -> 0.052396977 | Z90: =VALUE(H90) -> #VALUE!
A91: =MID(Taostats_CSV!C91,6,2)&"/"&MID(Taostats_CSV!C91,9,2)&"/"&LEFT(Taostats_CSV!C91,4)&" "&MID(Taostats_CSV!C91,12,8) -> 03/12/2025 23:59:48 | C91: =IF(Q91,OFFSET(Taostats_CSV!$E$1,MATCH(K91&D$1,Taostats_CSV!$X:$X,0)-1,0),IF(Taostats_CSV!F91="fee",IF(VALUE(Taostats_CSV!G91)>0,Taostats_CSV!E91,""),"")) | D91: =IF(Q91,OFFSET(Taostats_CSV!$G$1,MATCH(K91&D$1,Taostats_CSV!$X:$X,0)-1,0),IF(Taostats_CSV!F91="fee",IF(VALUE(Taostats_CSV!G91)>0,Taostats_CSV!G91,""),"")) | E91: =IF(AND(Q91,P91>0),OFFSET(Taostats_CSV!$E$1,MATCH(K91&F$1,Taostats_CSV!$X:$X,0)-1,0),IF(LEN(F91)>0,Taostats_CSV!E91,"")) -> TAO | F91: =TRIM(IF(AND(Q91,P91>0),OFFSET(Taostats_CSV!$H$1,MATCH(K91&F$1,Taostats_CSV!$X:$X,0)-1,0),IF(LEN(Taostats_CSV!H91)>0,Taostats_CSV!H91,Taostats_CSV!R91))) -> 0.048289917 | G91: =IF(AND(Q91,N91=1),OFFSET(Taostats_CSV!$E$1,MATCH(K91&H$1,Taostats_CSV!$X:$X,0)-1,0),"") | H91: =IF(AND(Q91,N91=1),OFFSET(Taostats_CSV!$G$1,MATCH(K91&H$1,Taostats_CSV!$X:$X,0)-1,0),"") | I91: =IF(AND(LEN(K91)=0,LEN(F91)>0),"Income",IF(AND(O91>0,P91>0,C91<>E91),"Trade",IF(AND(NOT(Q91),Taostats_CSV!F91="fee"),'READ ME'!$C$5,""))) -> Income | J91: =SUBSTITUTE(IF(LEN(I91)=0,Taostats_CSV!F91&" "&Taostats_CSV!J91,IF(I91="Cost","Extrinsic fee","")),"_"," ") | K91: =TRIM(IF(LEN(Taostats_CSV!I91)>0,Taostats_CSV!I91,"")) | L91: =IF(Taostats_CSV!E91<>"TAO",IF(LEN(F91)>0,F91,IF(LEN(D91)>0,D91,0))*Taostats_CSV!P91,"") | M91: =IF(LEN(L91)>0,"USD","") | N91: =COUNTIF(Taostats_CSV!$X:$X,Taostats_CSV!$I91&N$1) -> 0 | O91: =COUNTIF(Taostats_CSV!$X:$X,Taostats_CSV!$I91&O$1) -> 0 | P91: =COUNTIF(Taostats_CSV!$X:$X,Taostats_CSV!$I91&P$1) -> 0 | Q91: =AND(O91<=1,N91<=1,P91<=1,O91+N91+P91>=2) -> FALSE | R91: =IF(LEN(K91)>0,COUNTIF($K$3:K91,K91),FALSE) -> FALSE | S91: =IF(Taostats_CSV!A91=Taostats_CSV!$A$2,TRUE,Taostats_CSV!G91+Taostats_CSV!H91+Taostats_CSV!R91=0) -> FALSE | T91: =AND(NOT(S91),OR(NOT(Q91),R91=1)) -> TRUE | U91: {=AND(T91,OR(O91-N91>1,P91>1,ISERROR(A91:P91)))} -> FALSE | W91: =MATCH(K91&$W$2,Taostats_CSV!$X$3:$X$1167,0) -> #N/A | X91: =VALUE(D91) -> #VALUE! | Y91: =VALUE(F91) -> 0.048289917 | Z91: =VALUE(H91) -> #VALUE!
